Workbook

Sheet Shiftlab
A1: Area Name | B1: District Name | C1: Store | D1: Employee | E1: Title | F1: Date | G1: Scheduled In | H1: Scheduled Out | I1: Actual In | J1: Actual Out | K1: Hours Scheduled | L1: Hours Worked | M1: Breaks | N1: Break Minutes | O1: Event | P1: Camera In | Q1: Camera Out | R1: Total Time | S1: Showroom Time | T1: Backroom Time | U1: Break | V1: Monitored
A2: Central | B2: DFW East | C2: Golden Triangle | D2: JYE PECHACEK | E2: MOBILE ASSOCIATE | F2: 46296 | G2: 0.39583333 | H2: 0.75 | I2: 0.401875 | J2: 0.73311343 | K2: 8 | L2: 7.3669444 | M2: 1 | N2: 34.966667 | O2: Early Clock Out | P2: {=_xlfn.XLOOKUP(1,(Rebiz!A:A=Table2[[#This Row],[Employee]])*(Rebiz!C:C=Table2[[#This Row],[Date]]),Rebiz!E:E,"")} -> 46296.403 | Q2: {=_xlfn.XLOOKUP(1,(Rebiz!A:A=Table2[[#This Row],[Employee]])*(Rebiz!C:C=Table2[[#This Row],[Date]]),Rebiz!F:F,"")} -> 46296.737 | R2: {=_xlfn.XLOOKUP(1,(Rebiz!A:A=Table2[[#This Row],[Employee]])*(Rebiz!C:C=Table2[[#This Row],[Date]]),Rebiz!G:G,"")} -> 7:36 | S2: {=_xlfn.XLOOKUP(1,(Rebiz!A:A=Table2[[#This Row],[Employee]])*(Rebiz!C:C=Table2[[#This Row],[Date]]),Rebiz!H:H,"")} -> 7:36 | T2: {=_xlfn.XLOOKUP(1,(Rebiz!A:A=Table2[[#This Row],[Employee]])*(Rebiz!C:C=Table2[[#This Row],[Date]]),Rebiz!I:I,"")} -> 0:0 | U2: {=_xlfn.XLOOKUP(1,(Rebiz!A:A=Table2[[#This Row],[Employee]])*(Rebiz!C:C=Table2[[#This Row],[Date]]),Rebiz!J:J,"")} -> 0:25 | V2: {=_xlfn.XLOOKUP(1,(Rebiz!A:A=Table2[[#This Row],[Employee]])*(Rebiz!C:C=Table2[[#This Row],[Date]]),Rebiz!K:K,"")} -> Y
A3: Central | B3: DFW North | C3: Seventh Ave | D3: SUZANNE REINA | E3: MOBILE ASSOCIATE | F3: 46296 | G3: 0.41666667 | H3: 0.75 | I3: 0.41469907 | J3: 0.73038194 | K3: 7.5 | L3: 6.7869444 | M3: 1 | N3: 47.366667 | O3: Early Clock Out | P3: {=_xlfn.XLOOKUP(1,(Rebiz!A:A=Table2[[#This Row],[Employee]])*(Rebiz!C:C=Table2[[#This Row],[Date]]),Rebiz!E:E,"")} | Q3: {=_xlfn.XLOOKUP(1,(Rebiz!A:A=Table2[[#This Row],[Employee]])*(Rebiz!C:C=Table2[[#This Row],[Date]]),Rebiz!F:F,"")} | R3: {=_xlfn.XLOOKUP(1,(Rebiz!A:A=Table2[[#This Row],[Employee]])*(Rebiz!C:C=Table2[[#This Row],[Date]]),Rebiz!G:G,"")} | S3: {=_xlfn.XLOOKUP(1,(Rebiz!A:A=Table2[[#This Row],[Employee]])*(Rebiz!C:C=Table2[[#This Row],[Date]]),Rebiz!H:H,"")} | T3: {=_xlfn.XLOOKUP(1,(Rebiz!A:A=Table2[[#This Row],[Employee]])*(Rebiz!C:C=Table2[[#This Row],[Date]]),Rebiz!I:I,"")} | U3: {=_xlfn.XLOOKUP(1,(Rebiz!A:A=Table2[[#This Row],[Employee]])*(Rebiz!C:C=Table2[[#This Row],[Date]]),Rebiz!J:J,"")} | V3: {=_xlfn.XLOOKUP(1,(Rebiz!A:A=Table2[[#This Row],[Employee]])*(Rebiz!C:C=Table2[[#This Row],[Date]]),Rebiz!K:K,"")}
A4: Central | B4: South TX/RGV | C4: Kingsville | D4: ROEL GARCIA | E4: MOBILE ASSOCIATE | F4: 46296 | G4: 0.45833333 | H4: 0.79166667 | I4: 0.46592593 | J4: 0.73820602 | K4: 7 | L4: 5.5266667 | M4: 1 | N4: 60.483333 | O4: Late Clock In, Early Clock Out | P4: {=_xlfn.XLOOKUP(1,(Rebiz!A:A=Table2[[#This Row],[Employee]])*(Rebiz!C:C=Table2[[#This Row],[Date]]),Rebiz!E:E,"")} -> 46296.467 | Q4: {=_xlfn.XLOOKUP(1,(Rebiz!A:A=Table2[[#This Row],[Employee]])*(Rebiz!C:C=Table2[[#This Row],[Date]]),Rebiz!F:F,"")} -> 46296.74 | R4: {=_xlfn.XLOOKUP(1,(Rebiz!A:A=Table2[[#This Row],[Employee]])*(Rebiz!C:C=Table2[[#This Row],[Date]]),Rebiz!G:G,"")} -> 6:33 | S4: {=_xlfn.XLOOKUP(1,(Rebiz!A:A=Table2[[#This Row],[Employee]])*(Rebiz!C:C=Table2[[#This Row],[Date]]),Rebiz!H:H,"")} -> 6:21 | T4: {=_xlfn.XLOOKUP(1,(Rebiz!A:A=Table2[[#This Row],[Employee]])*(Rebiz!C:C=Table2[[#This Row],[Date]]),Rebiz!I:I,"")} -> 0:12 | U4: {=_xlfn.XLOOKUP(1,(Rebiz!A:A=Table2[[#This Row],[Employee]])*(Rebiz!C:C=Table2[[#This Row],[Date]]),Rebiz!J:J,"")} -> 0:0 | V4: {=_xlfn.XLOOKUP(1,(Rebiz!A:A=Table2[[#This Row],[Employee]])*(Rebiz!C:C=Table2[[#This Row],[Date]]),Rebiz!K:K,"")} -> Y
A5: Central | B5: KS/OK | C5: Garth Brooks Blvd | D5: SILAS LITTLE | E5: MOBILE ASSOCIATE | F5: 46296 | G5: 0.5 | H5: 0.85416667 | I5: 0.51321759 | J5: 0.75796296 | K5: 8 | L5: 5.3672222 | M5: 1 | N5: 30.4 | O5: Late Clock In, Early Clock Out | P5: {=_xlfn.XLOOKUP(1,(Rebiz!A:A=Table2[[#This Row],[Employee]])*(Rebiz!C:C=Table2[[#This Row],[Date]]),Rebiz!E:E,"")} | Q5: {=_xlfn.XLOOKUP(1,(Rebiz!A:A=Table2[[#This Row],[Employee]])*(Rebiz!C:C=Table2[[#This Row],[Date]]),Rebiz!F:F,"")} | R5: {=_xlfn.XLOOKUP(1,(Rebiz!A:A=Table2[[#This Row],[Employee]])*(Rebiz!C:C=Table2[[#This Row],[Date]]),Rebiz!G:G,"")} | S5: {=_xlfn.XLOOKUP(1,(Rebiz!A:A=Table2[[#This Row],[Employee]])*(Rebiz!C:C=Table2[[#This Row],[Date]]),Rebiz!H:H,"")} | T5: {=_xlfn.XLOOKUP(1,(Rebiz!A:A=Table2[[#This Row],[Employee]])*(Rebiz!C:C=Table2[[#This Row],[Date]]),Rebiz!I:I,"")} | U5: {=_xlfn.XLOOKUP(1,(Rebiz!A:A=Table2[[#This Row],[Employee]])*(Rebiz!C:C=Table2[[#This Row],[Date]]),Rebiz!J:J,"")} | V5: {=_xlfn.XLOOKUP(1,(Rebiz!A:A=Table2[[#This Row],[Employee]])*(Rebiz!C:C=Table2[[#This Row],[Date]]),Rebiz!K:K,"")}
A6: Central | B6: South TX/RGV | C6: Rockport | D6: ETHAN DUGGER | E6: MOBILE ASSOCIATE | F6: 46296 | I6: 0.41284722 | J6: 0.7309375 | K6: 0 | L6: 6.9158333 | M6: 1 | N6: 43.1 | O6: Not Scheduled | P6: {=_xlfn.XLOOKUP(1,(Rebiz!A:A=Table2[[#This Row],[Employee]])*(Rebiz!C:C=Table2[[#This Row],[Date]]),Rebiz!E:E,"")} -> 46296.414 | Q6: {=_xlfn.XLOOKUP(1,(Rebiz!A:A=Table2[[#This Row],[Employee]])*(Rebiz!C:C=Table2[[#This Row],[Date]]),Rebiz!F:F,"")} -> 46296.742 | R6: {=_xlfn.XLOOKUP(1,(Rebiz!A:A=Table2[[#This Row],[Employee]])*(Rebiz!C:C=Table2[[#This Row],[Date]]),Rebiz!G:G,"")} -> 7:52 | S6: {=_xlfn.XLOOKUP(1,(Rebiz!A:A=Table2[[#This Row],[Employee]])*(Rebiz!C:C=Table2[[#This Row],[Date]]),Rebiz!H:H,"")} -> 1:34 | T6: {=_xlfn.XLOOKUP(1,(Rebiz!A:A=Table2[[#This Row],[Employee]])*(Rebiz!C:C=Table2[[#This Row],[Date]]),Rebiz!I:I,"")} -> 6:18 | U6: {=_xlfn.XLOOKUP(1,(Rebiz!A:A=Table2[[#This Row],[Employee]])*(Rebiz!C:C=Table2[[#This Row],[Date]]),Rebiz!J:J,"")} -> 0:0 | V6: {=_xlfn.XLOOKUP(1,(Rebiz!A:A=Table2[[#This Row],[Employee]])*(Rebiz!C:C=Table2[[#This Row],[Date]]),Rebiz!K:K,"")} -> Y
A7: Central | B7: South TX/RGV | C7: Viejo | D7: JOAQUIN VILLARREAL | E7: MOBILE ASSOCIATE | F7: 46296 | G7: 0.39583333 | H7: 0.75 | I7: 0.40409722 | J7: 0.75050926 | K7: 8 | L7: 7.7133333 | M7: 1 | N7: 36.033333 | O7: Late Clock In | P7: {=_xlfn.XLOOKUP(1,(Rebiz!A:A=Table2[[#This Row],[Employee]])*(Rebiz!C:C=Table2[[#This Row],[Date]]),Rebiz!E:E,"")} -> 46296.399 | Q7: {=_xlfn.XLOOKUP(1,(Rebiz!A:A=Table2[[#This Row],[Employee]])*(Rebiz!C:C=Table2[[#This Row],[Date]]),Rebiz!F:F,"")} -> 46296.756 | R7: {=_xlfn.XLOOKUP(1,(Rebiz!A:A=Table2[[#This Row],[Employee]])*(Rebiz!C:C=Table2[[#This Row],[Date]]),Rebiz!G:G,"")} -> 8:34 | S7: {=_xlfn.XLOOKUP(1,(Rebiz!A:A=Table2[[#This Row],[Employee]])*(Rebiz!C:C=Table2[[#This Row],[Date]]),Rebiz!H:H,"")} -> 8:34 | T7: {=_xlfn.XLOOKUP(1,(Rebiz!A:A=Table2[[#This Row],[Employee]])*(Rebiz!C:C=Table2[[#This Row],[Date]]),Rebiz!I:I,"")} -> 0:0 | U7: {=_xlfn.XLOOKUP(1,(Rebiz!A:A=Table2[[#This Row],[Employee]])*(Rebiz!C:C=Table2[[#This Row],[Date]]),Rebiz!J:J,"")} -> 0:0 | V7: {=_xlfn.XLOOKUP(1,(Rebiz!A:A=Table2[[#This Row],[Employee]])*(Rebiz!C:C=Table2[[#This Row],[Date]]),Rebiz!K:K,"")} -> Y
A8: Central | B8: DFW North | C8: Seventh Ave | D8: LOGAN SMITH | E8: MOBILE ASSOCIATE | F8: 46296 | I8: 0.48005787 | J8: 0.73017361 | K8: 0 | L8: 5.0008333 | M8: 1 | N8: 60.116667 | O8: Not Scheduled | P8: {=_xlfn.XLOOKUP(1,(Rebiz!A:A=Table2[[#This Row],[Employee]])*(Rebiz!C:C=Table2[[#This Row],[Date]]),Rebiz!E:E,"")} -> 46296.483 | Q8: {=_xlfn.XLOOKUP(1,(Rebiz!A:A=Table2[[#This Row],[Employee]])*(Rebiz!C:C=Table2[[#This Row],[Date]]),Rebiz!F:F,"")} -> 46296.733 | R8: {=_xlfn.XLOOKUP(1,(Rebiz!A:A=Table2[[#This Row],[Employee]])*(Rebiz!C:C=Table2[[#This Row],[Date]]),Rebiz!G:G,"")} -> 5:2 | S8: {=_xlfn.XLOOKUP(1,(Rebiz!A:A=Table2[[#This Row],[Employee]])*(Rebiz!C:C=Table2[[#This Row],[Date]]),Rebiz!H:H,"")} -> 5:2 | T8: {=_xlfn.XLOOKUP(1,(Rebiz!A:A=Table2[[#This Row],[Employee]])*(Rebiz!C:C=Table2[[#This Row],[Date]]),Rebiz!I:I,"")} -> 0:0 | U8: {=_xlfn.XLOOKUP(1,(Rebiz!A:A=Table2[[#This Row],[Employee]])*(Rebiz!C:C=Table2[[#This Row],[Date]]),Rebiz!J:J,"")} -> 0:59 | V8: {=_xlfn.XLOOKUP(1,(Rebiz!A:A=Table2[[#This Row],[Employee]])*(Rebiz!C:C=Table2[[#This Row],[Date]]),Rebiz!K:K,"")} -> Y
A9: Central | B9: West Texas | C9: Olton | D9: NANCY BENAVIDES | E9: MOBILE ASSOCIATE | F9: 46296 | G9: 0.54166667 | H9: 0.85416667 | I9: 0.5424537 | J9: 0.85059028 | K9: 7 | L9: 6.3763889 | M9: 1 | N9: 61.133333 | O9: On Time | P9: {=_xlfn.XLOOKUP(1,(Rebiz!A:A=Table2[[#This Row],[Employee]])*(Rebiz!C:C=Table2[[#This Row],[Date]]),Rebiz!E:E,"")} -> 46296.545 | Q9: {=_xlfn.XLOOKUP(1,(Rebiz!A:A=Table2[[#This Row],[Employee]])*(Rebiz!C:C=Table2[[#This Row],[Date]]),Rebiz!F:F,"")} -> 46296.852 | R9: {=_xlfn.XLOOKUP(1,(Rebiz!A:A=Table2[[#This Row],[Employee]])*(Rebiz!C:C=Table2[[#This Row],[Date]]),Rebiz!G:G,"")} -> 6:10 | S9: {=_xlfn.XLOOKUP(1,(Rebiz!A:A=Table2[[#This Row],[Employee]])*(Rebiz!C:C=Table2[[#This Row],[Date]]),Rebiz!H:H,"")} -> 5:55 | T9: {=_xlfn.XLOOKUP(1,(Rebiz!A:A=Table2[[#This Row],[Employee]])*(Rebiz!C:C=Table2[[#This Row],[Date]]),Rebiz!I:I,"")} -> 0:15 | U9: {=_xlfn.XLOOKUP(1,(Rebiz!A:A=Table2[[#This Row],[Employee]])*(Rebiz!C:C=Table2[[#This Row],[Date]]),Rebiz!J:J,"")} -> 1:12 | V9: {=_xlfn.XLOOKUP(1,(Rebiz!A:A=Table2[[#This Row],[Employee]])*(Rebiz!C:C=Table2[[#This Row],[Date]]),Rebiz!K:K,"")} -> Y
A10: Central | B10: MO/IA/NE | C10: Virginia Avenue | D10: GUSTAVO CUATLACUATL | E10: MOBILE ASSOCIATE | F10: 46296 | G10: 0.52083333 | H10: 0.85416667 | K10: 7.5 | L10: 0 | M10: 0 | N10: 0 | O10: No Show | P10: {=_xlfn.XLOOKUP(1,(Rebiz!A:A=Table2[[#This Row],[Employee]])*(Rebiz!C:C=Table2[[#This Row],[Date]]),Rebiz!E:E,"")} | Q10: {=_xlfn.XLOOKUP(1,(Rebiz!A:A=Table2[[#This Row],[Employee]])*(Rebiz!C:C=Table2[[#This Row],[Date]]),Rebiz!F:F,"")} | R10: {=_xlfn.XLOOKUP(1,(Rebiz!A:A=Table2[[#This Row],[Employee]])*(Rebiz!C:C=Table2[[#This Row],[Date]]),Rebiz!G:G,"")} | S10: {=_xlfn.XLOOKUP(1,(Rebiz!A:A=Table2[[#This Row],[Employee]])*(Rebiz!C:C=Table2[[#This Row],[Date]]),Rebiz!H:H,"")} | T10: {=_xlfn.XLOOKUP(1,(Rebiz!A:A=Table2[[#This Row],[Employee]])*(Rebiz!C:C=Table2[[#This Row],[Date]]),Rebiz!I:I,"")} | U10: {=_xlfn.XLOOKUP(1,(Rebiz!A:A=Table2[[#This Row],[Employee]])*(Rebiz!C:C=Table2[[#This Row],[Date]]),Rebiz!J:J,"")} | V10: {=_xlfn.XLOOKUP(1,(Rebiz!A:A=Table2[[#This Row],[Employee]])*(Rebiz!C:C=Table2[[#This Row],[Date]]),Rebiz!K:K,"")}
A11: Central | B11: South TX/RGV | C11: Beeville | D11: ALBERT GARCIA | E11: MOBILE ASSOCIATE | F11: 46296 | G11: 0.45833333 | H11: 0.75 | I11: 0.45833333 | J11: 0.86954861 | K11: 6.5 | L11: 9.0927778 | M11: 1 | N11: 46.583333 | O11: Late Clock Out | P11: {=_xlfn.XLOOKUP(1,(Rebiz!A:A=Table2[[#This Row],[Employee]])*(Rebiz!C:C=Table2[[#This Row],[Date]]),Rebiz!E:E,"")} -> 46296.459 | Q11: {=_xlfn.XLOOKUP(1,(Rebiz!A:A=Table2[[#This Row],[Employee]])*(Rebiz!C:C=Table2[[#This Row],[Date]]),Rebiz!F:F,"")} -> 46296.872 | R11: {=_xlfn.XLOOKUP(1,(Rebiz!A:A=Table2[[#This Row],[Employee]])*(Rebiz!C:C=Table2[[#This Row],[Date]]),Rebiz!G:G,"")} -> 9:10 | S11: {=_xlfn.XLOOKUP(1,(Rebiz!A:A=Table2[[#This Row],[Employee]])*(Rebiz!C:C=Table2[[#This Row],[Date]]),Rebiz!H:H,"")} -> 7:13 | T11: {=_xlfn.XLOOKUP(1,(Rebiz!A:A=Table2[[#This Row],[Employee]])*(Rebiz!C:C=Table2[[#This Row],[Date]]),Rebiz!I:I,"")} -> 1:57 | U11: {=_xlfn.XLOOKUP(1,(Rebiz!A:A=Table2[[#This Row],[Employee]])*(Rebiz!C:C=Table2[[#This Row],[Date]]),Rebiz!J:J,"")} -> 0:45 | V11: {=_xlfn.XLOOKUP(1,(Rebiz!A:A=Table2[[#This Row],[Employee]])*(Rebiz!C:C=Table2[[#This Row],[Date]]),Rebiz!K:K,"")} -> Y
A12: Central | B12: SA South | C12: Palo Alto | D12: DANIELLE VILLARREAL | E12: MOBILE ASSOCIATE | F12: 46296 | I12: 0.47533565 | J12: 0.73929398 | K12: 0 | L12: 5.7925 | M12: 1 | N12: 32.55 | O12: Not Scheduled | P12: {=_xlfn.XLOOKUP(1,(Rebiz!A:A=Table2[[#This Row],[Employee]])*(Rebiz!C:C=Table2[[#This Row],[Date]]),Rebiz!E:E,"")} -> 46296.472 | Q12: {=_xlfn.XLOOKUP(1,(Rebiz!A:A=Table2[[#This Row],[Employee]])*(Rebiz!C:C=Table2[[#This Row],[Date]]),Rebiz!F:F,"")} -> 46296.742 | R12: {=_xlfn.XLOOKUP(1,(Rebiz!A:A=Table2[[#This Row],[Employee]])*(Rebiz!C:C=Table2[[#This Row],[Date]]),Rebiz!G:G,"")} -> 6:14 | S12: {=_xlfn.XLOOKUP(1,(Rebiz!A:A=Table2[[#This Row],[Employee]])*(Rebiz!C:C=Table2[[#This Row],[Date]]),Rebiz!H:H,"")} -> 3:5 | T12: {=_xlfn.XLOOKUP(1,(Rebiz!A:A=Table2[[#This Row],[Employee]])*(Rebiz!C:C=Table2[[#This Row],[Date]]),Rebiz!I:I,"")} -> 3:9 | U12: {=_xlfn.XLOOKUP(1,(Rebiz!A:A=Table2[[#This Row],[Employee]])*(Rebiz!C:C=Table2[[#This Row],[Date]]),Rebiz!J:J,"")} -> 0:16 | V12: {=_xlfn.XLOOKUP(1,(Rebiz!A:A=Table2[[#This Row],[Employee]])*(Rebiz!C:C=Table2[[#This Row],[Date]]),Rebiz!K:K,"")} -> Y
A13: Central | B13: DFW North | C13: Stephenville | D13: AUSTIN BROWN | E13: MOBILE ASSOCIATE | F13: 46296 | G13: 0.39583333 | H13: 0.75 | I13: 0.39608796 | J13: 0.75056713 | K13: 7.5 | L13: 7.5172222 | M13: 1 | N13: 59.416667 | O13: On Time | P13: {=_xlfn.XLOOKUP(1,(Rebiz!A:A=Table2[[#This Row],[Employee]])*(Rebiz!C:C=Table2[[#This Row],[Date]]),Rebiz!E:E,"")} -> 46296.397 | Q13: {=_xlfn.XLOOKUP(1,(Rebiz!A:A=Table2[[#This Row],[Employee]])*(Rebiz!C:C=Table2[[#This Row],[Date]]),Rebiz!F:F,"")} -> 46296.757 | R13: {=_xlfn.XLOOKUP(1,(Rebiz!A:A=Table2[[#This Row],[Employee]])*(Rebiz!C:C=Table2[[#This Row],[Date]]),Rebiz!G:G,"")} -> 8:39 | S13: {=_xlfn.XLOOKUP(1,(Rebiz!A:A=Table2[[#This Row],[Employee]])*(Rebiz!C:C=Table2[[#This Row],[Date]]),Rebiz!H:H,"")} -> 7:18 | T13: {=_xlfn.XLOOKUP(1,(Rebiz!A:A=Table2[[#This Row],[Employee]])*(Rebiz!C:C=Table2[[#This Row],[Date]]),Rebiz!I:I,"")} -> 1:21 | U13: {=_xlfn.XLOOKUP(1,(Rebiz!A:A=Table2[[#This Row],[Employee]])*(Rebiz!C:C=Table2[[#This Row],[Date]]),Rebiz!J:J,"")} -> 0:0 | V13: {=_xlfn.XLOOKUP(1,(Rebiz!A:A=Table2[[#This Row],[Employee]])*(Rebiz!C:C=Table2[[#This Row],[Date]]),Rebiz!K:K,"")} -> Y
A14: Central | B14: SA South | C14: Uvalde | D14: MIA LOPEZ | E14: MOBILE ASSOCIATE | F14: 46296 | G14: 0.45833333 | H14: 0.79166667 | I14: 0.46011574 | J14: 0.79436343 | K14: 7 | L14: 6.9305556 | M14: 1 | N14: 65.483333 | O14: On Time | P14: {=_xlfn.XLOOKUP(1,(Rebiz!A:A=Table2[[#This Row],[Employee]])*(Rebiz!C:C=Table2[[#This Row],[Date]]),Rebiz!E:E,"")} -> 46296.464 | Q14: {=_xlfn.XLOOKUP(1,(Rebiz!A:A=Table2[[#This Row],[Employee]])*(Rebiz!C:C=Table2[[#This Row],[Date]]),Rebiz!F:F,"")} -> 46296.797 | R14: {=_xlfn.XLOOKUP(1,(Rebiz!A:A=Table2[[#This Row],[Employee]])*(Rebiz!C:C=Table2[[#This Row],[Date]]),Rebiz!G:G,"")} -> 6:56 | S14: {=_xlfn.XLOOKUP(1,(Rebiz!A:A=Table2[[#This Row],[Employee]])*(Rebiz!C:C=Table2[[#This Row],[Date]]),Rebiz!H:H,"")} -> 6:56 | T14: {=_xlfn.XLOOKUP(1,(Rebiz!A:A=Table2[[#This Row],[Employee]])*(Rebiz!C:C=Table2[[#This Row],[Date]]),Rebiz!I:I,"")} -> 0:0 | U14: {=_xlfn.XLOOKUP(1,(Rebiz!A:A=Table2[[#This Row],[Employee]])*(Rebiz!C:C=Table2[[#This Row],[Date]]),Rebiz!J:J,"")} -> 1:4 | V14: {=_xlfn.XLOOKUP(1,(Rebiz!A:A=Table2[[#This Row],[Employee]])*(Rebiz!C:C=Table2[[#This Row],[Date]]),Rebiz!K:K,"")} -> Y
A15: Central | B15: MO/IA/NE | C15: Hannibal | D15: MARGARET NICHOLLS | E15: MOBILE ASSOCIATE | F15: 46296 | G15: 0.39583333 | H15: 0.75 | K15: 8 | L15: 0 | M15: 0 | N15: 0 | O15: No Show | P15: {=_xlfn.XLOOKUP(1,(Rebiz!A:A=Table2[[#This Row],[Employee]])*(Rebiz!C:C=Table2[[#This Row],[Date]]),Rebiz!E:E,"")} | Q15: {=_xlfn.XLOOKUP(1,(Rebiz!A:A=Table2[[#This Row],[Employee]])*(Rebiz!C:C=Table2[[#This Row],[Date]]),Rebiz!F:F,"")} | R15: {=_xlfn.XLOOKUP(1,(Rebiz!A:A=Table2[[#This Row],[Employee]])*(Rebiz!C:C=Table2[[#This Row],[Date]]),Rebiz!G:G,"")} | S15: {=_xlfn.XLOOKUP(1,(Rebiz!A:A=Table2[[#This Row],[Employee]])*(Rebiz!C:C=Table2[[#This Row],[Date]]),Rebiz!H:H,"")} | T15: {=_xlfn.XLOOKUP(1,(Rebiz!A:A=Table2[[#This Row],[Employee]])*(Rebiz!C:C=Table2[[#This Row],[Date]]),Rebiz!I:I,"")} | U15: {=_xlfn.XLOOKUP(1,(Rebiz!A:A=Table2[[#This Row],[Employee]])*(Rebiz!C:C=Table2[[#This Row],[Date]]),Rebiz!J:J,"")} | V15: {=_xlfn.XLOOKUP(1,(Rebiz!A:A=Table2[[#This Row],[Employee]])*(Rebiz!C:C=Table2[[#This Row],[Date]]),Rebiz!K:K,"")}
A16: Central | B16: SA/Hill Country | C16: Kerrville | D16: JORGE TORRALBA | E16: MOBILE ASSOCIATE | F16: 46296 | G16: 0.39583333 | H16: 0.75 | I16: 0.39353009 | J16: 0.750625 | K16: 7.5 | L16: 7.7313889 | M16: 1 | N16: 50.333333 | O16: On Time | P16: {=_xlfn.XLOOKUP(1,(Rebiz!A:A=Table2[[#This Row],[Employee]])*(Rebiz!C:C=Table2[[#This Row],[Date]]),Rebiz!E:E,"")} | Q16: {=_xlfn.XLOOKUP(1,(Rebiz!A:A=Table2[[#This Row],[Employee]])*(Rebiz!C:C=Table2[[#This Row],[Date]]),Rebiz!F:F,"")} | R16: {=_xlfn.XLOOKUP(1,(Rebiz!A:A=Table2[[#This Row],[Employee]])*(Rebiz!C:C=Table2[[#This Row],[Date]]),Rebiz!G:G,"")} | S16: {=_xlfn.XLOOKUP(1,(Rebiz!A:A=Table2[[#This Row],[Employee]])*(Rebiz!C:C=Table2[[#This Row],[Date]]),Rebiz!H:H,"")} | T16: {=_xlfn.XLOOKUP(1,(Rebiz!A:A=Table2[[#This Row],[Employee]])*(Rebiz!C:C=Table2[[#This Row],[Date]]),Rebiz!I:I,"")} | U16: {=_xlfn.XLOOKUP(1,(Rebiz!A:A=Table2[[#This Row],[Employee]])*(Rebiz!C:C=Table2[[#This Row],[Date]]),Rebiz!J:J,"")} | V16: {=_xlfn.XLOOKUP(1,(Rebiz!A:A=Table2[[#This Row],[Employee]])*(Rebiz!C:C=Table2[[#This Row],[Date]]),Rebiz!K:K,"")}
A17: Central | B17: West Texas | C17: S. Georgia | D17: DELERIA AGUILAR | E17: MOBILE ASSOCIATE | F17: 46296 | G17: 0.54166667 | H17: 0.85416667 | I17: 0.54092593 | J17: 0.85991898 | K17: 7 | L17: 7.1536111 | M17: 1 | N17: 30.133333 | O17: On Time | P17: {=_xlfn.XLOOKUP(1,(Rebiz!A:A=Table2[[#This Row],[Employee]])*(Rebiz!C:C=Table2[[#This Row],[Date]]),Rebiz!E:E,"")} -> 46296.556 | Q17: {=_xlfn.XLOOKUP(1,(Rebiz!A:A=Table2[[#This Row],[Employee]])*(Rebiz!C:C=Table2[[#This Row],[Date]]),Rebiz!F:F,"")} -> 46296.864 | R17: {=_xlfn.XLOOKUP(1,(Rebiz!A:A=Table2[[#This Row],[Employee]])*(Rebiz!C:C=Table2[[#This Row],[Date]]),Rebiz!G:G,"")} -> 6:40 | S17: {=_xlfn.XLOOKUP(1,(Rebiz!A:A=Table2[[#This Row],[Employee]])*(Rebiz!C:C=Table2[[#This Row],[Date]]),Rebiz!H:H,"")} -> 6:40 | T17: {=_xlfn.XLOOKUP(1,(Rebiz!A:A=Table2[[#This Row],[Employee]])*(Rebiz!C:C=Table2[[#This Row],[Date]]),Rebiz!I:I,"")} -> 0:0 | U17: {=_xlfn.XLOOKUP(1,(Rebiz!A:A=Table2[[#This Row],[Employee]])*(Rebiz!C:C=Table2[[#This Row],[Date]]),Rebiz!J:J,"")} -> 0:44 | V17: {=_xlfn.XLOOKUP(1,(Rebiz!A:A=Table2[[#This Row],[Employee]])*(Rebiz!C:C=Table2[[#This Row],[Date]]),Rebiz!K:K,"")} -> Y
A18: Central | B18: South TX/RGV | C18: Viejo | D18: JOSE ROBLES | E18: MOBILE ASSOCIATE | F18: 46296 | G18: 0.47916667 | H18: 0.83333333 | I18: 0.47871528 | J18: 0.87291667 | K18: 8 | L18: 8.6908333 | M18: 1 | N18: 46.2 | O18: Late Clock Out | P18: {=_xlfn.XLOOKUP(1,(Rebiz!A:A=Table2[[#This Row],[Employee]])*(Rebiz!C:C=Table2[[#This Row],[Date]]),Rebiz!E:E,"")} -> 46296.479 | Q18: {=_xlfn.XLOOKUP(1,(Rebiz!A:A=Table2[[#This Row],[Employee]])*(Rebiz!C:C=Table2[[#This Row],[Date]]),Rebiz!F:F,"")} -> 46296.875 | R18: {=_xlfn.XLOOKUP(1,(Rebiz!A:A=Table2[[#This Row],[Employee]])*(Rebiz!C:C=Table2[[#This Row],[Date]]),Rebiz!G:G,"")} -> 9:30 | S18: {=_xlfn.XLOOKUP(1,(Rebiz!A:A=Table2[[#This Row],[Employee]])*(Rebiz!C:C=Table2[[#This Row],[Date]]),Rebiz!H:H,"")} -> 9:30 | T18: {=_xlfn.XLOOKUP(1,(Rebiz!A:A=Table2[[#This Row],[Employee]])*(Rebiz!C:C=Table2[[#This Row],[Date]]),Rebiz!I:I,"")} -> 0:0 | U18: {=_xlfn.XLOOKUP(1,(Rebiz!A:A=Table2[[#This Row],[Employee]])*(Rebiz!C:C=Table2[[#This Row],[Date]]),Rebiz!J:J,"")} -> 0:0 | V18: {=_xlfn.XLOOKUP(1,(Rebiz!A:A=Table2[[#This Row],[Employee]])*(Rebiz!C:C=Table2[[#This Row],[Date]]),Rebiz!K:K,"")} -> Y
A19: Central | B19: DFW North | C19: Weatherford | D19: DARINNAY ALLEN | E19: MOBILE ASSOCIATE | F19: 46296 | G19: 0.375 | H19: 0.66666667 | I19: 0.40760417 | J19: 0.71179398 | K19: 6 | L19: 6.3072222 | M19: 1 | N19: 59.6 | O19: Late Clock Out, Late Clock In | P19: {=_xlfn.XLOOKUP(1,(Rebiz!A:A=Table2[[#This Row],[Employee]])*(Rebiz!C:C=Table2[[#This Row],[Date]]),Rebiz!E:E,"")} -> 46296.409 | Q19: {=_xlfn.XLOOKUP(1,(Rebiz!A:A=Table2[[#This Row],[Employee]])*(Rebiz!C:C=Table2[[#This Row],[Date]]),Rebiz!F:F,"")} -> 46296.713 | R19: {=_xlfn.XLOOKUP(1,(Rebiz!A:A=Table2[[#This Row],[Employee]])*(Rebiz!C:C=Table2[[#This Row],[Date]]),Rebiz!G:G,"")} -> 7:0 | S19: {=_xlfn.XLOOKUP(1,(Rebiz!A:A=Table2[[#This Row],[Employee]])*(Rebiz!C:C=Table2[[#This Row],[Date]]),Rebiz!H:H,"")} -> 5:42 | T19: {=_xlfn.XLOOKUP(1,(Rebiz!A:A=Table2[[#This Row],[Employee]])*(Rebiz!C:C=Table2[[#This Row],[Date]]),Rebiz!I:I,"")} -> 1:18 | U19: {=_xlfn.XLOOKUP(1,(Rebiz!A:A=Table2[[#This Row],[Employee]])*(Rebiz!C:C=Table2[[#This Row],[Date]]),Rebiz!J:J,"")} -> 0:17 | V19: {=_xlfn.XLOOKUP(1,(Rebiz!A:A=Table2[[#This Row],[Employee]])*(Rebiz!C:C=Table2[[#This Row],[Date]]),Rebiz!K:K,"")} -> Y
A20: Central | B20: West Texas | C20: Walmart Court | D20: NYA MARQUEZ | E20: MOBILE ASSOCIATE | F20: 46296 | G20: 0.5 | H20: 0.85416667 | I20: 0.50091435 | J20: 0.86041667 | K20: 8 | L20: 8.1338889 | M20: 1 | N20: 29.65 | O20: On Time | P20: {=_xlfn.XLOOKUP(1,(Rebiz!A:A=Table2[[#This Row],[Employee]])*(Rebiz!C:C=Table2[[#This Row],[Date]]),Rebiz!E:E,"")} -> 46296.503 | Q20: {=_xlfn.XLOOKUP(1,(Rebiz!A:A=Table2[[#This Row],[Employee]])*(Rebiz!C:C=Table2[[#This Row],[Date]]),Rebiz!F:F,"")} -> 46296.863 | R20: {=_xlfn.XLOOKUP(1,(Rebiz!A:A=Table2[[#This Row],[Employee]])*(Rebiz!C:C=Table2[[#This Row],[Date]]),Rebiz!G:G,"")} -> 8:10 | S20: {=_xlfn.XLOOKUP(1,(Rebiz!A:A=Table2[[#This Row],[Employee]])*(Rebiz!C:C=Table2[[#This Row],[Date]]),Rebiz!H:H,"")} -> 4:1 | T20: {=_xlfn.XLOOKUP(1,(Rebiz!A:A=Table2[[#This Row],[Employee]])*(Rebiz!C:C=Table2[[#This Row],[Date]]),Rebiz!I:I,"")} -> 4:9 | U20: {=_xlfn.XLOOKUP(1,(Rebiz!A:A=Table2[[#This Row],[Employee]])*(Rebiz!C:C=Table2[[#This Row],[Date]]),Rebiz!J:J,"")} -> 0:28 | V20: {=_xlfn.XLOOKUP(1,(Rebiz!A:A=Table2[[#This Row],[Employee]])*(Rebiz!C:C=Table2[[#This Row],[Date]]),Rebiz!K:K,"")} -> Y
A21: Central | B21: DFW East | C21: Cooper Street | D21: ABEL HERNANDEZ | E21: MOBILE ASSOCIATE | F21: 46296 | G21: 0.54166667 | H21: 0.89583333 | I21: 0.50607639 | J21: 0.88925926 | K21: 8 | L21: 8.1888889 | M21: 1 | N21: 60.45 | O21: Early Clock In | P21: {=_xlfn.XLOOKUP(1,(Rebiz!A:A=Table2[[#This Row],[Employee]])*(Rebiz!C:C=Table2[[#This Row],[Date]]),Rebiz!E:E,"")} -> 46296.508 | Q21: {=_xlfn.XLOOKUP(1,(Rebiz!A:A=Table2[[#This Row],[Employee]])*(Rebiz!C:C=Table2[[#This Row],[Date]]),Rebiz!F:F,"")} -> 46296.891 | R21: {=_xlfn.XLOOKUP(1,(Rebiz!A:A=Table2[[#This Row],[Employee]])*(Rebiz!C:C=Table2[[#This Row],[Date]]),Rebiz!G:G,"")} -> 9:11 | S21: {=_xlfn.XLOOKUP(1,(Rebiz!A:A=Table2[[#This Row],[Employee]])*(Rebiz!C:C=Table2[[#This Row],[Date]]),Rebiz!H:H,"")} -> 6:41 | T21: {=_xlfn.XLOOKUP(1,(Rebiz!A:A=Table2[[#This Row],[Employee]])*(Rebiz!C:C=Table2[[#This Row],[Date]]),Rebiz!I:I,"")} -> 2:30 | U21: {=_xlfn.XLOOKUP(1,(Rebiz!A:A=Table2[[#This Row],[Employee]])*(Rebiz!C:C=Table2[[#This Row],[Date]]),Rebiz!J:J,"")} -> 0:0 | V21: {=_xlfn.XLOOKUP(1,(Rebiz!A:A=Table2[[#This Row],[Employee]])*(Rebiz!C:C=Table2[[#This Row],[Date]]),Rebiz!K:K,"")} -> Y
A22: Central | B22: Central Texas | C22: Texas Ave | D22: DAMIAN GOMEZ-TORRES | E22: MOBILE ASSOCIATE | F22: 46296 | G22: 0.41666667 | H22: 0.70833333 | I22: 0.41527778 | J22: 0.70940972 | K22: 6 | L22: 6.4425 | M22: 1 | N22: 37 | O22: On Time | P22: {=_xlfn.XLOOKUP(1,(Rebiz!A:A=Table2[[#This Row],[Employee]])*(Rebiz!C:C=Table2[[#This Row],[Date]]),Rebiz!E:E,"")} -> 46296.412 | Q22: {=_xlfn.XLOOKUP(1,(Rebiz!A:A=Table2[[#This Row],[Employee]])*(Rebiz!C:C=Table2[[#This Row],[Date]]),Rebiz!F:F,"")} -> 46296.71 | R22: {=_xlfn.XLOOKUP(1,(Rebiz!A:A=Table2[[#This Row],[Employee]])*(Rebiz!C:C=Table2[[#This Row],[Date]]),Rebiz!G:G,"")} -> 7:10 | S22: {=_xlfn.XLOOKUP(1,(Rebiz!A:A=Table2[[#This Row],[Employee]])*(Rebiz!C:C=Table2[[#This Row],[Date]]),Rebiz!H:H,"")} -> 6:7 | T22: {=_xlfn.XLOOKUP(1,(Rebiz!A:A=Table2[[#This Row],[Employee]])*(Rebiz!C:C=Table2[[#This Row],[Date]]),Rebiz!I:I,"")} -> 1:3 | U22: {=_xlfn.XLOOKUP(1,(Rebiz!A:A=Table2[[#This Row],[Employee]])*(Rebiz!C:C=Table2[[#This Row],[Date]]),Rebiz!J:J,"")} -> 0:0 | V22: {=_xlfn.XLOOKUP(1,(Rebiz!A:A=Table2[[#This Row],[Employee]])*(Rebiz!C:C=Table2[[#This Row],[Date]]),Rebiz!K:K,"")} -> Y
A23: Central | B23: KS/OK | C23: Garth Brooks Blvd | D23: ZACH RHODES | E23: MOBILE ASSOCIATE | F23: 46296 | I23: 0.50168981 | J23: 0.70628472 | K23: 0 | L23: 4.0672222 | M23: 1 | N23: 50.583333 | O23: Not Scheduled | P23: {=_xlfn.XLOOKUP(1,(Rebiz!A:A=Table2[[#This Row],[Employee]])*(Rebiz!C:C=Table2[[#This Row],[Date]]),Rebiz!E:E,"")} -> 46296.499 | Q23: {=_xlfn.XLOOKUP(1,(Rebiz!A:A=Table2[[#This Row],[Employee]])*(Rebiz!C:C=Table2[[#This Row],[Date]]),Rebiz!F:F,"")} -> 46296.709 | R23: {=_xlfn.XLOOKUP(1,(Rebiz!A:A=Table2[[#This Row],[Employee]])*(Rebiz!C:C=Table2[[#This Row],[Date]]),Rebiz!G:G,"")} -> 5:3 | S23: {=_xlfn.XLOOKUP(1,(Rebiz!A:A=Table2[[#This Row],[Employee]])*(Rebiz!C:C=Table2[[#This Row],[Date]]),Rebiz!H:H,"")} -> 5:3 | T23: {=_xlfn.XLOOKUP(1,(Rebiz!A:A=Table2[[#This Row],[Employee]])*(Rebiz!C:C=Table2[[#This Row],[Date]]),Rebiz!I:I,"")} -> 0:0 | U23: {=_xlfn.XLOOKUP(1,(Rebiz!A:A=Table2[[#This Row],[Employee]])*(Rebiz!C:C=Table2[[#This Row],[Date]]),Rebiz!J:J,"")} -> 0:0 | V23: {=_xlfn.XLOOKUP(1,(Rebiz!A:A=Table2[[#This Row],[Employee]])*(Rebiz!C:C=Table2[[#This Row],[Date]]),Rebiz!K:K,"")} -> Y
A24: Central | B24: SA/Hill Country | C24: Creekside | D24: ASA LEE | E24: MOBILE ASSOCIATE | F24: 46296 | G24: 0.39583333 | H24: 0.70833333 | I24: 0.39309028 | J24: 0.71862269 | K24: 6.5 | L24: 6.9186111 | M24: 1 | N24: 53.65 | O24: On Time | P24: {=_xlfn.XLOOKUP(1,(Rebiz!A:A=Table2[[#This Row],[Employee]])*(Rebiz!C:C=Table2[[#This Row],[Date]]),Rebiz!E:E,"")} | Q24: {=_xlfn.XLOOKUP(1,(Rebiz!A:A=Table2[[#This Row],[Employee]])*(Rebiz!C:C=Table2[[#This Row],[Date]]),Rebiz!F:F,"")} | R24: {=_xlfn.XLOOKUP(1,(Rebiz!A:A=Table2[[#This Row],[Employee]])*(Rebiz!C:C=Table2[[#This Row],[Date]]),Rebiz!G:G,"")} | S24: {=_xlfn.XLOOKUP(1,(Rebiz!A:A=Table2[[#This Row],[Employee]])*(Rebiz!C:C=Table2[[#This Row],[Date]]),Rebiz!H:H,"")} | T24: {=_xlfn.XLOOKUP(1,(Rebiz!A:A=Table2[[#This Row],[Employee]])*(Rebiz!C:C=Table2[[#This Row],[Date]]),Rebiz!I:I,"")} | U24: {=_xlfn.XLOOKUP(1,(Rebiz!A:A=Table2[[#This Row],[Employee]])*(Rebiz!C:C=Table2[[#This Row],[Date]]),Rebiz!J:J,"")} | V24: {=_xlfn.XLOOKUP(1,(Rebiz!A:A=Table2[[#This Row],[Employee]])*(Rebiz!C:C=Table2[[#This Row],[Date]]),Rebiz!K:K,"")}
A25: Central | B25: DFW North | C25: Stephenville | D25: GABRIELLA LIENDO BARRON | E25: MOBILE ASSOCIATE | F25: 46296 | G25: 0.54166667 | H25: 0.85416667 | I25: 0.54240741 | J25: 0.84076389 | K25: 6.5 | L25: 6.1522222 | M25: 1 | N25: 60.5 | O25: Early Clock Out | P25: {=_xlfn.XLOOKUP(1,(Rebiz!A:A=Table2[[#This Row],[Employee]])*(Rebiz!C:C=Table2[[#This Row],[Date]]),Rebiz!E:E,"")} -> 46296.549 | Q25: {=_xlfn.XLOOKUP(1,(Rebiz!A:A=Table2[[#This Row],[Employee]])*(Rebiz!C:C=Table2[[#This Row],[Date]]),Rebiz!F:F,"")} -> 46296.844 | R25: {=_xlfn.XLOOKUP(1,(Rebiz!A:A=Table2[[#This Row],[Employee]])*(Rebiz!C:C=Table2[[#This Row],[Date]]),Rebiz!G:G,"")} -> 6:4 | S25: {=_xlfn.XLOOKUP(1,(Rebiz!A:A=Table2[[#This Row],[Employee]])*(Rebiz!C:C=Table2[[#This Row],[Date]]),Rebiz!H:H,"")} -> 5:55 | T25: {=_xlfn.XLOOKUP(1,(Rebiz!A:A=Table2[[#This Row],[Employee]])*(Rebiz!C:C=Table2[[#This Row],[Date]]),Rebiz!I:I,"")} -> 0:9 | U25: {=_xlfn.XLOOKUP(1,(Rebiz!A:A=Table2[[#This Row],[Employee]])*(Rebiz!C:C=Table2[[#This Row],[Date]]),Rebiz!J:J,"")} -> 1:1 | V25: {=_xlfn.XLOOKUP(1,(Rebiz!A:A=Table2[[#This Row],[Employee]])*(Rebiz!C:C=Table2[[#This Row],[Date]]),Rebiz!K:K,"")} -> Y
A26: Central | B26: DFW East | C26: Walnut | D26: BRANDON LOPEZ-RODRIGUEZ | E26: MOBILE ASSOCIATE | F26: 46296 | G26: 0.45833333 | H26: 0.83333333 | I26: 0.45733796 | J26: 0.84027778 | K26: 8 | L26: 8.2008333 | M26: 1 | N26: 59.383333 | O26: On Time | P26: {=_xlfn.XLOOKUP(1,(Rebiz!A:A=Table2[[#This Row],[Employee]])*(Rebiz!C:C=Table2[[#This Row],[Date]]),Rebiz!E:E,"")} -> 46296.46 | Q26: {=_xlfn.XLOOKUP(1,(Rebiz!A:A=Table2[[#This Row],[Employee]])*(Rebiz!C:C=Table2[[#This Row],[Date]]),Rebiz!F:F,"")} -> 46296.849 | R26: {=_xlfn.XLOOKUP(1,(Rebiz!A:A=Table2[[#This Row],[Employee]])*(Rebiz!C:C=Table2[[#This Row],[Date]]),Rebiz!G:G,"")} -> 9:20 | S26: {=_xlfn.XLOOKUP(1,(Rebiz!A:A=Table2[[#This Row],[Employee]])*(Rebiz!C:C=Table2[[#This Row],[Date]]),Rebiz!H:H,"")} -> 9:20 | T26: {=_xlfn.XLOOKUP(1,(Rebiz!A:A=Table2[[#This Row],[Employee]])*(Rebiz!C:C=Table2[[#This Row],[Date]]),Rebiz!I:I,"")} -> 0:0 | U26: {=_xlfn.XLOOKUP(1,(Rebiz!A:A=Table2[[#This Row],[Employee]])*(Rebiz!C:C=Table2[[#This Row],[Date]]),Rebiz!J:J,"")} -> 0:0 | V26: {=_xlfn.XLOOKUP(1,(Rebiz!A:A=Table2[[#This Row],[Employee]])*(Rebiz!C:C=Table2[[#This Row],[Date]]),Rebiz!K:K,"")} -> Y
A27: Central | B27: MO/IA/NE | C27: Rolla | D27: PRESTON MELTON | E27: MOBILE ASSOCIATE | F27: 46296 | G27: 0.375 | H27: 0.70833333 | I27: 0.3740625 | J27: 0.7162963 | K27: 7.5 | L27: 7.7069444 | M27: 1 | N27: 30.4 | O27: On Time | P27: {=_xlfn.XLOOKUP(1,(Rebiz!A:A=Table2[[#This Row],[Employee]])*(Rebiz!C:C=Table2[[#This Row],[Date]]),Rebiz!E:E,"")} -> 46296.376 | Q27: {=_xlfn.XLOOKUP(1,(Rebiz!A:A=Table2[[#This Row],[Employee]])*(Rebiz!C:C=Table2[[#This Row],[Date]]),Rebiz!F:F,"")} -> 46296.717 | R27: {=_xlfn.XLOOKUP(1,(Rebiz!A:A=Table2[[#This Row],[Employee]])*(Rebiz!C:C=Table2[[#This Row],[Date]]),Rebiz!G:G,"")} -> 7:22 | S27: {=_xlfn.XLOOKUP(1,(Rebiz!A:A=Table2[[#This Row],[Employee]])*(Rebiz!C:C=Table2[[#This Row],[Date]]),Rebiz!H:H,"")} -> 7:22 | T27: {=_xlfn.XLOOKUP(1,(Rebiz!A:A=Table2[[#This Row],[Employee]])*(Rebiz!C:C=Table2[[#This Row],[Date]]),Rebiz!I:I,"")} -> 0:0 | U27: {=_xlfn.XLOOKUP(1,(Rebiz!A:A=Table2[[#This Row],[Employee]])*(Rebiz!C:C=Table2[[#This Row],[Date]]),Rebiz!J:J,"")} -> 0:49 | V27: {=_xlfn.XLOOKUP(1,(Rebiz!A:A=Table2[[#This Row],[Employee]])*(Rebiz!C:C=Table2[[#This Row],[Date]]),Rebiz!K:K,"")} -> Y
A28: Central | B28: MO/IA/NE | C28: Grand Island | D28: DAMARIS MEIGHAN | E28: MOBILE ASSOCIATE | F28: 46296 | G28: 0.39583333 | H28: 0.75 | I28: 0.39614583 | J28: 0.70887731 | K28: 8 | L28: 6.6805556 | M28: 1 | N28: 49.5 | O28: Early Clock Out | P28: {=_xlfn.XLOOKUP(1,(Rebiz!A:A=Table2[[#This Row],[Employee]])*(Rebiz!C:C=Table2[[#This Row],[Date]]),Rebiz!E:E,"")} -> 46296.397 | Q28: {=_xlfn.XLOOKUP(1,(Rebiz!A:A=Table2[[#This Row],[Employee]])*(Rebiz!C:C=Table2[[#This Row],[Date]]),Rebiz!F:F,"")} -> 46296.711 | R28: {=_xlfn.XLOOKUP(1,(Rebiz!A:A=Table2[[#This Row],[Employee]])*(Rebiz!C:C=Table2[[#This Row],[Date]]),Rebiz!G:G,"")} -> 6:45 | S28: {=_xlfn.XLOOKUP(1,(Rebiz!A:A=Table2[[#This Row],[Employee]])*(Rebiz!C:C=Table2[[#This Row],[Date]]),Rebiz!H:H,"")} -> 6:39 | T28: {=_xlfn.XLOOKUP(1,(Rebiz!A:A=Table2[[#This Row],[Employee]])*(Rebiz!C:C=Table2[[#This Row],[Date]]),Rebiz!I:I,"")} -> 0:6 | U28: {=_xlfn.XLOOKUP(1,(Rebiz!A:A=Table2[[#This Row],[Employee]])*(Rebiz!C:C=Table2[[#This Row],[Date]]),Rebiz!J:J,"")} -> 0:48 | V28: {=_xlfn.XLOOKUP(1,(Rebiz!A:A=Table2[[#This Row],[Employee]])*(Rebiz!C:C=Table2[[#This Row],[Date]]),Rebiz!K:K,"")} -> Y
A29: Central | B29: DFW East | C29: Pines Road | D29: BRIANNA GLOVER | E29: MOBILE ASSOCIATE | F29: 46296 | G29: 0.5 | H29: 0.79166667 | K29: 6.5 | L29: 0 | M29: 0 | N29: 0 | O29: No Show | P29: {=_xlfn.XLOOKUP(1,(Rebiz!A:A=Table2[[#This Row],[Employee]])*(Rebiz!C:C=Table2[[#This Row],[Date]]),Rebiz!E:E,"")} | Q29: {=_xlfn.XLOOKUP(1,(Rebiz!A:A=Table2[[#This Row],[Employee]])*(Rebiz!C:C=Table2[[#This Row],[Date]]),Rebiz!F:F,"")} | R29: {=_xlfn.XLOOKUP(1,(Rebiz!A:A=Table2[[#This Row],[Employee]])*(Rebiz!C:C=Table2[[#This Row],[Date]]),Rebiz!G:G,"")} | S29: {=_xlfn.XLOOKUP(1,(Rebiz!A:A=Table2[[#This Row],[Employee]])*(Rebiz!C:C=Table2[[#This Row],[Date]]),Rebiz!H:H,"")} | T29: {=_xlfn.XLOOKUP(1,(Rebiz!A:A=Table2[[#This Row],[Employee]])*(Rebiz!C:C=Table2[[#This Row],[Date]]),Rebiz!I:I,"")} | U29: {=_xlfn.XLOOKUP(1,(Rebiz!A:A=Table2[[#This Row],[Employee]])*(Rebiz!C:C=Table2[[#This Row],[Date]]),Rebiz!J:J,"")} | V29: {=_xlfn.XLOOKUP(1,(Rebiz!A:A=Table2[[#This Row],[Employee]])*(Rebiz!C:C=Table2[[#This Row],[Date]]),Rebiz!K:K,"")}
A30: Central | B30: DFW East | C30: Eastchase | D30: ANGEL RUBALCAVA | E30: MOBILE ASSOCIATE | F30: 46296 | G30: 0.45833333 | H30: 0.85416667 | I30: 0.43159722 | J30: 0.79372685 | K30: 8.5 | L30: 7.7180556 | M30: 1 | N30: 58.383333 | O30: Early Clock In, Early Clock Out | P30: {=_xlfn.XLOOKUP(1,(Rebiz!A:A=Table2[[#This Row],[Employee]])*(Rebiz!C:C=Table2[[#This Row],[Date]]),Rebiz!E:E,"")} -> 46296.432 | Q30: {=_xlfn.XLOOKUP(1,(Rebiz!A:A=Table2[[#This Row],[Employee]])*(Rebiz!C:C=Table2[[#This Row],[Date]]),Rebiz!F:F,"")} -> 46296.797 | R30: {=_xlfn.XLOOKUP(1,(Rebiz!A:A=Table2[[#This Row],[Employee]])*(Rebiz!C:C=Table2[[#This Row],[Date]]),Rebiz!G:G,"")} -> 8:30 | S30: {=_xlfn.XLOOKUP(1,(Rebiz!A:A=Table2[[#This Row],[Employee]])*(Rebiz!C:C=Table2[[#This Row],[Date]]),Rebiz!H:H,"")} -> 7:18 | T30: {=_xlfn.XLOOKUP(1,(Rebiz!A:A=Table2[[#This Row],[Employee]])*(Rebiz!C:C=Table2[[#This Row],[Date]]),Rebiz!I:I,"")} -> 1:12 | U30: {=_xlfn.XLOOKUP(1,(Rebiz!A:A=Table2[[#This Row],[Employee]])*(Rebiz!C:C=Table2[[#This Row],[Date]]),Rebiz!J:J,"")} -> 0:16 | V30: {=_xlfn.XLOOKUP(1,(Rebiz!A:A=Table2[[#This Row],[Employee]])*(Rebiz!C:C=Table2[[#This Row],[Date]]),Rebiz!K:K,"")} -> Y
A31: Central | B31: Central Texas | C31: Marble Falls | D31: ALEX TURLEY | E31: MOBILE ASSOCIATE | F31: 46296 | G31: 0.5 | H31: 0.84375 | I31: 0.50005787 | J31: 0.84892361 | K31: 7.75 | L31: 7.8147222 | M31: 1 | N31: 33.483333 | O31: On Time | P31: {=_xlfn.XLOOKUP(1,(Rebiz!A:A=Table2[[#This Row],[Employee]])*(Rebiz!C:C=Table2[[#This Row],[Date]]),Rebiz!E:E,"")} -> 46296.499 | Q31: {=_xlfn.XLOOKUP(1,(Rebiz!A:A=Table2[[#This Row],[Employee]])*(Rebiz!C:C=Table2[[#This Row],[Date]]),Rebiz!F:F,"")} -> 46296.851 | R31: {=_xlfn.XLOOKUP(1,(Rebiz!A:A=Table2[[#This Row],[Employee]])*(Rebiz!C:C=Table2[[#This Row],[Date]]),Rebiz!G:G,"")} -> 8:14 | S31: {=_xlfn.XLOOKUP(1,(Rebiz!A:A=Table2[[#This Row],[Employee]])*(Rebiz!C:C=Table2[[#This Row],[Date]]),Rebiz!H:H,"")} -> 7:23 | T31: {=_xlfn.XLOOKUP(1,(Rebiz!A:A=Table2[[#This Row],[Employee]])*(Rebiz!C:C=Table2[[#This Row],[Date]]),Rebiz!I:I,"")} -> 0:51 | U31: {=_xlfn.XLOOKUP(1,(Rebiz!A:A=Table2[[#This Row],[Employee]])*(Rebiz!C:C=Table2[[#This Row],[Date]]),Rebiz!J:J,"")} -> 0:13 | V31: {=_xlfn.XLOOKUP(1,(Rebiz!A:A=Table2[[#This Row],[Employee]])*(Rebiz!C:C=Table2[[#This Row],[Date]]),Rebiz!K:K,"")} -> Y
A32: Central | B32: South TX/RGV | C32: Ocean Blvd | D32: ALEJANDRA SILGUERO | E32: MOBILE ASSOCIATE | F32: 46296 | G32: 0.5 | H32: 0.85416667 | I32: 0.50027778 | J32: 0.85141204 | K32: 8 | L32: 7.5755556 | M32: 1 | N32: 51.1 | O32: On Time | P32: {=_xlfn.XLOOKUP(1,(Rebiz!A:A=Table2[[#This Row],[Employee]])*(Rebiz!C:C=Table2[[#This Row],[Date]]),Rebiz!E:E,"")} | Q32: {=_xlfn.XLOOKUP(1,(Rebiz!A:A=Table2[[#This Row],[Employee]])*(Rebiz!C:C=Table2[[#This Row],[Date]]),Rebiz!F:F,"")} | R32: {=_xlfn.XLOOKUP(1,(Rebiz!A:A=Table2[[#This Row],[Employee]])*(Rebiz!C:C=Table2[[#This Row],[Date]]),Rebiz!G:G,"")} | S32: {=_xlfn.XLOOKUP(1,(Rebiz!A:A=Table2[[#This Row],[Employee]])*(Rebiz!C:C=Table2[[#This Row],[Date]]),Rebiz!H:H,"")} | T32: {=_xlfn.XLOOKUP(1,(Rebiz!A:A=Table2[[#This Row],[Employee]])*(Rebiz!C:C=Table2[[#This Row],[Date]]),Rebiz!I:I,"")} | U32: {=_xlfn.XLOOKUP(1,(Rebiz!A:A=Table2[[#This Row],[Employee]])*(Rebiz!C:C=Table2[[#This Row],[Date]]),Rebiz!J:J,"")} | V32: {=_xlfn.XLOOKUP(1,(Rebiz!A:A=Table2[[#This Row],[Employee]])*(Rebiz!C:C=Table2[[#This Row],[Date]]),Rebiz!K:K,"")}
A33: Central | B33: KS/OK | C33: Schilling | D33: KYLE BURCH | E33: MOBILE ASSOCIATE | F33: 46296 | I33: 0.45277778 | J33: 0.71738426 | K33: 0 | L33: 5.8505556 | M33: 1 | N33: 30 | O33: Not Scheduled | P33: {=_xlfn.XLOOKUP(1,(Rebiz!A:A=Table2[[#This Row],[Employee]])*(Rebiz!C:C=Table2[[#This Row],[Date]]),Rebiz!E:E,"")} -> 46296.456 | Q33: {=_xlfn.XLOOKUP(1,(Rebiz!A:A=Table2[[#This Row],[Employee]])*(Rebiz!C:C=Table2[[#This Row],[Date]]),Rebiz!F:F,"")} -> 46296.721 | R33: {=_xlfn.XLOOKUP(1,(Rebiz!A:A=Table2[[#This Row],[Employee]])*(Rebiz!C:C=Table2[[#This Row],[Date]]),Rebiz!G:G,"")} -> 6:22 | S33: {=_xlfn.XLOOKUP(1,(Rebiz!A:A=Table2[[#This Row],[Employee]])*(Rebiz!C:C=Table2[[#This Row],[Date]]),Rebiz!H:H,"")} -> 3:22 | T33: {=_xlfn.XLOOKUP(1,(Rebiz!A:A=Table2[[#This Row],[Employee]])*(Rebiz!C:C=Table2[[#This Row],[Date]]),Rebiz!I:I,"")} -> 3:0 | U33: {=_xlfn.XLOOKUP(1,(Rebiz!A:A=Table2[[#This Row],[Employee]])*(Rebiz!C:C=Table2[[#This Row],[Date]]),Rebiz!J:J,"")} -> 0:0 | V33: {=_xlfn.XLOOKUP(1,(Rebiz!A:A=Table2[[#This Row],[Employee]])*(Rebiz!C:C=Table2[[#This Row],[Date]]),Rebiz!K:K,"")} -> Y
A34: Central | B34: KS/OK | C34: Ardmore | D34: MICHAEL RODRIGUEZ | E34: MOBILE ASSOCIATE | F34: 46296 | G34: 0.5 | H34: 0.83333333 | I34: 0.50353009 | J34: 0.8505787 | K34: 7 | L34: 7.8361111 | M34: 1 | N34: 29.583333 | O34: Late Clock Out | P34: {=_xlfn.XLOOKUP(1,(Rebiz!A:A=Table2[[#This Row],[Employee]])*(Rebiz!C:C=Table2[[#This Row],[Date]]),Rebiz!E:E,"")} | Q34: {=_xlfn.XLOOKUP(1,(Rebiz!A:A=Table2[[#This Row],[Employee]])*(Rebiz!C:C=Table2[[#This Row],[Date]]),Rebiz!F:F,"")} | R34: {=_xlfn.XLOOKUP(1,(Rebiz!A:A=Table2[[#This Row],[Employee]])*(Rebiz!C:C=Table2[[#This Row],[Date]]),Rebiz!G:G,"")} | S34: {=_xlfn.XLOOKUP(1,(Rebiz!A:A=Table2[[#This Row],[Employee]])*(Rebiz!C:C=Table2[[#This Row],[Date]]),Rebiz!H:H,"")} | T34: {=_xlfn.XLOOKUP(1,(Rebiz!A:A=Table2[[#This Row],[Employee]])*(Rebiz!C:C=Table2[[#This Row],[Date]]),Rebiz!I:I,"")} | U34: {=_xlfn.XLOOKUP(1,(Rebiz!A:A=Table2[[#This Row],[Employee]])*(Rebiz!C:C=Table2[[#This Row],[Date]]),Rebiz!J:J,"")} | V34: {=_xlfn.XLOOKUP(1,(Rebiz!A:A=Table2[[#This Row],[Employee]])*(Rebiz!C:C=Table2[[#This Row],[Date]]),Rebiz!K:K,"")}
A35: Central | B35: KS/OK | C35: Owen Garriott | D35: KEVIN DE LA TORRE | E35: MOBILE ASSOCIATE | F35: 46296 | G35: 0.45833333 | H35: 0.75 | I35: 0.45747685 | J35: 0.74844907 | K35: 6.5 | L35: 6.475 | M35: 1 | N35: 30.5 | O35: On Time | P35: {=_xlfn.XLOOKUP(1,(Rebiz!A:A=Table2[[#This Row],[Employee]])*(Rebiz!C:C=Table2[[#This Row],[Date]]),Rebiz!E:E,"")} -> 46296.46 | Q35: {=_xlfn.XLOOKUP(1,(Rebiz!A:A=Table2[[#This Row],[Employee]])*(Rebiz!C:C=Table2[[#This Row],[Date]]),Rebiz!F:F,"")} -> 46296.75 | R35: {=_xlfn.XLOOKUP(1,(Rebiz!A:A=Table2[[#This Row],[Employee]])*(Rebiz!C:C=Table2[[#This Row],[Date]]),Rebiz!G:G,"")} -> 6:28 | S35: {=_xlfn.XLOOKUP(1,(Rebiz!A:A=Table2[[#This Row],[Employee]])*(Rebiz!C:C=Table2[[#This Row],[Date]]),Rebiz!H:H,"")} -> 6:22 | T35: {=_xlfn.XLOOKUP(1,(Rebiz!A:A=Table2[[#This Row],[Employee]])*(Rebiz!C:C=Table2[[#This Row],[Date]]),Rebiz!I:I,"")} -> 0:6 | U35: {=_xlfn.XLOOKUP(1,(Rebiz!A:A=Table2[[#This Row],[Employee]])*(Rebiz!C:C=Table2[[#This Row],[Date]]),Rebiz!J:J,"")} -> 0:30 | V35: {=_xlfn.XLOOKUP(1,(Rebiz!A:A=Table2[[#This Row],[Employee]])*(Rebiz!C:C=Table2[[#This Row],[Date]]),Rebiz!K:K,"")} -> Y
A36: Central | B36: South TX/RGV | C36: Rockport | D36: AVERY STRUBE | E36: MOBILE ASSOCIATE | F36: 46296 | G36: 0.5 | H36: 0.75 | I36: 0.50003472 | J36: 0.77710648 | K36: 5.5 | L36: 6.1461111 | M36: 1 | N36: 30.216667 | O36: Late Clock Out | P36: {=_xlfn.XLOOKUP(1,(Rebiz!A:A=Table2[[#This Row],[Employee]])*(Rebiz!C:C=Table2[[#This Row],[Date]]),Rebiz!E:E,"")} -> 46296.5 | Q36: {=_xlfn.XLOOKUP(1,(Rebiz!A:A=Table2[[#This Row],[Employee]])*(Rebiz!C:C=Table2[[#This Row],[Date]]),Rebiz!F:F,"")} -> 46296.781 | R36: {=_xlfn.XLOOKUP(1,(Rebiz!A:A=Table2[[#This Row],[Employee]])*(Rebiz!C:C=Table2[[#This Row],[Date]]),Rebiz!G:G,"")} -> 6:22 | S36: {=_xlfn.XLOOKUP(1,(Rebiz!A:A=Table2[[#This Row],[Employee]])*(Rebiz!C:C=Table2[[#This Row],[Date]]),Rebiz!H:H,"")} -> 6:4 | T36: {=_xlfn.XLOOKUP(1,(Rebiz!A:A=Table2[[#This Row],[Employee]])*(Rebiz!C:C=Table2[[#This Row],[Date]]),Rebiz!I:I,"")} -> 0:18 | U36: {=_xlfn.XLOOKUP(1,(Rebiz!A:A=Table2[[#This Row],[Employee]])*(Rebiz!C:C=Table2[[#This Row],[Date]]),Rebiz!J:J,"")} -> 0:22 | V36: {=_xlfn.XLOOKUP(1,(Rebiz!A:A=Table2[[#This Row],[Employee]])*(Rebiz!C:C=Table2[[#This Row],[Date]]),Rebiz!K:K,"")} -> Y
A37: Central | B37: DFW North | C37: Granbury | D37: JONATHAN LOPEZ | E37: MOBILE ASSOCIATE | F37: 46296 | G37: 0.47916667 | H37: 0.85416667 | I37: 0.45244213 | J37: 0.83626157 | K37: 8 | L37: 8.1291667 | M37: 1 | N37: 64.95 | O37: Early Clock In, Early Clock Out | P37: {=_xlfn.XLOOKUP(1,(Rebiz!A:A=Table2[[#This Row],[Employee]])*(Rebiz!C:C=Table2[[#This Row],[Date]]),Rebiz!E:E,"")} -> 46296.454 | Q37: {=_xlfn.XLOOKUP(1,(Rebiz!A:A=Table2[[#This Row],[Employee]])*(Rebiz!C:C=Table2[[#This Row],[Date]]),Rebiz!F:F,"")} -> 46296.839 | R37: {=_xlfn.XLOOKUP(1,(Rebiz!A:A=Table2[[#This Row],[Employee]])*(Rebiz!C:C=Table2[[#This Row],[Date]]),Rebiz!G:G,"")} -> 8:6 | S37: {=_xlfn.XLOOKUP(1,(Rebiz!A:A=Table2[[#This Row],[Employee]])*(Rebiz!C:C=Table2[[#This Row],[Date]]),Rebiz!H:H,"")} -> 7:21 | T37: {=_xlfn.XLOOKUP(1,(Rebiz!A:A=Table2[[#This Row],[Employee]])*(Rebiz!C:C=Table2[[#This Row],[Date]]),Rebiz!I:I,"")} -> 0:45 | U37: {=_xlfn.XLOOKUP(1,(Rebiz!A:A=Table2[[#This Row],[Employee]])*(Rebiz!C:C=Table2[[#This Row],[Date]]),Rebiz!J:J,"")} -> 1:8 | V37: {=_xlfn.XLOOKUP(1,(Rebiz!A:A=Table2[[#This Row],[Employee]])*(Rebiz!C:C=Table2[[#This Row],[Date]]),Rebiz!K:K,"")} -> Y
A38: Central | B38: MO/IA/NE | C38: Hannibal | D38: XANDER MARTIN | E38: MOBILE ASSOCIATE | F38: 46296 | G38: 0.5 | H38: 0.85416667 | K38: 8 | L38: 0 | M38: 0 | N38: 0 | O38: No Show | P38: {=_xlfn.XLOOKUP(1,(Rebiz!A:A=Table2[[#This Row],[Employee]])*(Rebiz!C:C=Table2[[#This Row],[Date]]),Rebiz!E:E,"")} | Q38: {=_xlfn.XLOOKUP(1,(Rebiz!A:A=Table2[[#This Row],[Employee]])*(Rebiz!C:C=Table2[[#This Row],[Date]]),Rebiz!F:F,"")} | R38: {=_xlfn.XLOOKUP(1,(Rebiz!A:A=Table2[[#This Row],[Employee]])*(Rebiz!C:C=Table2[[#This Row],[Date]]),Rebiz!G:G,"")} | S38: {=_xlfn.XLOOKUP(1,(Rebiz!A:A=Table2[[#This Row],[Employee]])*(Rebiz!C:C=Table2[[#This Row],[Date]]),Rebiz!H:H,"")} | T38: {=_xlfn.XLOOKUP(1,(Rebiz!A:A=Table2[[#This Row],[Employee]])*(Rebiz!C:C=Table2[[#This Row],[Date]]),Rebiz!I:I,"")} | U38: {=_xlfn.XLOOKUP(1,(Rebiz!A:A=Table2[[#This Row],[Employee]])*(Rebiz!C:C=Table2[[#This Row],[Date]]),Rebiz!J:J,"")} | V38: {=_xlfn.XLOOKUP(1,(Rebiz!A:A=Table2[[#This Row],[Employee]])*(Rebiz!C:C=Table2[[#This Row],[Date]]),Rebiz!K:K,"")}
A39: Central | B39: MO/IA/NE | C39: Center | D39: CLAUDETTE DENNIS | E39: MOBILE ASSOCIATE | F39: 46296 | G39: 0.39583333 | H39: 0.83333333 | I39: 0.39814815 | J39: 0.8371875 | K39: 10 | L39: 10.042222 | M39: 1 | N39: 29.683333 | O39: On Time | P39: {=_xlfn.XLOOKUP(1,(Rebiz!A:A=Table2[[#This Row],[Employee]])*(Rebiz!C:C=Table2[[#This Row],[Date]]),Rebiz!E:E,"")} -> 46296.399 | Q39: {=_xlfn.XLOOKUP(1,(Rebiz!A:A=Table2[[#This Row],[Employee]])*(Rebiz!C:C=Table2[[#This Row],[Date]]),Rebiz!F:F,"")} -> 46296.843 | R39: {=_xlfn.XLOOKUP(1,(Rebiz!A:A=Table2[[#This Row],[Employee]])*(Rebiz!C:C=Table2[[#This Row],[Date]]),Rebiz!G:G,"")} -> 10:40 | S39: {=_xlfn.XLOOKUP(1,(Rebiz!A:A=Table2[[#This Row],[Employee]])*(Rebiz!C:C=Table2[[#This Row],[Date]]),Rebiz!H:H,"")} -> 10:40 | T39: {=_xlfn.XLOOKUP(1,(Rebiz!A:A=Table2[[#This Row],[Employee]])*(Rebiz!C:C=Table2[[#This Row],[Date]]),Rebiz!I:I,"")} -> 0:0 | U39: {=_xlfn.XLOOKUP(1,(Rebiz!A:A=Table2[[#This Row],[Employee]])*(Rebiz!C:C=Table2[[#This Row],[Date]]),Rebiz!J:J,"")} -> 0:0 | V39: {=_xlfn.XLOOKUP(1,(Rebiz!A:A=Table2[[#This Row],[Employee]])*(Rebiz!C:C=Table2[[#This Row],[Date]]),Rebiz!K:K,"")} -> Y
A40: Central | B40: MO/IA/NE | C40: King Lane | D40: JEFFREY SURA | E40: MOBILE ASSOCIATE | F40: 46296 | G40: 0.375 | H40: 0.70833333 | I40: 0.38459491 | J40: 0.72356481 | K40: 7.5 | L40: 7.5933333 | M40: 1 | N40: 32.516667 | O40: Late Clock Out, Late Clock In | P40: {=_xlfn.XLOOKUP(1,(Rebiz!A:A=Table2[[#This Row],[Employee]])*(Rebiz!C:C=Table2[[#This Row],[Date]]),Rebiz!E:E,"")} -> 46296.387 | Q40: {=_xlfn.XLOOKUP(1,(Rebiz!A:A=Table2[[#This Row],[Employee]])*(Rebiz!C:C=Table2[[#This Row],[Date]]),Rebiz!F:F,"")} -> 46296.726 | R40: {=_xlfn.XLOOKUP(1,(Rebiz!A:A=Table2[[#This Row],[Employee]])*(Rebiz!C:C=Table2[[#This Row],[Date]]),Rebiz!G:G,"")} -> 8:8 | S40: {=_xlfn.XLOOKUP(1,(Rebiz!A:A=Table2[[#This Row],[Employee]])*(Rebiz!C:C=Table2[[#This Row],[Date]]),Rebiz!H:H,"")} -> 5:23 | T40: {=_xlfn.XLOOKUP(1,(Rebiz!A:A=Table2[[#This Row],[Employee]])*(Rebiz!C:C=Table2[[#This Row],[Date]]),Rebiz!I:I,"")} -> 2:45 | U40: {=_xlfn.XLOOKUP(1,(Rebiz!A:A=Table2[[#This Row],[Employee]])*(Rebiz!C:C=Table2[[#This Row],[Date]]),Rebiz!J:J,"")} -> 0:0 | V40: {=_xlfn.XLOOKUP(1,(Rebiz!A:A=Table2[[#This Row],[Employee]])*(Rebiz!C:C=Table2[[#This Row],[Date]]),Rebiz!K:K,"")} -> Y
A41: Central | B41: DFW North | C41: Weatherford | D41: ASHLEY RATEL | E41: MOBILE ASSOCIATE | F41: 46296 | G41: 0.5 | H41: 0.84375 | I41: 0.37203704 | J41: 0.8359375 | K41: 7.25 | L41: 10.158889 | M41: 2 | N41: 58.483333 | O41: Early Clock In, Early Clock Out | P41: {=_xlfn.XLOOKUP(1,(Rebiz!A:A=Table2[[#This Row],[Employee]])*(Rebiz!C:C=Table2[[#This Row],[Date]]),Rebiz!E:E,"")} | Q41: {=_xlfn.XLOOKUP(1,(Rebiz!A:A=Table2[[#This Row],[Employee]])*(Rebiz!C:C=Table2[[#This Row],[Date]]),Rebiz!F:F,"")} | R41: {=_xlfn.XLOOKUP(1,(Rebiz!A:A=Table2[[#This Row],[Employee]])*(Rebiz!C:C=Table2[[#This Row],[Date]]),Rebiz!G:G,"")} | S41: {=_xlfn.XLOOKUP(1,(Rebiz!A:A=Table2[[#This Row],[Employee]])*(Rebiz!C:C=Table2[[#This Row],[Date]]),Rebiz!H:H,"")} | T41: {=_xlfn.XLOOKUP(1,(Rebiz!A:A=Table2[[#This Row],[Employee]])*(Rebiz!C:C=Table2[[#This Row],[Date]]),Rebiz!I:I,"")} | U41: {=_xlfn.XLOOKUP(1,(Rebiz!A:A=Table2[[#This Row],[Employee]])*(Rebiz!C:C=Table2[[#This Row],[Date]]),Rebiz!J:J,"")} | V41: {=_xlfn.XLOOKUP(1,(Rebiz!A:A=Table2[[#This Row],[Employee]])*(Rebiz!C:C=Table2[[#This Row],[Date]]),Rebiz!K:K,"")}
A42: Central | B42: DFW North | C42: Weatherford | D42: ASHLEY RATEL | E42: MOBILE ASSOCIATE | F42: 46296 | G42: 0.375 | H42: 0.41666667 | I42: 0.37203704 | J42: 0.8359375 | K42: 1 | L42: 10.158889 | M42: 2 | N42: 58.483333 | O42: Late Clock Out | P42: {=_xlfn.XLOOKUP(1,(Rebiz!A:A=Table2[[#This Row],[Employee]])*(Rebiz!C:C=Table2[[#This Row],[Date]]),Rebiz!E:E,"")} | Q42: {=_xlfn.XLOOKUP(1,(Rebiz!A:A=Table2[[#This Row],[Employee]])*(Rebiz!C:C=Table2[[#This Row],[Date]]),Rebiz!F:F,"")} | R42: {=_xlfn.XLOOKUP(1,(Rebiz!A:A=Table2[[#This Row],[Employee]])*(Rebiz!C:C=Table2[[#This Row],[Date]]),Rebiz!G:G,"")} | S42: {=_xlfn.XLOOKUP(1,(Rebiz!A:A=Table2[[#This Row],[Employee]])*(Rebiz!C:C=Table2[[#This Row],[Date]]),Rebiz!H:H,"")} | T42: {=_xlfn.XLOOKUP(1,(Rebiz!A:A=Table2[[#This Row],[Employee]])*(Rebiz!C:C=Table2[[#This Row],[Date]]),Rebiz!I:I,"")} | U42: {=_xlfn.XLOOKUP(1,(Rebiz!A:A=Table2[[#This Row],[Employee]])*(Rebiz!C:C=Table2[[#This Row],[Date]]),Rebiz!J:J,"")} | V42: {=_xlfn.XLOOKUP(1,(Rebiz!A:A=Table2[[#This Row],[Employee]])*(Rebiz!C:C=Table2[[#This Row],[Date]]),Rebiz!K:K,"")}
A43: Central | B43: MO/IA/NE | C43: Jeff City | D43: JAYLEN LEAVELL | E43: MOBILE ASSOCIATE | F43: 46296 | G43: 0.45833333 | H43: 0.80208333 | I43: 0.50414352 | J43: 0.85748843 | K43: 7.75 | L43: 8.4802778 | M43: 0 | N43: 0 | O43: Late Clock Out, Late Clock In | P43: {=_xlfn.XLOOKUP(1,(Rebiz!A:A=Table2[[#This Row],[Employee]])*(Rebiz!C:C=Table2[[#This Row],[Date]]),Rebiz!E:E,"")} -> 46296.504 | Q43: {=_xlfn.XLOOKUP(1,(Rebiz!A:A=Table2[[#This Row],[Employee]])*(Rebiz!C:C=Table2[[#This Row],[Date]]),Rebiz!F:F,"")} -> 46296.858 | R43: {=_xlfn.XLOOKUP(1,(Rebiz!A:A=Table2[[#This Row],[Employee]])*(Rebiz!C:C=Table2[[#This Row],[Date]]),Rebiz!G:G,"")} -> 8:30 | S43: {=_xlfn.XLOOKUP(1,(Rebiz!A:A=Table2[[#This Row],[Employee]])*(Rebiz!C:C=Table2[[#This Row],[Date]]),Rebiz!H:H,"")} -> 7:54 | T43: {=_xlfn.XLOOKUP(1,(Rebiz!A:A=Table2[[#This Row],[Employee]])*(Rebiz!C:C=Table2[[#This Row],[Date]]),Rebiz!I:I,"")} -> 0:36 | U43: {=_xlfn.XLOOKUP(1,(Rebiz!A:A=Table2[[#This Row],[Employee]])*(Rebiz!C:C=Table2[[#This Row],[Date]]),Rebiz!J:J,"")} -> 0:0 | V43: {=_xlfn.XLOOKUP(1,(Rebiz!A:A=Table2[[#This Row],[Employee]])*(Rebiz!C:C=Table2[[#This Row],[Date]]),Rebiz!K:K,"")} -> Y
A44: Central | B44: Central Texas | C44: Bryan | D44: EMILY THIGPEN | E44: MOBILE ASSOCIATE | F44: 46296 | G44: 0.45833333 | H44: 0.77083333 | I44: 0.46248843 | J44: 0.78347222 | K44: 6.5 | L44: 6.6430556 | M44: 1 | N44: 63.633333 | O44: Late Clock Out | P44: {=_xlfn.XLOOKUP(1,(Rebiz!A:A=Table2[[#This Row],[Employee]])*(Rebiz!C:C=Table2[[#This Row],[Date]]),Rebiz!E:E,"")} -> 46296.463 | Q44: {=_xlfn.XLOOKUP(1,(Rebiz!A:A=Table2[[#This Row],[Employee]])*(Rebiz!C:C=Table2[[#This Row],[Date]]),Rebiz!F:F,"")} -> 46296.786 | R44: {=_xlfn.XLOOKUP(1,(Rebiz!A:A=Table2[[#This Row],[Employee]])*(Rebiz!C:C=Table2[[#This Row],[Date]]),Rebiz!G:G,"")} -> 6:42 | S44: {=_xlfn.XLOOKUP(1,(Rebiz!A:A=Table2[[#This Row],[Employee]])*(Rebiz!C:C=Table2[[#This Row],[Date]]),Rebiz!H:H,"")} -> 6:42 | T44: {=_xlfn.XLOOKUP(1,(Rebiz!A:A=Table2[[#This Row],[Employee]])*(Rebiz!C:C=Table2[[#This Row],[Date]]),Rebiz!I:I,"")} -> 0:0 | U44: {=_xlfn.XLOOKUP(1,(Rebiz!A:A=Table2[[#This Row],[Employee]])*(Rebiz!C:C=Table2[[#This Row],[Date]]),Rebiz!J:J,"")} -> 1:3 | V44: {=_xlfn.XLOOKUP(1,(Rebiz!A:A=Table2[[#This Row],[Employee]])*(Rebiz!C:C=Table2[[#This Row],[Date]]),Rebiz!K:K,"")} -> Y
A45: Central | B45: DFW North | C45: Seventh Ave | D45: SALOME GUERRA | E45: MOBILE ASSOCIATE | F45: 46296 | G45: 0.39583333 | H45: 0.70833333 | I45: 0.4 | J45: 0.66606481 | K45: 7 | L45: 5.5261111 | M45: 1 | N45: 51.566667 | O45: Early Clock Out | P45: {=_xlfn.XLOOKUP(1,(Rebiz!A:A=Table2[[#This Row],[Employee]])*(Rebiz!C:C=Table2[[#This Row],[Date]]),Rebiz!E:E,"")} -> 46296.401 | Q45: {=_xlfn.XLOOKUP(1,(Rebiz!A:A=Table2[[#This Row],[Employee]])*(Rebiz!C:C=Table2[[#This Row],[Date]]),Rebiz!F:F,"")} -> 46296.667 | R45: {=_xlfn.XLOOKUP(1,(Rebiz!A:A=Table2[[#This Row],[Employee]])*(Rebiz!C:C=Table2[[#This Row],[Date]]),Rebiz!G:G,"")} -> 5:31 | S45: {=_xlfn.XLOOKUP(1,(Rebiz!A:A=Table2[[#This Row],[Employee]])*(Rebiz!C:C=Table2[[#This Row],[Date]]),Rebiz!H:H,"")} -> 5:31 | T45: {=_xlfn.XLOOKUP(1,(Rebiz!A:A=Table2[[#This Row],[Employee]])*(Rebiz!C:C=Table2[[#This Row],[Date]]),Rebiz!I:I,"")} -> 0:0 | U45: {=_xlfn.XLOOKUP(1,(Rebiz!A:A=Table2[[#This Row],[Employee]])*(Rebiz!C:C=Table2[[#This Row],[Date]]),Rebiz!J:J,"")} -> 0:51 | V45: {=_xlfn.XLOOKUP(1,(Rebiz!A:A=Table2[[#This Row],[Employee]])*(Rebiz!C:C=Table2[[#This Row],[Date]]),Rebiz!K:K,"")} -> Y
A46: Central | B46: West Texas | C46: Midland | D46: ALEXANDER ASHBY | E46: MOBILE ASSOCIATE | F46: 46296 | G46: 0.45833333 | H46: 0.85416667 | I46: 0.45717593 | J46: 0.84788194 | K46: 8.5 | L46: 8.3680556 | M46: 1 | N46: 60.533333 | O46: On Time | P46: {=_xlfn.XLOOKUP(1,(Rebiz!A:A=Table2[[#This Row],[Employee]])*(Rebiz!C:C=Table2[[#This Row],[Date]]),Rebiz!E:E,"")} -> 46296.46 | Q46: {=_xlfn.XLOOKUP(1,(Rebiz!A:A=Table2[[#This Row],[Employee]])*(Rebiz!C:C=Table2[[#This Row],[Date]]),Rebiz!F:F,"")} -> 46296.852 | R46: {=_xlfn.XLOOKUP(1,(Rebiz!A:A=Table2[[#This Row],[Employee]])*(Rebiz!C:C=Table2[[#This Row],[Date]]),Rebiz!G:G,"")} -> 8:24 | S46: {=_xlfn.XLOOKUP(1,(Rebiz!A:A=Table2[[#This Row],[Employee]])*(Rebiz!C:C=Table2[[#This Row],[Date]]),Rebiz!H:H,"")} -> 7:30 | T46: {=_xlfn.XLOOKUP(1,(Rebiz!A:A=Table2[[#This Row],[Employee]])*(Rebiz!C:C=Table2[[#This Row],[Date]]),Rebiz!I:I,"")} -> 0:54 | U46: {=_xlfn.XLOOKUP(1,(Rebiz!A:A=Table2[[#This Row],[Employee]])*(Rebiz!C:C=Table2[[#This Row],[Date]]),Rebiz!J:J,"")} -> 1:1 | V46: {=_xlfn.XLOOKUP(1,(Rebiz!A:A=Table2[[#This Row],[Employee]])*(Rebiz!C:C=Table2[[#This Row],[Date]]),Rebiz!K:K,"")} -> Y
A47: Central | B47: MO/IA/NE | C47: Dubuque | D47: PAIGE JONES | E47: MOBILE ASSOCIATE | F47: 46296 | I47: 0.66466435 | J47: 0.71731481 | K47: 0 | L47: 1.2636111 | M47: 0 | N47: 0 | O47: Not Scheduled | P47: {=_xlfn.XLOOKUP(1,(Rebiz!A:A=Table2[[#This Row],[Employee]])*(Rebiz!C:C=Table2[[#This Row],[Date]]),Rebiz!E:E,"")} -> 46296.652 | Q47: {=_xlfn.XLOOKUP(1,(Rebiz!A:A=Table2[[#This Row],[Employee]])*(Rebiz!C:C=Table2[[#This Row],[Date]]),Rebiz!F:F,"")} -> 46296.722 | R47: {=_xlfn.XLOOKUP(1,(Rebiz!A:A=Table2[[#This Row],[Employee]])*(Rebiz!C:C=Table2[[#This Row],[Date]]),Rebiz!G:G,"")} -> 1:41 | S47: {=_xlfn.XLOOKUP(1,(Rebiz!A:A=Table2[[#This Row],[Employee]])*(Rebiz!C:C=Table2[[#This Row],[Date]]),Rebiz!H:H,"")} -> 1:38 | T47: {=_xlfn.XLOOKUP(1,(Rebiz!A:A=Table2[[#This Row],[Employee]])*(Rebiz!C:C=Table2[[#This Row],[Date]]),Rebiz!I:I,"")} -> 0:3 | U47: {=_xlfn.XLOOKUP(1,(Rebiz!A:A=Table2[[#This Row],[Employee]])*(Rebiz!C:C=Table2[[#This Row],[Date]]),Rebiz!J:J,"")} -> 0:0 | V47: {=_xlfn.XLOOKUP(1,(Rebiz!A:A=Table2[[#This Row],[Employee]])*(Rebiz!C:C=Table2[[#This Row],[Date]]),Rebiz!K:K,"")} -> Y
A48: Central | B48: West Texas | C48: Midland | D48: LILY FRIED | E48: MOBILE ASSOCIATE | F48: 46296 | G48: 0.45833333 | H48: 0.77083333 | I48: 0.37774306 | J48: 0.71028935 | K48: 6.5 | L48: 7.1786111 | M48: 1 | N48: 48.15 | O48: Early Clock In, Early Clock Out | P48: {=_xlfn.XLOOKUP(1,(Rebiz!A:A=Table2[[#This Row],[Employee]])*(Rebiz!C:C=Table2[[#This Row],[Date]]),Rebiz!E:E,"")} | Q48: {=_xlfn.XLOOKUP(1,(Rebiz!A:A=Table2[[#This Row],[Employee]])*(Rebiz!C:C=Table2[[#This Row],[Date]]),Rebiz!F:F,"")} | R48: {=_xlfn.XLOOKUP(1,(Rebiz!A:A=Table2[[#This Row],[Employee]])*(Rebiz!C:C=Table2[[#This Row],[Date]]),Rebiz!G:G,"")} | S48: {=_xlfn.XLOOKUP(1,(Rebiz!A:A=Table2[[#This Row],[Employee]])*(Rebiz!C:C=Table2[[#This Row],[Date]]),Rebiz!H:H,"")} | T48: {=_xlfn.XLOOKUP(1,(Rebiz!A:A=Table2[[#This Row],[Employee]])*(Rebiz!C:C=Table2[[#This Row],[Date]]),Rebiz!I:I,"")} | U48: {=_xlfn.XLOOKUP(1,(Rebiz!A:A=Table2[[#This Row],[Employee]])*(Rebiz!C:C=Table2[[#This Row],[Date]]),Rebiz!J:J,"")} | V48: {=_xlfn.XLOOKUP(1,(Rebiz!A:A=Table2[[#This Row],[Employee]])*(Rebiz!C:C=Table2[[#This Row],[Date]]),Rebiz!K:K,"")}
A49: Central | B49: South TX/RGV | C49: Victoria | D49: SAGE DIGMAN | E49: MOBILE ASSOCIATE | F49: 46296 | I49: 0.41333333 | J49: 0.71189815 | K49: 0 | L49: 6.2733333 | M49: 1 | N49: 53.533333 | O49: Not Scheduled | P49: {=_xlfn.XLOOKUP(1,(Rebiz!A:A=Table2[[#This Row],[Employee]])*(Rebiz!C:C=Table2[[#This Row],[Date]]),Rebiz!E:E,"")} -> 46296.415 | Q49: {=_xlfn.XLOOKUP(1,(Rebiz!A:A=Table2[[#This Row],[Employee]])*(Rebiz!C:C=Table2[[#This Row],[Date]]),Rebiz!F:F,"")} -> 46296.714 | R49: {=_xlfn.XLOOKUP(1,(Rebiz!A:A=Table2[[#This Row],[Employee]])*(Rebiz!C:C=Table2[[#This Row],[Date]]),Rebiz!G:G,"")} -> 6:18 | S49: {=_xlfn.XLOOKUP(1,(Rebiz!A:A=Table2[[#This Row],[Employee]])*(Rebiz!C:C=Table2[[#This Row],[Date]]),Rebiz!H:H,"")} -> 5:30 | T49: {=_xlfn.XLOOKUP(1,(Rebiz!A:A=Table2[[#This Row],[Employee]])*(Rebiz!C:C=Table2[[#This Row],[Date]]),Rebiz!I:I,"")} -> 0:48 | U49: {=_xlfn.XLOOKUP(1,(Rebiz!A:A=Table2[[#This Row],[Employee]])*(Rebiz!C:C=Table2[[#This Row],[Date]]),Rebiz!J:J,"")} -> 0:53 | V49: {=_xlfn.XLOOKUP(1,(Rebiz!A:A=Table2[[#This Row],[Employee]])*(Rebiz!C:C=Table2[[#This Row],[Date]]),Rebiz!K:K,"")} -> Y
A50: Central | B50: DFW North | C50: Weatherford | D50: WENDY BURGE | E50: MOBILE ASSOCIATE | F50: 46296 | G50: 0.375 | H50: 0.41666667 | I50: 0.37248843 | J50: 0.42616898 | K50: 1 | L50: 1.2883333 | M50: 0 | N50: 0 | O50: On Time | P50: {=_xlfn.XLOOKUP(1,(Rebiz!A:A=Table2[[#This Row],[Employee]])*(Rebiz!C:C=Table2[[#This Row],[Date]]),Rebiz!E:E,"")} -> 46296.376 | Q50: {=_xlfn.XLOOKUP(1,(Rebiz!A:A=Table2[[#This Row],[Employee]])*(Rebiz!C:C=Table2[[#This Row],[Date]]),Rebiz!F:F,"")} -> 46296.429 | R50: {=_xlfn.XLOOKUP(1,(Rebiz!A:A=Table2[[#This Row],[Employee]])*(Rebiz!C:C=Table2[[#This Row],[Date]]),Rebiz!G:G,"")} -> 1:17 | S50: {=_xlfn.XLOOKUP(1,(Rebiz!A:A=Table2[[#This Row],[Employee]])*(Rebiz!C:C=Table2[[#This Row],[Date]]),Rebiz!H:H,"")} -> 0:59 | T50: {=_xlfn.XLOOKUP(1,(Rebiz!A:A=Table2[[#This Row],[Employee]])*(Rebiz!C:C=Table2[[#This Row],[Date]]),Rebiz!I:I,"")} -> 0:18 | U50: {=_xlfn.XLOOKUP(1,(Rebiz!A:A=Table2[[#This Row],[Employee]])*(Rebiz!C:C=Table2[[#This Row],[Date]]),Rebiz!J:J,"")} -> 0:0 | V50: {=_xlfn.XLOOKUP(1,(Rebiz!A:A=Table2[[#This Row],[Employee]])*(Rebiz!C:C=Table2[[#This Row],[Date]]),Rebiz!K:K,"")} -> Y
A51: Central | B51: MO/IA/NE | C51: King Lane | D51: VALERIE SCHARTON | E51: MOBILE ASSOCIATE | F51: 46296 | G51: 0.375 | H51: 0.6875 | I51: 0.38461806 | J51: 0.74774306 | K51: 7 | L51: 8.17 | M51: 1 | N51: 32.7 | O51: Late Clock Out, Late Clock In | P51: {=_xlfn.XLOOKUP(1,(Rebiz!A:A=Table2[[#This Row],[Employee]])*(Rebiz!C:C=Table2[[#This Row],[Date]]),Rebiz!E:E,"")} -> 46296.387 | Q51: {=_xlfn.XLOOKUP(1,(Rebiz!A:A=Table2[[#This Row],[Employee]])*(Rebiz!C:C=Table2[[#This Row],[Date]]),Rebiz!F:F,"")} -> 46296.753 | R51: {=_xlfn.XLOOKUP(1,(Rebiz!A:A=Table2[[#This Row],[Employee]])*(Rebiz!C:C=Table2[[#This Row],[Date]]),Rebiz!G:G,"")} -> 8:48 | S51: {=_xlfn.XLOOKUP(1,(Rebiz!A:A=Table2[[#This Row],[Employee]])*(Rebiz!C:C=Table2[[#This Row],[Date]]),Rebiz!H:H,"")} -> 7:39 | T51: {=_xlfn.XLOOKUP(1,(Rebiz!A:A=Table2[[#This Row],[Employee]])*(Rebiz!C:C=Table2[[#This Row],[Date]]),Rebiz!I:I,"")} -> 1:9 | U51: {=_xlfn.XLOOKUP(1,(Rebiz!A:A=Table2[[#This Row],[Employee]])*(Rebiz!C:C=Table2[[#This Row],[Date]]),Rebiz!J:J,"")} -> 0:0 | V51: {=_xlfn.XLOOKUP(1,(Rebiz!A:A=Table2[[#This Row],[Employee]])*(Rebiz!C:C=Table2[[#This Row],[Date]]),Rebiz!K:K,"")} -> Y
A52: Central | B52: SA South | C52: South Bibb | D52: ENRIQUE GONZALEZ | E52: MOBILE EXPERT | F52: 46296 | G52: 0.54166667 | H52: 0.85416667 | I52: 0.53512731 | J52: 0.84873843 | K52: 7 | L52: 7.5266667 | M52: 0 | N52: 0 | O52: On Time | P52: {=_xlfn.XLOOKUP(1,(Rebiz!A:A=Table2[[#This Row],[Employee]])*(Rebiz!C:C=Table2[[#This Row],[Date]]),Rebiz!E:E,"")} -> 46296.535 | Q52: {=_xlfn.XLOOKUP(1,(Rebiz!A:A=Table2[[#This Row],[Employee]])*(Rebiz!C:C=Table2[[#This Row],[Date]]),Rebiz!F:F,"")} -> 46296.851 | R52: {=_xlfn.XLOOKUP(1,(Rebiz!A:A=Table2[[#This Row],[Employee]])*(Rebiz!C:C=Table2[[#This Row],[Date]]),Rebiz!G:G,"")} -> 7:35 | S52: {=_xlfn.XLOOKUP(1,(Rebiz!A:A=Table2[[#This Row],[Employee]])*(Rebiz!C:C=Table2[[#This Row],[Date]]),Rebiz!H:H,"")} -> 7:29 | T52: {=_xlfn.XLOOKUP(1,(Rebiz!A:A=Table2[[#This Row],[Employee]])*(Rebiz!C:C=Table2[[#This Row],[Date]]),Rebiz!I:I,"")} -> 0:6 | U52: {=_xlfn.XLOOKUP(1,(Rebiz!A:A=Table2[[#This Row],[Employee]])*(Rebiz!C:C=Table2[[#This Row],[Date]]),Rebiz!J:J,"")} -> 0:0 | V52: {=_xlfn.XLOOKUP(1,(Rebiz!A:A=Table2[[#This Row],[Employee]])*(Rebiz!C:C=Table2[[#This Row],[Date]]),Rebiz!K:K,"")} -> Y
A53: Central | B53: South TX/RGV | C53: Alice | D53: ERIN MEDINA | E53: MOBILE EXPERT | F53: 46296 | G53: 0.625 | H53: 0.85416667 | I53: 0.62622685 | J53: 0.80287037 | K53: 5.5 | L53: 4.2394444 | M53: 0 | N53: 0 | O53: Early Clock Out | P53: {=_xlfn.XLOOKUP(1,(Rebiz!A:A=Table2[[#This Row],[Employee]])*(Rebiz!C:C=Table2[[#This Row],[Date]]),Rebiz!E:E,"")} -> 46296.627 | Q53: {=_xlfn.XLOOKUP(1,(Rebiz!A:A=Table2[[#This Row],[Employee]])*(Rebiz!C:C=Table2[[#This Row],[Date]]),Rebiz!F:F,"")} -> 46296.804 | R53: {=_xlfn.XLOOKUP(1,(Rebiz!A:A=Table2[[#This Row],[Employee]])*(Rebiz!C:C=Table2[[#This Row],[Date]]),Rebiz!G:G,"")} -> 4:3 | S53: {=_xlfn.XLOOKUP(1,(Rebiz!A:A=Table2[[#This Row],[Employee]])*(Rebiz!C:C=Table2[[#This Row],[Date]]),Rebiz!H:H,"")} -> 4:3 | T53: {=_xlfn.XLOOKUP(1,(Rebiz!A:A=Table2[[#This Row],[Employee]])*(Rebiz!C:C=Table2[[#This Row],[Date]]),Rebiz!I:I,"")} -> 0:0 | U53: {=_xlfn.XLOOKUP(1,(Rebiz!A:A=Table2[[#This Row],[Employee]])*(Rebiz!C:C=Table2[[#This Row],[Date]]),Rebiz!J:J,"")} -> 0:12 | V53: {=_xlfn.XLOOKUP(1,(Rebiz!A:A=Table2[[#This Row],[Employee]])*(Rebiz!C:C=Table2[[#This Row],[Date]]),Rebiz!K:K,"")} -> Y
A54: Central | B54: DFW East | C54: Richardson TX | D54: DESTINEE FLORES | E54: MOBILE EXPERT | F54: 46296 | G54: 0.375 | H54: 0.75 | I54: 0.38549769 | J54: 0.80621528 | K54: 8.5 | L54: 8.9891667 | M54: 1 | N54: 66.483333 | O54: Late Clock Out, Late Clock In | P54: {=_xlfn.XLOOKUP(1,(Rebiz!A:A=Table2[[#This Row],[Employee]])*(Rebiz!C:C=Table2[[#This Row],[Date]]),Rebiz!E:E,"")} -> 46296.399 | Q54: {=_xlfn.XLOOKUP(1,(Rebiz!A:A=Table2[[#This Row],[Employee]])*(Rebiz!C:C=Table2[[#This Row],[Date]]),Rebiz!F:F,"")} -> 46296.806 | R54: {=_xlfn.XLOOKUP(1,(Rebiz!A:A=Table2[[#This Row],[Employee]])*(Rebiz!C:C=Table2[[#This Row],[Date]]),Rebiz!G:G,"")} -> 9:28 | S54: {=_xlfn.XLOOKUP(1,(Rebiz!A:A=Table2[[#This Row],[Employee]])*(Rebiz!C:C=Table2[[#This Row],[Date]]),Rebiz!H:H,"")} -> 8:34 | T54: {=_xlfn.XLOOKUP(1,(Rebiz!A:A=Table2[[#This Row],[Employee]])*(Rebiz!C:C=Table2[[#This Row],[Date]]),Rebiz!I:I,"")} -> 0:54 | U54: {=_xlfn.XLOOKUP(1,(Rebiz!A:A=Table2[[#This Row],[Employee]])*(Rebiz!C:C=Table2[[#This Row],[Date]]),Rebiz!J:J,"")} -> 0:19 | V54: {=_xlfn.XLOOKUP(1,(Rebiz!A:A=Table2[[#This Row],[Employee]])*(Rebiz!C:C=Table2[[#This Row],[Date]]),Rebiz!K:K,"")} -> Y
A55: Central | B55: DFW North | C55: Duncanville | D55: NOEMY HERRERA | E55: MOBILE EXPERT | F55: 46296 | G55: 0.41666667 | H55: 0.75 | I55: 0.42142361 | J55: 0.89594907 | K55: 7.5 | L55: 9.2963889 | M55: 2 | N55: 125.53333 | O55: Late Clock Out | P55: {=_xlfn.XLOOKUP(1,(Rebiz!A:A=Table2[[#This Row],[Employee]])*(Rebiz!C:C=Table2[[#This Row],[Date]]),Rebiz!E:E,"")} -> 46296.425 | Q55: {=_xlfn.XLOOKUP(1,(Rebiz!A:A=Table2[[#This Row],[Employee]])*(Rebiz!C:C=Table2[[#This Row],[Date]]),Rebiz!F:F,"")} -> 46296.877 | R55: {=_xlfn.XLOOKUP(1,(Rebiz!A:A=Table2[[#This Row],[Employee]])*(Rebiz!C:C=Table2[[#This Row],[Date]]),Rebiz!G:G,"")} -> 8:54 | S55: {=_xlfn.XLOOKUP(1,(Rebiz!A:A=Table2[[#This Row],[Employee]])*(Rebiz!C:C=Table2[[#This Row],[Date]]),Rebiz!H:H,"")} -> 7:54 | T55: {=_xlfn.XLOOKUP(1,(Rebiz!A:A=Table2[[#This Row],[Employee]])*(Rebiz!C:C=Table2[[#This Row],[Date]]),Rebiz!I:I,"")} -> 1:0 | U55: {=_xlfn.XLOOKUP(1,(Rebiz!A:A=Table2[[#This Row],[Employee]])*(Rebiz!C:C=Table2[[#This Row],[Date]]),Rebiz!J:J,"")} -> 1:57 | V55: {=_xlfn.XLOOKUP(1,(Rebiz!A:A=Table2[[#This Row],[Employee]])*(Rebiz!C:C=Table2[[#This Row],[Date]]),Rebiz!K:K,"")} -> Y
A56: Central | B56: DFW East | C56: Pines Road | D56: JEREMY HUDSON | E56: MOBILE EXPERT | F56: 46296 | G56: 0.375 | H56: 0.79166667 | I56: 0.38143519 | J56: 0.79166667 | K56: 9.5 | L56: 6.3288889 | M56: 1 | N56: 211 | O56: On Time | P56: {=_xlfn.XLOOKUP(1,(Rebiz!A:A=Table2[[#This Row],[Employee]])*(Rebiz!C:C=Table2[[#This Row],[Date]]),Rebiz!E:E,"")} -> 46296.39 | Q56: {=_xlfn.XLOOKUP(1,(Rebiz!A:A=Table2[[#This Row],[Employee]])*(Rebiz!C:C=Table2[[#This Row],[Date]]),Rebiz!F:F,"")} -> 46296.801 | R56: {=_xlfn.XLOOKUP(1,(Rebiz!A:A=Table2[[#This Row],[Employee]])*(Rebiz!C:C=Table2[[#This Row],[Date]]),Rebiz!G:G,"")} -> 8:23 | S56: {=_xlfn.XLOOKUP(1,(Rebiz!A:A=Table2[[#This Row],[Employee]])*(Rebiz!C:C=Table2[[#This Row],[Date]]),Rebiz!H:H,"")} -> 8:11 | T56: {=_xlfn.XLOOKUP(1,(Rebiz!A:A=Table2[[#This Row],[Employee]])*(Rebiz!C:C=Table2[[#This Row],[Date]]),Rebiz!I:I,"")} -> 0:12 | U56: {=_xlfn.XLOOKUP(1,(Rebiz!A:A=Table2[[#This Row],[Employee]])*(Rebiz!C:C=Table2[[#This Row],[Date]]),Rebiz!J:J,"")} -> 1:30 | V56: {=_xlfn.XLOOKUP(1,(Rebiz!A:A=Table2[[#This Row],[Employee]])*(Rebiz!C:C=Table2[[#This Row],[Date]]),Rebiz!K:K,"")} -> Y
A57: Central | B57: SA/Hill Country | C57: Spring Branch | D57: BENJAMIN CARRION | E57: MOBILE EXPERT | F57: 46296 | G57: 0.54166667 | H57: 0.83333333 | I57: 0.54123843 | J57: 0.8358912 | K57: 6 | L57: 6.0680556 | M57: 1 | N57: 60.216667 | O57: On Time | P57: {=_xlfn.XLOOKUP(1,(Rebiz!A:A=Table2[[#This Row],[Employee]])*(Rebiz!C:C=Table2[[#This Row],[Date]]),Rebiz!E:E,"")} | Q57: {=_xlfn.XLOOKUP(1,(Rebiz!A:A=Table2[[#This Row],[Employee]])*(Rebiz!C:C=Table2[[#This Row],[Date]]),Rebiz!F:F,"")} | R57: {=_xlfn.XLOOKUP(1,(Rebiz!A:A=Table2[[#This Row],[Employee]])*(Rebiz!C:C=Table2[[#This Row],[Date]]),Rebiz!G:G,"")} | S57: {=_xlfn.XLOOKUP(1,(Rebiz!A:A=Table2[[#This Row],[Employee]])*(Rebiz!C:C=Table2[[#This Row],[Date]]),Rebiz!H:H,"")} | T57: {=_xlfn.XLOOKUP(1,(Rebiz!A:A=Table2[[#This Row],[Employee]])*(Rebiz!C:C=Table2[[#This Row],[Date]]),Rebiz!I:I,"")} | U57: {=_xlfn.XLOOKUP(1,(Rebiz!A:A=Table2[[#This Row],[Employee]])*(Rebiz!C:C=Table2[[#This Row],[Date]]),Rebiz!J:J,"")} | V57: {=_xlfn.XLOOKUP(1,(Rebiz!A:A=Table2[[#This Row],[Employee]])*(Rebiz!C:C=Table2[[#This Row],[Date]]),Rebiz!K:K,"")}
A58: Central | B58: Central Texas | C58: Killeen | D58: MICHAEL SIMS-DAVIS | E58: MOBILE EXPERT | F58: 46296 | G58: 0.54166667 | H58: 0.84375 | I58: 0.53834491 | J58: 0.86197917 | K58: 6.75 | L58: 7.1080556 | M58: 1 | N58: 39.55 | O58: Late Clock Out | P58: {=_xlfn.XLOOKUP(1,(Rebiz!A:A=Table2[[#This Row],[Employee]])*(Rebiz!C:C=Table2[[#This Row],[Date]]),Rebiz!E:E,"")} -> 46296.541 | Q58: {=_xlfn.XLOOKUP(1,(Rebiz!A:A=Table2[[#This Row],[Employee]])*(Rebiz!C:C=Table2[[#This Row],[Date]]),Rebiz!F:F,"")} -> 46296.865 | R58: {=_xlfn.XLOOKUP(1,(Rebiz!A:A=Table2[[#This Row],[Employee]])*(Rebiz!C:C=Table2[[#This Row],[Date]]),Rebiz!G:G,"")} -> 7:13 | S58: {=_xlfn.XLOOKUP(1,(Rebiz!A:A=Table2[[#This Row],[Employee]])*(Rebiz!C:C=Table2[[#This Row],[Date]]),Rebiz!H:H,"")} -> 6:58 | T58: {=_xlfn.XLOOKUP(1,(Rebiz!A:A=Table2[[#This Row],[Employee]])*(Rebiz!C:C=Table2[[#This Row],[Date]]),Rebiz!I:I,"")} -> 0:15 | U58: {=_xlfn.XLOOKUP(1,(Rebiz!A:A=Table2[[#This Row],[Employee]])*(Rebiz!C:C=Table2[[#This Row],[Date]]),Rebiz!J:J,"")} -> 0:33 | V58: {=_xlfn.XLOOKUP(1,(Rebiz!A:A=Table2[[#This Row],[Employee]])*(Rebiz!C:C=Table2[[#This Row],[Date]]),Rebiz!K:K,"")} -> Y
A59: Central | B59: MO/IA/NE | C59: Council Bluffs | D59: DAVID BETTGER | E59: MOBILE EXPERT | F59: 46296 | G59: 0.39583333 | H59: 0.85416667 | I59: 0.41288194 | J59: 0.84928241 | K59: 10.5 | L59: 9.9519444 | M59: 1 | N59: 31.3 | O59: Late Clock In | P59: {=_xlfn.XLOOKUP(1,(Rebiz!A:A=Table2[[#This Row],[Employee]])*(Rebiz!C:C=Table2[[#This Row],[Date]]),Rebiz!E:E,"")} -> 46296.412 | Q59: {=_xlfn.XLOOKUP(1,(Rebiz!A:A=Table2[[#This Row],[Employee]])*(Rebiz!C:C=Table2[[#This Row],[Date]]),Rebiz!F:F,"")} -> 46296.852 | R59: {=_xlfn.XLOOKUP(1,(Rebiz!A:A=Table2[[#This Row],[Employee]])*(Rebiz!C:C=Table2[[#This Row],[Date]]),Rebiz!G:G,"")} -> 10:3 | S59: {=_xlfn.XLOOKUP(1,(Rebiz!A:A=Table2[[#This Row],[Employee]])*(Rebiz!C:C=Table2[[#This Row],[Date]]),Rebiz!H:H,"")} -> 9:12 | T59: {=_xlfn.XLOOKUP(1,(Rebiz!A:A=Table2[[#This Row],[Employee]])*(Rebiz!C:C=Table2[[#This Row],[Date]]),Rebiz!I:I,"")} -> 0:51 | U59: {=_xlfn.XLOOKUP(1,(Rebiz!A:A=Table2[[#This Row],[Employee]])*(Rebiz!C:C=Table2[[#This Row],[Date]]),Rebiz!J:J,"")} -> 0:30 | V59: {=_xlfn.XLOOKUP(1,(Rebiz!A:A=Table2[[#This Row],[Employee]])*(Rebiz!C:C=Table2[[#This Row],[Date]]),Rebiz!K:K,"")} -> Y
A60: Central | B60: Central Texas | C60: Marble Falls | D60: MAURO MONTERROSO | E60: MOBILE EXPERT | F60: 46296 | G60: 0.39583333 | H60: 0.70833333 | I60: 0.39594907 | J60: 0.70887731 | K60: 7 | L60: 6.9283333 | M60: 1 | N60: 34.916667 | O60: On Time | P60: {=_xlfn.XLOOKUP(1,(Rebiz!A:A=Table2[[#This Row],[Employee]])*(Rebiz!C:C=Table2[[#This Row],[Date]]),Rebiz!E:E,"")} -> 46296.401 | Q60: {=_xlfn.XLOOKUP(1,(Rebiz!A:A=Table2[[#This Row],[Employee]])*(Rebiz!C:C=Table2[[#This Row],[Date]]),Rebiz!F:F,"")} -> 46296.71 | R60: {=_xlfn.XLOOKUP(1,(Rebiz!A:A=Table2[[#This Row],[Employee]])*(Rebiz!C:C=Table2[[#This Row],[Date]]),Rebiz!G:G,"")} -> 6:49 | S60: {=_xlfn.XLOOKUP(1,(Rebiz!A:A=Table2[[#This Row],[Employee]])*(Rebiz!C:C=Table2[[#This Row],[Date]]),Rebiz!H:H,"")} -> 6:49 | T60: {=_xlfn.XLOOKUP(1,(Rebiz!A:A=Table2[[#This Row],[Employee]])*(Rebiz!C:C=Table2[[#This Row],[Date]]),Rebiz!I:I,"")} -> 0:0 | U60: {=_xlfn.XLOOKUP(1,(Rebiz!A:A=Table2[[#This Row],[Employee]])*(Rebiz!C:C=Table2[[#This Row],[Date]]),Rebiz!J:J,"")} -> 0:36 | V60: {=_xlfn.XLOOKUP(1,(Rebiz!A:A=Table2[[#This Row],[Employee]])*(Rebiz!C:C=Table2[[#This Row],[Date]]),Rebiz!K:K,"")} -> Y
A61: Central | B61: MO/IA/NE | C61: Center | D61: FERNANDO MARTINEZ | E61: MOBILE EXPERT | F61: 46296 | G61: 0.39583333 | H61: 0.85416667 | I61: 0.40162037 | J61: 0.83835648 | K61: 10.5 | L61: 9.9816667 | M61: 1 | N61: 30 | O61: Early Clock Out | P61: {=_xlfn.XLOOKUP(1,(Rebiz!A:A=Table2[[#This Row],[Employee]])*(Rebiz!C:C=Table2[[#This Row],[Date]]),Rebiz!E:E,"")} -> 46296.402 | Q61: {=_xlfn.XLOOKUP(1,(Rebiz!A:A=Table2[[#This Row],[Employee]])*(Rebiz!C:C=Table2[[#This Row],[Date]]),Rebiz!F:F,"")} -> 46296.84 | R61: {=_xlfn.XLOOKUP(1,(Rebiz!A:A=Table2[[#This Row],[Employee]])*(Rebiz!C:C=Table2[[#This Row],[Date]]),Rebiz!G:G,"")} -> 9:39 | S61: {=_xlfn.XLOOKUP(1,(Rebiz!A:A=Table2[[#This Row],[Employee]])*(Rebiz!C:C=Table2[[#This Row],[Date]]),Rebiz!H:H,"")} -> 9:33 | T61: {=_xlfn.XLOOKUP(1,(Rebiz!A:A=Table2[[#This Row],[Employee]])*(Rebiz!C:C=Table2[[#This Row],[Date]]),Rebiz!I:I,"")} -> 0:6 | U61: {=_xlfn.XLOOKUP(1,(Rebiz!A:A=Table2[[#This Row],[Employee]])*(Rebiz!C:C=Table2[[#This Row],[Date]]),Rebiz!J:J,"")} -> 0:52 | V61: {=_xlfn.XLOOKUP(1,(Rebiz!A:A=Table2[[#This Row],[Employee]])*(Rebiz!C:C=Table2[[#This Row],[Date]]),Rebiz!K:K,"")} -> Y
... A64: Central | B64: Central Texas | C64: Copperas Cove | D64: WILBERT ORTIZ | E64: MOBILE EXPERT | F64: 46296 | G64: 0.375 | H64: 0.75 | I64: 0.40262731 | J64: 0.75157407 | K64: 8.5 | L64: 7.3652778 | M64: 1 | N64: 60.566667 | O64: Late Clock In | P64: {=_xlfn.XLOOKUP(1,(Rebiz!A:A=Table2[[#This Row],[Employee]])*(Rebiz!C:C=Table2[[#This Row],[Date]]),Rebiz!E:E,"")} -> 46296.405 | Q64: {=_xlfn.XLOOKUP(1,(Rebiz!A:A=Table2[[#This Row],[Employee]])*(Rebiz!C:C=Table2[[#This Row],[Date]]),Rebiz!F:F,"")} -> 46296.755 | R64: {=_xlfn.XLOOKUP(1,(Rebiz!A:A=Table2[[#This Row],[Employee]])*(Rebiz!C:C=Table2[[#This Row],[Date]]),Rebiz!G:G,"")} -> 6:45 | S64: {=_xlfn.XLOOKUP(1,(Rebiz!A:A=Table2[[#This Row],[Employee]])*(Rebiz!C:C=Table2[[#This Row],[Date]]),Rebiz!H:H,"")} -> 6:33 | T64: {=_xlfn.XLOOKUP(1,(Rebiz!A:A=Table2[[#This Row],[Employee]])*(Rebiz!C:C=Table2[[#This Row],[Date]]),Rebiz!I:I,"")} -> 0:12 | U64: {=_xlfn.XLOOKUP(1,(Rebiz!A:A=Table2[[#This Row],[Employee]])*(Rebiz!C:C=Table2[[#This Row],[Date]]),Rebiz!J:J,"")} -> 1:39 | V64: {=_xlfn.XLOOKUP(1,(Rebiz!A:A=Table2[[#This Row],[Employee]])*(Rebiz!C:C=Table2[[#This Row],[Date]]),Rebiz!K:K,"")} -> Y
A65: Central | B65: West Texas | C65: Farmington | D65: AUDREY ARMES | E65: MOBILE EXPERT | F65: 46296 | I65: 0.42039352 | J65: 0.58076389 | K65: 0 | L65: 3.8488889 | M65: 0 | N65: 0 | O65: Not Scheduled | P65: {=_xlfn.XLOOKUP(1,(Rebiz!A:A=Table2[[#This Row],[Employee]])*(Rebiz!C:C=Table2[[#This Row],[Date]]),Rebiz!E:E,"")} -> 46296.417 | Q65: {=_xlfn.XLOOKUP(1,(Rebiz!A:A=Table2[[#This Row],[Employee]])*(Rebiz!C:C=Table2[[#This Row],[Date]]),Rebiz!F:F,"")} -> 46296.582 | R65: {=_xlfn.XLOOKUP(1,(Rebiz!A:A=Table2[[#This Row],[Employee]])*(Rebiz!C:C=Table2[[#This Row],[Date]]),Rebiz!G:G,"")} -> 3:57 | S65: {=_xlfn.XLOOKUP(1,(Rebiz!A:A=Table2[[#This Row],[Employee]])*(Rebiz!C:C=Table2[[#This Row],[Date]]),Rebiz!H:H,"")} -> 3:57 | T65: {=_xlfn.XLOOKUP(1,(Rebiz!A:A=Table2[[#This Row],[Employee]])*(Rebiz!C:C=Table2[[#This Row],[Date]]),Rebiz!I:I,"")} -> 0:0 | U65: {=_xlfn.XLOOKUP(1,(Rebiz!A:A=Table2[[#This Row],[Employee]])*(Rebiz!C:C=Table2[[#This Row],[Date]]),Rebiz!J:J,"")} -> 0:0 | V65: {=_xlfn.XLOOKUP(1,(Rebiz!A:A=Table2[[#This Row],[Employee]])*(Rebiz!C:C=Table2[[#This Row],[Date]]),Rebiz!K:K,"")} -> Y
A66: Central | B66: West Texas | C66: Olton | D66: JON SILVA | E66: MOBILE EXPERT | F66: 46296 | G66: 0.39583333 | H66: 0.70833333 | I66: 0.39583333 | J66: 0.70888889 | K66: 7 | L66: 7.0188889 | M66: 1 | N66: 29.666667 | O66: On Time | P66: {=_xlfn.XLOOKUP(1,(Rebiz!A:A=Table2[[#This Row],[Employee]])*(Rebiz!C:C=Table2[[#This Row],[Date]]),Rebiz!E:E,"")} -> 46296.397 | Q66: {=_xlfn.XLOOKUP(1,(Rebiz!A:A=Table2[[#This Row],[Employee]])*(Rebiz!C:C=Table2[[#This Row],[Date]]),Rebiz!F:F,"")} -> 46296.71 | R66: {=_xlfn.XLOOKUP(1,(Rebiz!A:A=Table2[[#This Row],[Employee]])*(Rebiz!C:C=Table2[[#This Row],[Date]]),Rebiz!G:G,"")} -> 7:22 | S66: {=_xlfn.XLOOKUP(1,(Rebiz!A:A=Table2[[#This Row],[Employee]])*(Rebiz!C:C=Table2[[#This Row],[Date]]),Rebiz!H:H,"")} -> 7:22 | T66: {=_xlfn.XLOOKUP(1,(Rebiz!A:A=Table2[[#This Row],[Employee]])*(Rebiz!C:C=Table2[[#This Row],[Date]]),Rebiz!I:I,"")} -> 0:0 | U66: {=_xlfn.XLOOKUP(1,(Rebiz!A:A=Table2[[#This Row],[Employee]])*(Rebiz!C:C=Table2[[#This Row],[Date]]),Rebiz!J:J,"")} -> 0:10 | V66: {=_xlfn.XLOOKUP(1,(Rebiz!A:A=Table2[[#This Row],[Employee]])*(Rebiz!C:C=Table2[[#This Row],[Date]]),Rebiz!K:K,"")} -> Y
A67: Central | B67: MO/IA/NE | C67: Hannibal | D67: ELIZABETH LAMME | E67: MOBILE EXPERT | F67: 46296 | G67: 0.39583333 | H67: 0.75 | K67: 8 | L67: 0 | M67: 0 | N67: 0 | O67: No Show | P67: {=_xlfn.XLOOKUP(1,(Rebiz!A:A=Table2[[#This Row],[Employee]])*(Rebiz!C:C=Table2[[#This Row],[Date]]),Rebiz!E:E,"")} | Q67: {=_xlfn.XLOOKUP(1,(Rebiz!A:A=Table2[[#This Row],[Employee]])*(Rebiz!C:C=Table2[[#This Row],[Date]]),Rebiz!F:F,"")} | R67: {=_xlfn.XLOOKUP(1,(Rebiz!A:A=Table2[[#This Row],[Employee]])*(Rebiz!C:C=Table2[[#This Row],[Date]]),Rebiz!G:G,"")} | S67: {=_xlfn.XLOOKUP(1,(Rebiz!A:A=Table2[[#This Row],[Employee]])*(Rebiz!C:C=Table2[[#This Row],[Date]]),Rebiz!H:H,"")} | T67: {=_xlfn.XLOOKUP(1,(Rebiz!A:A=Table2[[#This Row],[Employee]])*(Rebiz!C:C=Table2[[#This Row],[Date]]),Rebiz!I:I,"")} | U67: {=_xlfn.XLOOKUP(1,(Rebiz!A:A=Table2[[#This Row],[Employee]])*(Rebiz!C:C=Table2[[#This Row],[Date]]),Rebiz!J:J,"")} | V67: {=_xlfn.XLOOKUP(1,(Rebiz!A:A=Table2[[#This Row],[Employee]])*(Rebiz!C:C=Table2[[#This Row],[Date]]),Rebiz!K:K,"")}
A68: Central | B68: SA/Hill Country | C68: Thousand Oaks | D68: BRYAN FERDIN | E68: MOBILE EXPERT | F68: 46296 | G68: 0.39583333 | H68: 0.70833333 | I68: 0.54096065 | J68: 0.84145833 | K68: 6.5 | L68: 1.0077778 | M68: 1 | N68: 372.25 | O68: Late Clock Out, Late Clock In | P68: {=_xlfn.XLOOKUP(1,(Rebiz!A:A=Table2[[#This Row],[Employee]])*(Rebiz!C:C=Table2[[#This Row],[Date]]),Rebiz!E:E,"")} -> 46296.393 | Q68: {=_xlfn.XLOOKUP(1,(Rebiz!A:A=Table2[[#This Row],[Employee]])*(Rebiz!C:C=Table2[[#This Row],[Date]]),Rebiz!F:F,"")} -> 46296.844 | R68: {=_xlfn.XLOOKUP(1,(Rebiz!A:A=Table2[[#This Row],[Employee]])*(Rebiz!C:C=Table2[[#This Row],[Date]]),Rebiz!G:G,"")} -> 10:25 | S68: {=_xlfn.XLOOKUP(1,(Rebiz!A:A=Table2[[#This Row],[Employee]])*(Rebiz!C:C=Table2[[#This Row],[Date]]),Rebiz!H:H,"")} -> 10:1 | T68: {=_xlfn.XLOOKUP(1,(Rebiz!A:A=Table2[[#This Row],[Employee]])*(Rebiz!C:C=Table2[[#This Row],[Date]]),Rebiz!I:I,"")} -> 0:24 | U68: {=_xlfn.XLOOKUP(1,(Rebiz!A:A=Table2[[#This Row],[Employee]])*(Rebiz!C:C=Table2[[#This Row],[Date]]),Rebiz!J:J,"")} -> 0:25 | V68: {=_xlfn.XLOOKUP(1,(Rebiz!A:A=Table2[[#This Row],[Employee]])*(Rebiz!C:C=Table2[[#This Row],[Date]]),Rebiz!K:K,"")} -> Y
A69: Central | B69: SA/Hill Country | C69: Cibolo | D69: PAUL REYES | E69: MOBILE EXPERT | F69: 46296 | G69: 0.41666667 | H69: 0.75 | I69: 0.41719907 | J69: 0.76027778 | K69: 7 | L69: 7.2336111 | M69: 1 | N69: 60.016667 | O69: On Time | P69: {=_xlfn.XLOOKUP(1,(Rebiz!A:A=Table2[[#This Row],[Employee]])*(Rebiz!C:C=Table2[[#This Row],[Date]]),Rebiz!E:E,"")} -> 46296.419 | Q69: {=_xlfn.XLOOKUP(1,(Rebiz!A:A=Table2[[#This Row],[Employee]])*(Rebiz!C:C=Table2[[#This Row],[Date]]),Rebiz!F:F,"")} -> 46296.764 | R69: {=_xlfn.XLOOKUP(1,(Rebiz!A:A=Table2[[#This Row],[Employee]])*(Rebiz!C:C=Table2[[#This Row],[Date]]),Rebiz!G:G,"")} -> 8:3 | S69: {=_xlfn.XLOOKUP(1,(Rebiz!A:A=Table2[[#This Row],[Employee]])*(Rebiz!C:C=Table2[[#This Row],[Date]]),Rebiz!H:H,"")} -> 7:30 | T69: {=_xlfn.XLOOKUP(1,(Rebiz!A:A=Table2[[#This Row],[Employee]])*(Rebiz!C:C=Table2[[#This Row],[Date]]),Rebiz!I:I,"")} -> 0:33 | U69: {=_xlfn.XLOOKUP(1,(Rebiz!A:A=Table2[[#This Row],[Employee]])*(Rebiz!C:C=Table2[[#This Row],[Date]]),Rebiz!J:J,"")} -> 0:14 | V69: {=_xlfn.XLOOKUP(1,(Rebiz!A:A=Table2[[#This Row],[Employee]])*(Rebiz!C:C=Table2[[#This Row],[Date]]),Rebiz!K:K,"")} -> Y
A70: Central | B70: SA South | C70: Uvalde | D70: JULIANNA VARGAS | E70: MOBILE EXPERT | F70: 46296 | G70: 0.39583333 | H70: 0.72916667 | I70: 0.39835648 | J70: 0.72763889 | K70: 7 | L70: 6.9219444 | M70: 1 | N70: 58.85 | O70: On Time | P70: {=_xlfn.XLOOKUP(1,(Rebiz!A:A=Table2[[#This Row],[Employee]])*(Rebiz!C:C=Table2[[#This Row],[Date]]),Rebiz!E:E,"")} -> 46296.401 | Q70: {=_xlfn.XLOOKUP(1,(Rebiz!A:A=Table2[[#This Row],[Employee]])*(Rebiz!C:C=Table2[[#This Row],[Date]]),Rebiz!F:F,"")} -> 46296.731 | R70: {=_xlfn.XLOOKUP(1,(Rebiz!A:A=Table2[[#This Row],[Employee]])*(Rebiz!C:C=Table2[[#This Row],[Date]]),Rebiz!G:G,"")} -> 6:55 | S70: {=_xlfn.XLOOKUP(1,(Rebiz!A:A=Table2[[#This Row],[Employee]])*(Rebiz!C:C=Table2[[#This Row],[Date]]),Rebiz!H:H,"")} -> 6:55 | T70: {=_xlfn.XLOOKUP(1,(Rebiz!A:A=Table2[[#This Row],[Employee]])*(Rebiz!C:C=Table2[[#This Row],[Date]]),Rebiz!I:I,"")} -> 0:0 | U70: {=_xlfn.XLOOKUP(1,(Rebiz!A:A=Table2[[#This Row],[Employee]])*(Rebiz!C:C=Table2[[#This Row],[Date]]),Rebiz!J:J,"")} -> 0:59 | V70: {=_xlfn.XLOOKUP(1,(Rebiz!A:A=Table2[[#This Row],[Employee]])*(Rebiz!C:C=Table2[[#This Row],[Date]]),Rebiz!K:K,"")} -> Y
A71: Central | B71: MO/IA/NE | C71: Osage | D71: ANGELA HENRY | E71: MOBILE EXPERT | F71: 46296 | G71: 0.5 | H71: 0.84375 | I71: 0.49190972 | J71: 0.84056713 | K71: 7.75 | L71: 7.8722222 | M71: 1 | N71: 29.733333 | O71: On Time | P71: {=_xlfn.XLOOKUP(1,(Rebiz!A:A=Table2[[#This Row],[Employee]])*(Rebiz!C:C=Table2[[#This Row],[Date]]),Rebiz!E:E,"")} | Q71: {=_xlfn.XLOOKUP(1,(Rebiz!A:A=Table2[[#This Row],[Employee]])*(Rebiz!C:C=Table2[[#This Row],[Date]]),Rebiz!F:F,"")} | R71: {=_xlfn.XLOOKUP(1,(Rebiz!A:A=Table2[[#This Row],[Employee]])*(Rebiz!C:C=Table2[[#This Row],[Date]]),Rebiz!G:G,"")} | S71: {=_xlfn.XLOOKUP(1,(Rebiz!A:A=Table2[[#This Row],[Employee]])*(Rebiz!C:C=Table2[[#This Row],[Date]]),Rebiz!H:H,"")} | T71: {=_xlfn.XLOOKUP(1,(Rebiz!A:A=Table2[[#This Row],[Employee]])*(Rebiz!C:C=Table2[[#This Row],[Date]]),Rebiz!I:I,"")} | U71: {=_xlfn.XLOOKUP(1,(Rebiz!A:A=Table2[[#This Row],[Employee]])*(Rebiz!C:C=Table2[[#This Row],[Date]]),Rebiz!J:J,"")} | V71: {=_xlfn.XLOOKUP(1,(Rebiz!A:A=Table2[[#This Row],[Employee]])*(Rebiz!C:C=Table2[[#This Row],[Date]]),Rebiz!K:K,"")}
A72: Central | B72: Central Texas | C72: Killeen | D72: AUGUST GILES | E72: MOBILE EXPERT | F72: 46296 | G72: 0.375 | H72: 0.70833333 | I72: 0.37471065 | J72: 0.71768519 | K72: 7.5 | L72: 7.6980556 | M72: 1 | N72: 32 | O72: On Time | P72: {=_xlfn.XLOOKUP(1,(Rebiz!A:A=Table2[[#This Row],[Employee]])*(Rebiz!C:C=Table2[[#This Row],[Date]]),Rebiz!E:E,"")} -> 46296.376 | Q72: {=_xlfn.XLOOKUP(1,(Rebiz!A:A=Table2[[#This Row],[Employee]])*(Rebiz!C:C=Table2[[#This Row],[Date]]),Rebiz!F:F,"")} -> 46296.72 | R72: {=_xlfn.XLOOKUP(1,(Rebiz!A:A=Table2[[#This Row],[Employee]])*(Rebiz!C:C=Table2[[#This Row],[Date]]),Rebiz!G:G,"")} -> 8:16 | S72: {=_xlfn.XLOOKUP(1,(Rebiz!A:A=Table2[[#This Row],[Employee]])*(Rebiz!C:C=Table2[[#This Row],[Date]]),Rebiz!H:H,"")} -> 7:34 | T72: {=_xlfn.XLOOKUP(1,(Rebiz!A:A=Table2[[#This Row],[Employee]])*(Rebiz!C:C=Table2[[#This Row],[Date]]),Rebiz!I:I,"")} -> 0:42 | U72: {=_xlfn.XLOOKUP(1,(Rebiz!A:A=Table2[[#This Row],[Employee]])*(Rebiz!C:C=Table2[[#This Row],[Date]]),Rebiz!J:J,"")} -> 0:0 | V72: {=_xlfn.XLOOKUP(1,(Rebiz!A:A=Table2[[#This Row],[Employee]])*(Rebiz!C:C=Table2[[#This Row],[Date]]),Rebiz!K:K,"")} -> Y
A73: Central | B73: South TX/RGV | C73: Rockport | D73: KELLIE SIDES | E73: MOBILE EXPERT | F73: 46296 | G73: 0.5 | H73: 0.85416667 | I73: 0.50018519 | J73: 0.84824074 | K73: 8 | L73: 5.1811111 | M73: 1 | N73: 190.33333 | O73: On Time | P73: {=_xlfn.XLOOKUP(1,(Rebiz!A:A=Table2[[#This Row],[Employee]])*(Rebiz!C:C=Table2[[#This Row],[Date]]),Rebiz!E:E,"")} -> 46296.5 | Q73: {=_xlfn.XLOOKUP(1,(Rebiz!A:A=Table2[[#This Row],[Employee]])*(Rebiz!C:C=Table2[[#This Row],[Date]]),Rebiz!F:F,"")} -> 46296.85 | R73: {=_xlfn.XLOOKUP(1,(Rebiz!A:A=Table2[[#This Row],[Employee]])*(Rebiz!C:C=Table2[[#This Row],[Date]]),Rebiz!G:G,"")} -> 8:24 | S73: {=_xlfn.XLOOKUP(1,(Rebiz!A:A=Table2[[#This Row],[Employee]])*(Rebiz!C:C=Table2[[#This Row],[Date]]),Rebiz!H:H,"")} -> 7:57 | T73: {=_xlfn.XLOOKUP(1,(Rebiz!A:A=Table2[[#This Row],[Employee]])*(Rebiz!C:C=Table2[[#This Row],[Date]]),Rebiz!I:I,"")} -> 0:27 | U73: {=_xlfn.XLOOKUP(1,(Rebiz!A:A=Table2[[#This Row],[Employee]])*(Rebiz!C:C=Table2[[#This Row],[Date]]),Rebiz!J:J,"")} -> 0:0 | V73: {=_xlfn.XLOOKUP(1,(Rebiz!A:A=Table2[[#This Row],[Employee]])*(Rebiz!C:C=Table2[[#This Row],[Date]]),Rebiz!K:K,"")} -> Y
A74: Central | B74: KS/OK | C74: Sapulpa | D74: YERSONN CASTELLANOS | E74: MOBILE EXPERT | F74: 46296 | G74: 0.41666667 | H74: 0.84722222 | I74: 0.41666667 | J74: 0.81372685 | K74: 8.8333333 | L74: 8.8125 | M74: 1 | N74: 43.016667 | O74: Early Clock Out | P74: {=_xlfn.XLOOKUP(1,(Rebiz!A:A=Table2[[#This Row],[Employee]])*(Rebiz!C:C=Table2[[#This Row],[Date]]),Rebiz!E:E,"")} -> 46296.42 | Q74: {=_xlfn.XLOOKUP(1,(Rebiz!A:A=Table2[[#This Row],[Employee]])*(Rebiz!C:C=Table2[[#This Row],[Date]]),Rebiz!F:F,"")} -> 46296.815 | R74: {=_xlfn.XLOOKUP(1,(Rebiz!A:A=Table2[[#This Row],[Employee]])*(Rebiz!C:C=Table2[[#This Row],[Date]]),Rebiz!G:G,"")} -> 8:46 | S74: {=_xlfn.XLOOKUP(1,(Rebiz!A:A=Table2[[#This Row],[Employee]])*(Rebiz!C:C=Table2[[#This Row],[Date]]),Rebiz!H:H,"")} -> 8:46 | T74: {=_xlfn.XLOOKUP(1,(Rebiz!A:A=Table2[[#This Row],[Employee]])*(Rebiz!C:C=Table2[[#This Row],[Date]]),Rebiz!I:I,"")} -> 0:0 | U74: {=_xlfn.XLOOKUP(1,(Rebiz!A:A=Table2[[#This Row],[Employee]])*(Rebiz!C:C=Table2[[#This Row],[Date]]),Rebiz!J:J,"")} -> 0:43 | V74: {=_xlfn.XLOOKUP(1,(Rebiz!A:A=Table2[[#This Row],[Employee]])*(Rebiz!C:C=Table2[[#This Row],[Date]]),Rebiz!K:K,"")} -> Y
A75: Central | B75: South TX/RGV | C75: North Conway | D75: FABIOLA GARCIA | E75: MOBILE EXPERT | F75: 46296 | G75: 0.39583333 | H75: 0.70833333 | I75: 0.39819444 | J75: 0.71108796 | K75: 7 | L75: 6.4727778 | M75: 1 | N75: 62.2 | O75: On Time | P75: {=_xlfn.XLOOKUP(1,(Rebiz!A:A=Table2[[#This Row],[Employee]])*(Rebiz!C:C=Table2[[#This Row],[Date]]),Rebiz!E:E,"")} -> 46296.401 | Q75: {=_xlfn.XLOOKUP(1,(Rebiz!A:A=Table2[[#This Row],[Employee]])*(Rebiz!C:C=Table2[[#This Row],[Date]]),Rebiz!F:F,"")} -> 46296.71 | R75: {=_xlfn.XLOOKUP(1,(Rebiz!A:A=Table2[[#This Row],[Employee]])*(Rebiz!C:C=Table2[[#This Row],[Date]]),Rebiz!G:G,"")} -> 6:28 | S75: {=_xlfn.XLOOKUP(1,(Rebiz!A:A=Table2[[#This Row],[Employee]])*(Rebiz!C:C=Table2[[#This Row],[Date]]),Rebiz!H:H,"")} -> 6:10 | T75: {=_xlfn.XLOOKUP(1,(Rebiz!A:A=Table2[[#This Row],[Employee]])*(Rebiz!C:C=Table2[[#This Row],[Date]]),Rebiz!I:I,"")} -> 0:18 | U75: {=_xlfn.XLOOKUP(1,(Rebiz!A:A=Table2[[#This Row],[Employee]])*(Rebiz!C:C=Table2[[#This Row],[Date]]),Rebiz!J:J,"")} -> 0:58 | V75: {=_xlfn.XLOOKUP(1,(Rebiz!A:A=Table2[[#This Row],[Employee]])*(Rebiz!C:C=Table2[[#This Row],[Date]]),Rebiz!K:K,"")} -> Y
A76: Central | B76: SA/Hill Country | C76: Seguin | D76: ROSENDO CHACON | E76: MOBILE EXPERT | F76: 46296 | G76: 0.45833333 | H76: 0.84375 | I76: 0.45594907 | J76: 0.84697917 | K76: 8.25 | L76: 8.1219444 | M76: 1 | N76: 75.766667 | O76: On Time | P76: {=_xlfn.XLOOKUP(1,(Rebiz!A:A=Table2[[#This Row],[Employee]])*(Rebiz!C:C=Table2[[#This Row],[Date]]),Rebiz!E:E,"")} -> 46296.457 | Q76: {=_xlfn.XLOOKUP(1,(Rebiz!A:A=Table2[[#This Row],[Employee]])*(Rebiz!C:C=Table2[[#This Row],[Date]]),Rebiz!F:F,"")} -> 46296.85 | R76: {=_xlfn.XLOOKUP(1,(Rebiz!A:A=Table2[[#This Row],[Employee]])*(Rebiz!C:C=Table2[[#This Row],[Date]]),Rebiz!G:G,"")} -> 8:11 | S76: {=_xlfn.XLOOKUP(1,(Rebiz!A:A=Table2[[#This Row],[Employee]])*(Rebiz!C:C=Table2[[#This Row],[Date]]),Rebiz!H:H,"")} -> 6:32 | T76: {=_xlfn.XLOOKUP(1,(Rebiz!A:A=Table2[[#This Row],[Employee]])*(Rebiz!C:C=Table2[[#This Row],[Date]]),Rebiz!I:I,"")} -> 1:39 | U76: {=_xlfn.XLOOKUP(1,(Rebiz!A:A=Table2[[#This Row],[Employee]])*(Rebiz!C:C=Table2[[#This Row],[Date]]),Rebiz!J:J,"")} -> 1:15 | V76: {=_xlfn.XLOOKUP(1,(Rebiz!A:A=Table2[[#This Row],[Employee]])*(Rebiz!C:C=Table2[[#This Row],[Date]]),Rebiz!K:K,"")} -> Y
A77: Central | B77: DFW East | C77: Wesley | D77: SUZANNE BOSHELL | E77: MOBILE EXPERT | F77: 46296 | G77: 0.5 | H77: 0.85416667 | I77: 0.49737269 | J77: 0.83648148 | K77: 8 | L77: 7.5844444 | M77: 1 | N77: 33.25 | O77: Early Clock Out | P77: {=_xlfn.XLOOKUP(1,(Rebiz!A:A=Table2[[#This Row],[Employee]])*(Rebiz!C:C=Table2[[#This Row],[Date]]),Rebiz!E:E,"")} | Q77: {=_xlfn.XLOOKUP(1,(Rebiz!A:A=Table2[[#This Row],[Employee]])*(Rebiz!C:C=Table2[[#This Row],[Date]]),Rebiz!F:F,"")} | R77: {=_xlfn.XLOOKUP(1,(Rebiz!A:A=Table2[[#This Row],[Employee]])*(Rebiz!C:C=Table2[[#This Row],[Date]]),Rebiz!G:G,"")} | S77: {=_xlfn.XLOOKUP(1,(Rebiz!A:A=Table2[[#This Row],[Employee]])*(Rebiz!C:C=Table2[[#This Row],[Date]]),Rebiz!H:H,"")} | T77: {=_xlfn.XLOOKUP(1,(Rebiz!A:A=Table2[[#This Row],[Employee]])*(Rebiz!C:C=Table2[[#This Row],[Date]]),Rebiz!I:I,"")} | U77: {=_xlfn.XLOOKUP(1,(Rebiz!A:A=Table2[[#This Row],[Employee]])*(Rebiz!C:C=Table2[[#This Row],[Date]]),Rebiz!J:J,"")} | V77: {=_xlfn.XLOOKUP(1,(Rebiz!A:A=Table2[[#This Row],[Employee]])*(Rebiz!C:C=Table2[[#This Row],[Date]]),Rebiz!K:K,"")}
A78: Central | B78: MO/IA/NE | C78: Jeff City | D78: ERIC ANGEL | E78: MOBILE EXPERT | F78: 46296 | G78: 0.52083333 | H78: 0.85416667 | I78: 0.38157407 | J78: 0.80846065 | K78: 7.5 | L78: 9.5619444 | M78: 1 | N78: 41 | O78: Early Clock In, Early Clock Out | P78: {=_xlfn.XLOOKUP(1,(Rebiz!A:A=Table2[[#This Row],[Employee]])*(Rebiz!C:C=Table2[[#This Row],[Date]]),Rebiz!E:E,"")} -> 46296.385 | Q78: {=_xlfn.XLOOKUP(1,(Rebiz!A:A=Table2[[#This Row],[Employee]])*(Rebiz!C:C=Table2[[#This Row],[Date]]),Rebiz!F:F,"")} -> 46296.8 | R78: {=_xlfn.XLOOKUP(1,(Rebiz!A:A=Table2[[#This Row],[Employee]])*(Rebiz!C:C=Table2[[#This Row],[Date]]),Rebiz!G:G,"")} -> 8:57 | S78: {=_xlfn.XLOOKUP(1,(Rebiz!A:A=Table2[[#This Row],[Employee]])*(Rebiz!C:C=Table2[[#This Row],[Date]]),Rebiz!H:H,"")} -> 8:57 | T78: {=_xlfn.XLOOKUP(1,(Rebiz!A:A=Table2[[#This Row],[Employee]])*(Rebiz!C:C=Table2[[#This Row],[Date]]),Rebiz!I:I,"")} -> 0:0 | U78: {=_xlfn.XLOOKUP(1,(Rebiz!A:A=Table2[[#This Row],[Employee]])*(Rebiz!C:C=Table2[[#This Row],[Date]]),Rebiz!J:J,"")} -> 1:1 | V78: {=_xlfn.XLOOKUP(1,(Rebiz!A:A=Table2[[#This Row],[Employee]])*(Rebiz!C:C=Table2[[#This Row],[Date]]),Rebiz!K:K,"")} -> Y
A79: Central | B79: KS/OK | C79: Garth Brooks Blvd | D79: CHLOE BRANSON | E79: MOBILE EXPERT | F79: 46296 | G79: 0.5 | H79: 0.85416667 | I79: 0.49671296 | J79: 0.86611111 | K79: 8 | L79: 8.3544444 | M79: 1 | N79: 30.666667 | O79: Late Clock Out | P79: {=_xlfn.XLOOKUP(1,(Rebiz!A:A=Table2[[#This Row],[Employee]])*(Rebiz!C:C=Table2[[#This Row],[Date]]),Rebiz!E:E,"")} -> 46296.496 | Q79: {=_xlfn.XLOOKUP(1,(Rebiz!A:A=Table2[[#This Row],[Employee]])*(Rebiz!C:C=Table2[[#This Row],[Date]]),Rebiz!F:F,"")} -> 46296.87 | R79: {=_xlfn.XLOOKUP(1,(Rebiz!A:A=Table2[[#This Row],[Employee]])*(Rebiz!C:C=Table2[[#This Row],[Date]]),Rebiz!G:G,"")} -> 8:30 | S79: {=_xlfn.XLOOKUP(1,(Rebiz!A:A=Table2[[#This Row],[Employee]])*(Rebiz!C:C=Table2[[#This Row],[Date]]),Rebiz!H:H,"")} -> 7:42 | T79: {=_xlfn.XLOOKUP(1,(Rebiz!A:A=Table2[[#This Row],[Employee]])*(Rebiz!C:C=Table2[[#This Row],[Date]]),Rebiz!I:I,"")} -> 0:48 | U79: {=_xlfn.XLOOKUP(1,(Rebiz!A:A=Table2[[#This Row],[Employee]])*(Rebiz!C:C=Table2[[#This Row],[Date]]),Rebiz!J:J,"")} -> 0:29 | V79: {=_xlfn.XLOOKUP(1,(Rebiz!A:A=Table2[[#This Row],[Employee]])*(Rebiz!C:C=Table2[[#This Row],[Date]]),Rebiz!K:K,"")} -> Y
A80: Central | B80: SA South | C80: South Park Mall | D80: VIVIANA COLLAZO | E80: MOBILE EXPERT | F80: 46296 | G80: 0.4375 | H80: 0.70833333 | I80: 0.43680556 | J80: 0.63248843 | K80: 6 | L80: 4.6963889 | M80: 0 | N80: 0 | O80: Early Clock Out | P80: {=_xlfn.XLOOKUP(1,(Rebiz!A:A=Table2[[#This Row],[Employee]])*(Rebiz!C:C=Table2[[#This Row],[Date]]),Rebiz!E:E,"")} -> 46296.447 | Q80: {=_xlfn.XLOOKUP(1,(Rebiz!A:A=Table2[[#This Row],[Employee]])*(Rebiz!C:C=Table2[[#This Row],[Date]]),Rebiz!F:F,"")} -> 46296.662 | R80: {=_xlfn.XLOOKUP(1,(Rebiz!A:A=Table2[[#This Row],[Employee]])*(Rebiz!C:C=Table2[[#This Row],[Date]]),Rebiz!G:G,"")} -> 5:9 | S80: {=_xlfn.XLOOKUP(1,(Rebiz!A:A=Table2[[#This Row],[Employee]])*(Rebiz!C:C=Table2[[#This Row],[Date]]),Rebiz!H:H,"")} -> 4:33 | T80: {=_xlfn.XLOOKUP(1,(Rebiz!A:A=Table2[[#This Row],[Employee]])*(Rebiz!C:C=Table2[[#This Row],[Date]]),Rebiz!I:I,"")} -> 0:36 | U80: {=_xlfn.XLOOKUP(1,(Rebiz!A:A=Table2[[#This Row],[Employee]])*(Rebiz!C:C=Table2[[#This Row],[Date]]),Rebiz!J:J,"")} -> 0:0 | V80: {=_xlfn.XLOOKUP(1,(Rebiz!A:A=Table2[[#This Row],[Employee]])*(Rebiz!C:C=Table2[[#This Row],[Date]]),Rebiz!K:K,"")} -> Y
A81: Central | B81: Central Texas | C81: Taylor | D81: ROBERT CASTRO | E81: MOBILE EXPERT | F81: 46296 | G81: 0.45833333 | H81: 0.84375 | K81: 8.75 | L81: 0 | M81: 0 | N81: 0 | O81: No Show | P81: {=_xlfn.XLOOKUP(1,(Rebiz!A:A=Table2[[#This Row],[Employee]])*(Rebiz!C:C=Table2[[#This Row],[Date]]),Rebiz!E:E,"")} -> 1 | Q81: {=_xlfn.XLOOKUP(1,(Rebiz!A:A=Table2[[#This Row],[Employee]])*(Rebiz!C:C=Table2[[#This Row],[Date]]),Rebiz!F:F,"")} -> 1 | R81: {=_xlfn.XLOOKUP(1,(Rebiz!A:A=Table2[[#This Row],[Employee]])*(Rebiz!C:C=Table2[[#This Row],[Date]]),Rebiz!G:G,"")} -> 0:0 | S81: {=_xlfn.XLOOKUP(1,(Rebiz!A:A=Table2[[#This Row],[Employee]])*(Rebiz!C:C=Table2[[#This Row],[Date]]),Rebiz!H:H,"")} -> 0:0 | T81: {=_xlfn.XLOOKUP(1,(Rebiz!A:A=Table2[[#This Row],[Employee]])*(Rebiz!C:C=Table2[[#This Row],[Date]]),Rebiz!I:I,"")} -> 0:0 | U81: {=_xlfn.XLOOKUP(1,(Rebiz!A:A=Table2[[#This Row],[Employee]])*(Rebiz!C:C=Table2[[#This Row],[Date]]),Rebiz!J:J,"")} -> 0:0 | V81: {=_xlfn.XLOOKUP(1,(Rebiz!A:A=Table2[[#This Row],[Employee]])*(Rebiz!C:C=Table2[[#This Row],[Date]]),Rebiz!K:K,"")} -> Y
A82: Central | B82: KS/OK | C82: Chickasha | D82: KISSA HORSECHIEF | E82: MOBILE EXPERT | F82: 46296 | G82: 0.54166667 | H82: 0.85416667 | I82: 0.54145833 | J82: 0.84762731 | K82: 7 | L82: 6.5355556 | M82: 1 | N82: 48.75 | O82: On Time | P82: {=_xlfn.XLOOKUP(1,(Rebiz!A:A=Table2[[#This Row],[Employee]])*(Rebiz!C:C=Table2[[#This Row],[Date]]),Rebiz!E:E,"")} -> 46296.537 | Q82: {=_xlfn.XLOOKUP(1,(Rebiz!A:A=Table2[[#This Row],[Employee]])*(Rebiz!C:C=Table2[[#This Row],[Date]]),Rebiz!F:F,"")} -> 46296.849 | R82: {=_xlfn.XLOOKUP(1,(Rebiz!A:A=Table2[[#This Row],[Employee]])*(Rebiz!C:C=Table2[[#This Row],[Date]]),Rebiz!G:G,"")} -> 7:5 | S82: {=_xlfn.XLOOKUP(1,(Rebiz!A:A=Table2[[#This Row],[Employee]])*(Rebiz!C:C=Table2[[#This Row],[Date]]),Rebiz!H:H,"")} -> 6:50 | T82: {=_xlfn.XLOOKUP(1,(Rebiz!A:A=Table2[[#This Row],[Employee]])*(Rebiz!C:C=Table2[[#This Row],[Date]]),Rebiz!I:I,"")} -> 0:15 | U82: {=_xlfn.XLOOKUP(1,(Rebiz!A:A=Table2[[#This Row],[Employee]])*(Rebiz!C:C=Table2[[#This Row],[Date]]),Rebiz!J:J,"")} -> 0:24 | V82: {=_xlfn.XLOOKUP(1,(Rebiz!A:A=Table2[[#This Row],[Employee]])*(Rebiz!C:C=Table2[[#This Row],[Date]]),Rebiz!K:K,"")} -> Y
A83: Central | B83: DFW East | C83: Cooper Street | D83: ADALISAHARY GARCIA | E83: MOBILE EXPERT | F83: 46296 | G83: 0.375 | H83: 0.75 | I83: 0.38260417 | J83: 0.74770833 | K83: 8.5 | L83: 7.7625 | M83: 1 | N83: 60 | O83: Late Clock In | P83: {=_xlfn.XLOOKUP(1,(Rebiz!A:A=Table2[[#This Row],[Employee]])*(Rebiz!C:C=Table2[[#This Row],[Date]]),Rebiz!E:E,"")} -> 46296.394 | Q83: {=_xlfn.XLOOKUP(1,(Rebiz!A:A=Table2[[#This Row],[Employee]])*(Rebiz!C:C=Table2[[#This Row],[Date]]),Rebiz!F:F,"")} -> 46296.751 | R83: {=_xlfn.XLOOKUP(1,(Rebiz!A:A=Table2[[#This Row],[Employee]])*(Rebiz!C:C=Table2[[#This Row],[Date]]),Rebiz!G:G,"")} -> 6:30 | S83: {=_xlfn.XLOOKUP(1,(Rebiz!A:A=Table2[[#This Row],[Employee]])*(Rebiz!C:C=Table2[[#This Row],[Date]]),Rebiz!H:H,"")} -> 6:12 | T83: {=_xlfn.XLOOKUP(1,(Rebiz!A:A=Table2[[#This Row],[Employee]])*(Rebiz!C:C=Table2[[#This Row],[Date]]),Rebiz!I:I,"")} -> 0:18 | U83: {=_xlfn.XLOOKUP(1,(Rebiz!A:A=Table2[[#This Row],[Employee]])*(Rebiz!C:C=Table2[[#This Row],[Date]]),Rebiz!J:J,"")} -> 2:4 | V83: {=_xlfn.XLOOKUP(1,(Rebiz!A:A=Table2[[#This Row],[Employee]])*(Rebiz!C:C=Table2[[#This Row],[Date]]),Rebiz!K:K,"")} -> Y
A84: Central | B84: DFW East | C84: Custer | D84: KENDALL WADE | E84: MOBILE EXPERT | F84: 46296 | G84: 0.39583333 | H84: 0.75 | I84: 0.39072917 | J84: 0.55976852 | K84: 8 | L84: 4.0569444 | M84: 0 | N84: 0 | O84: Early Clock Out | P84: {=_xlfn.XLOOKUP(1,(Rebiz!A:A=Table2[[#This Row],[Employee]])*(Rebiz!C:C=Table2[[#This Row],[Date]]),Rebiz!E:E,"")} -> 46296.391 | Q84: {=_xlfn.XLOOKUP(1,(Rebiz!A:A=Table2[[#This Row],[Employee]])*(Rebiz!C:C=Table2[[#This Row],[Date]]),Rebiz!F:F,"")} -> 46296.561 | R84: {=_xlfn.XLOOKUP(1,(Rebiz!A:A=Table2[[#This Row],[Employee]])*(Rebiz!C:C=Table2[[#This Row],[Date]]),Rebiz!G:G,"")} -> 4:5 | S84: {=_xlfn.XLOOKUP(1,(Rebiz!A:A=Table2[[#This Row],[Employee]])*(Rebiz!C:C=Table2[[#This Row],[Date]]),Rebiz!H:H,"")} -> 3:47 | T84: {=_xlfn.XLOOKUP(1,(Rebiz!A:A=Table2[[#This Row],[Employee]])*(Rebiz!C:C=Table2[[#This Row],[Date]]),Rebiz!I:I,"")} -> 0:18 | U84: {=_xlfn.XLOOKUP(1,(Rebiz!A:A=Table2[[#This Row],[Employee]])*(Rebiz!C:C=Table2[[#This Row],[Date]]),Rebiz!J:J,"")} -> 0:0 | V84: {=_xlfn.XLOOKUP(1,(Rebiz!A:A=Table2[[#This Row],[Employee]])*(Rebiz!C:C=Table2[[#This Row],[Date]]),Rebiz!K:K,"")} -> Y
A85: Central | B85: MO/IA/NE | C85: Dubuque | D85: JASE KEMKE | E85: MOBILE EXPERT | F85: 46296 | G85: 0.39583333 | H85: 0.83333333 | I85: 0.3977662 | J85: 0.86467593 | K85: 10 | L85: 10.687222 | M85: 1 | N85: 31.116667 | O85: Late Clock Out | P85: {=_xlfn.XLOOKUP(1,(Rebiz!A:A=Table2[[#This Row],[Employee]])*(Rebiz!C:C=Table2[[#This Row],[Date]]),Rebiz!E:E,"")} -> 46296.399 | Q85: {=_xlfn.XLOOKUP(1,(Rebiz!A:A=Table2[[#This Row],[Employee]])*(Rebiz!C:C=Table2[[#This Row],[Date]]),Rebiz!F:F,"")} -> 46296.865 | R85: {=_xlfn.XLOOKUP(1,(Rebiz!A:A=Table2[[#This Row],[Employee]])*(Rebiz!C:C=Table2[[#This Row],[Date]]),Rebiz!G:G,"")} -> 11:11 | S85: {=_xlfn.XLOOKUP(1,(Rebiz!A:A=Table2[[#This Row],[Employee]])*(Rebiz!C:C=Table2[[#This Row],[Date]]),Rebiz!H:H,"")} -> 9:53 | T85: {=_xlfn.XLOOKUP(1,(Rebiz!A:A=Table2[[#This Row],[Employee]])*(Rebiz!C:C=Table2[[#This Row],[Date]]),Rebiz!I:I,"")} -> 1:18 | U85: {=_xlfn.XLOOKUP(1,(Rebiz!A:A=Table2[[#This Row],[Employee]])*(Rebiz!C:C=Table2[[#This Row],[Date]]),Rebiz!J:J,"")} -> 0:0 | V85: {=_xlfn.XLOOKUP(1,(Rebiz!A:A=Table2[[#This Row],[Employee]])*(Rebiz!C:C=Table2[[#This Row],[Date]]),Rebiz!K:K,"")} -> Y
A86: Central | B86: MO/IA/NE | C86: Maple | D86: WILFREDO CALDERON | E86: MOBILE EXPERT | F86: 46296 | G86: 0.39583333 | H86: 0.8125 | I86: 0.41836806 | J86: 0.83774306 | K86: 9.5 | L86: 9.5644444 | M86: 1 | N86: 30.033333 | O86: Late Clock Out, Late Clock In | P86: {=_xlfn.XLOOKUP(1,(Rebiz!A:A=Table2[[#This Row],[Employee]])*(Rebiz!C:C=Table2[[#This Row],[Date]]),Rebiz!E:E,"")} -> 46296.419 | Q86: {=_xlfn.XLOOKUP(1,(Rebiz!A:A=Table2[[#This Row],[Employee]])*(Rebiz!C:C=Table2[[#This Row],[Date]]),Rebiz!F:F,"")} -> 46296.84 | R86: {=_xlfn.XLOOKUP(1,(Rebiz!A:A=Table2[[#This Row],[Employee]])*(Rebiz!C:C=Table2[[#This Row],[Date]]),Rebiz!G:G,"")} -> 9:38 | S86: {=_xlfn.XLOOKUP(1,(Rebiz!A:A=Table2[[#This Row],[Employee]])*(Rebiz!C:C=Table2[[#This Row],[Date]]),Rebiz!H:H,"")} -> 4:20 | T86: {=_xlfn.XLOOKUP(1,(Rebiz!A:A=Table2[[#This Row],[Employee]])*(Rebiz!C:C=Table2[[#This Row],[Date]]),Rebiz!I:I,"")} -> 5:18 | U86: {=_xlfn.XLOOKUP(1,(Rebiz!A:A=Table2[[#This Row],[Employee]])*(Rebiz!C:C=Table2[[#This Row],[Date]]),Rebiz!J:J,"")} -> 0:28 | V86: {=_xlfn.XLOOKUP(1,(Rebiz!A:A=Table2[[#This Row],[Employee]])*(Rebiz!C:C=Table2[[#This Row],[Date]]),Rebiz!K:K,"")} -> Y
A87: Central | B87: DFW North | C87: Ennis | D87: ZENAIDA CISNEROS | E87: MOBILE EXPERT | F87: 46296 | G87: 0.45833333 | H87: 0.85416667 | I87: 0.49873843 | J87: 0.84199074 | K87: 9 | L87: 7.3261111 | M87: 1 | N87: 54.716667 | O87: Late Clock In, Early Clock Out | P87: {=_xlfn.XLOOKUP(1,(Rebiz!A:A=Table2[[#This Row],[Employee]])*(Rebiz!C:C=Table2[[#This Row],[Date]]),Rebiz!E:E,"")} -> 46296.499 | Q87: {=_xlfn.XLOOKUP(1,(Rebiz!A:A=Table2[[#This Row],[Employee]])*(Rebiz!C:C=Table2[[#This Row],[Date]]),Rebiz!F:F,"")} -> 46296.845 | R87: {=_xlfn.XLOOKUP(1,(Rebiz!A:A=Table2[[#This Row],[Employee]])*(Rebiz!C:C=Table2[[#This Row],[Date]]),Rebiz!G:G,"")} -> 7:23 | S87: {=_xlfn.XLOOKUP(1,(Rebiz!A:A=Table2[[#This Row],[Employee]])*(Rebiz!C:C=Table2[[#This Row],[Date]]),Rebiz!H:H,"")} -> 6:50 | T87: {=_xlfn.XLOOKUP(1,(Rebiz!A:A=Table2[[#This Row],[Employee]])*(Rebiz!C:C=Table2[[#This Row],[Date]]),Rebiz!I:I,"")} -> 0:33 | U87: {=_xlfn.XLOOKUP(1,(Rebiz!A:A=Table2[[#This Row],[Employee]])*(Rebiz!C:C=Table2[[#This Row],[Date]]),Rebiz!J:J,"")} -> 0:56 | V87: {=_xlfn.XLOOKUP(1,(Rebiz!A:A=Table2[[#This Row],[Employee]])*(Rebiz!C:C=Table2[[#This Row],[Date]]),Rebiz!K:K,"")} -> Y
A88: Central | B88: SA/Hill Country | C88: Thousand Oaks | D88: ABDIEL SANCHEZ | E88: MOBILE EXPERT | F88: 46296 | G88: 0.41666667 | H88: 0.83333333 | K88: 9 | L88: 0 | M88: 0 | N88: 0 | O88: No Show | P88: {=_xlfn.XLOOKUP(1,(Rebiz!A:A=Table2[[#This Row],[Employee]])*(Rebiz!C:C=Table2[[#This Row],[Date]]),Rebiz!E:E,"")} -> 1 | Q88: {=_xlfn.XLOOKUP(1,(Rebiz!A:A=Table2[[#This Row],[Employee]])*(Rebiz!C:C=Table2[[#This Row],[Date]]),Rebiz!F:F,"")} -> 1 | R88: {=_xlfn.XLOOKUP(1,(Rebiz!A:A=Table2[[#This Row],[Employee]])*(Rebiz!C:C=Table2[[#This Row],[Date]]),Rebiz!G:G,"")} -> 0:0 | S88: {=_xlfn.XLOOKUP(1,(Rebiz!A:A=Table2[[#This Row],[Employee]])*(Rebiz!C:C=Table2[[#This Row],[Date]]),Rebiz!H:H,"")} -> 0:0 | T88: {=_xlfn.XLOOKUP(1,(Rebiz!A:A=Table2[[#This Row],[Employee]])*(Rebiz!C:C=Table2[[#This Row],[Date]]),Rebiz!I:I,"")} -> 0:0 | U88: {=_xlfn.XLOOKUP(1,(Rebiz!A:A=Table2[[#This Row],[Employee]])*(Rebiz!C:C=Table2[[#This Row],[Date]]),Rebiz!J:J,"")} -> 0:0 | V88: {=_xlfn.XLOOKUP(1,(Rebiz!A:A=Table2[[#This Row],[Employee]])*(Rebiz!C:C=Table2[[#This Row],[Date]]),Rebiz!K:K,"")} -> Y
A89: Central | B89: DFW North | C89: Stonebrook | D89: MICHAEL HENGER | E89: MOBILE EXPERT | F89: 46296 | G89: 0.375 | H89: 0.75 | I89: 0.38297454 | J89: 0.7474537 | K89: 8.5 | L89: 7.9330556 | M89: 1 | N89: 48.866667 | O89: Late Clock In | P89: {=_xlfn.XLOOKUP(1,(Rebiz!A:A=Table2[[#This Row],[Employee]])*(Rebiz!C:C=Table2[[#This Row],[Date]]),Rebiz!E:E,"")} -> 1 | Q89: {=_xlfn.XLOOKUP(1,(Rebiz!A:A=Table2[[#This Row],[Employee]])*(Rebiz!C:C=Table2[[#This Row],[Date]]),Rebiz!F:F,"")} -> 1 | R89: {=_xlfn.XLOOKUP(1,(Rebiz!A:A=Table2[[#This Row],[Employee]])*(Rebiz!C:C=Table2[[#This Row],[Date]]),Rebiz!G:G,"")} -> 0:0 | S89: {=_xlfn.XLOOKUP(1,(Rebiz!A:A=Table2[[#This Row],[Employee]])*(Rebiz!C:C=Table2[[#This Row],[Date]]),Rebiz!H:H,"")} -> 0:0 | T89: {=_xlfn.XLOOKUP(1,(Rebiz!A:A=Table2[[#This Row],[Employee]])*(Rebiz!C:C=Table2[[#This Row],[Date]]),Rebiz!I:I,"")} -> 0:0 | U89: {=_xlfn.XLOOKUP(1,(Rebiz!A:A=Table2[[#This Row],[Employee]])*(Rebiz!C:C=Table2[[#This Row],[Date]]),Rebiz!J:J,"")} -> 0:0 | V89: {=_xlfn.XLOOKUP(1,(Rebiz!A:A=Table2[[#This Row],[Employee]])*(Rebiz!C:C=Table2[[#This Row],[Date]]),Rebiz!K:K,"")} -> Y
A90: Central | B90: DFW North | C90: Jefferson | D90: RUBEN HERRERA BARRIENTOS | E90: MOBILE EXPERT | F90: 46296 | G90: 0.58333333 | H90: 0.875 | I90: 0.58230324 | J90: 0.84149306 | K90: 6.5 | L90: 5.695 | M90: 1 | N90: 31.533333 | O90: Early Clock Out | P90: {=_xlfn.XLOOKUP(1,(Rebiz!A:A=Table2[[#This Row],[Employee]])*(Rebiz!C:C=Table2[[#This Row],[Date]]),Rebiz!E:E,"")} -> 46296.581 | Q90: {=_xlfn.XLOOKUP(1,(Rebiz!A:A=Table2[[#This Row],[Employee]])*(Rebiz!C:C=Table2[[#This Row],[Date]]),Rebiz!F:F,"")} -> 46296.845 | R90: {=_xlfn.XLOOKUP(1,(Rebiz!A:A=Table2[[#This Row],[Employee]])*(Rebiz!C:C=Table2[[#This Row],[Date]]),Rebiz!G:G,"")} -> 5:51 | S90: {=_xlfn.XLOOKUP(1,(Rebiz!A:A=Table2[[#This Row],[Employee]])*(Rebiz!C:C=Table2[[#This Row],[Date]]),Rebiz!H:H,"")} -> 5:36 | T90: {=_xlfn.XLOOKUP(1,(Rebiz!A:A=Table2[[#This Row],[Employee]])*(Rebiz!C:C=Table2[[#This Row],[Date]]),Rebiz!I:I,"")} -> 0:15 | U90: {=_xlfn.XLOOKUP(1,(Rebiz!A:A=Table2[[#This Row],[Employee]])*(Rebiz!C:C=Table2[[#This Row],[Date]]),Rebiz!J:J,"")} -> 0:30 | V90: {=_xlfn.XLOOKUP(1,(Rebiz!A:A=Table2[[#This Row],[Employee]])*(Rebiz!C:C=Table2[[#This Row],[Date]]),Rebiz!K:K,"")} -> Y
A91: Central | B91: MO/IA/NE | C91: Hannibal | D91: CAITLYN BROWN | E91: MOBILE EXPERT | F91: 46296 | G91: 0.5 | H91: 0.85416667 | K91: 8 | L91: 0 | M91: 0 | N91: 0 | O91: No Show | P91: {=_xlfn.XLOOKUP(1,(Rebiz!A:A=Table2[[#This Row],[Employee]])*(Rebiz!C:C=Table2[[#This Row],[Date]]),Rebiz!E:E,"")} | Q91: {=_xlfn.XLOOKUP(1,(Rebiz!A:A=Table2[[#This Row],[Employee]])*(Rebiz!C:C=Table2[[#This Row],[Date]]),Rebiz!F:F,"")} | R91: {=_xlfn.XLOOKUP(1,(Rebiz!A:A=Table2[[#This Row],[Employee]])*(Rebiz!C:C=Table2[[#This Row],[Date]]),Rebiz!G:G,"")} | S91: {=_xlfn.XLOOKUP(1,(Rebiz!A:A=Table2[[#This Row],[Employee]])*(Rebiz!C:C=Table2[[#This Row],[Date]]),Rebiz!H:H,"")} | T91: {=_xlfn.XLOOKUP(1,(Rebiz!A:A=Table2[[#This Row],[Employee]])*(Rebiz!C:C=Table2[[#This Row],[Date]]),Rebiz!I:I,"")} | U91: {=_xlfn.XLOOKUP(1,(Rebiz!A:A=Table2[[#This Row],[Employee]])*(Rebiz!C:C=Table2[[#This Row],[Date]]),Rebiz!J:J,"")} | V91: {=_xlfn.XLOOKUP(1,(Rebiz!A:A=Table2[[#This Row],[Employee]])*(Rebiz!C:C=Table2[[#This Row],[Date]]),Rebiz!K:K,"")}
A92: Central | B92: DFW East | C92: Custer | D92: CESAR CASTELLANO | E92: MOBILE EXPERT | F92: 46296 | G92: 0.45833333 | H92: 0.83333333 | I92: 0.47443287 | J92: 0.78810185 | K92: 8.5 | L92: 6.9983333 | M92: 1 | N92: 31.783333 | O92: Late Clock In, Early Clock Out | P92: {=_xlfn.XLOOKUP(1,(Rebiz!A:A=Table2[[#This Row],[Employee]])*(Rebiz!C:C=Table2[[#This Row],[Date]]),Rebiz!E:E,"")} -> 46296.476 | Q92: {=_xlfn.XLOOKUP(1,(Rebiz!A:A=Table2[[#This Row],[Employee]])*(Rebiz!C:C=Table2[[#This Row],[Date]]),Rebiz!F:F,"")} -> 46296.792 | R92: {=_xlfn.XLOOKUP(1,(Rebiz!A:A=Table2[[#This Row],[Employee]])*(Rebiz!C:C=Table2[[#This Row],[Date]]),Rebiz!G:G,"")} -> 7:23 | S92: {=_xlfn.XLOOKUP(1,(Rebiz!A:A=Table2[[#This Row],[Employee]])*(Rebiz!C:C=Table2[[#This Row],[Date]]),Rebiz!H:H,"")} -> 6:20 | T92: {=_xlfn.XLOOKUP(1,(Rebiz!A:A=Table2[[#This Row],[Employee]])*(Rebiz!C:C=Table2[[#This Row],[Date]]),Rebiz!I:I,"")} -> 1:3 | U92: {=_xlfn.XLOOKUP(1,(Rebiz!A:A=Table2[[#This Row],[Employee]])*(Rebiz!C:C=Table2[[#This Row],[Date]]),Rebiz!J:J,"")} -> 0:12 | V92: {=_xlfn.XLOOKUP(1,(Rebiz!A:A=Table2[[#This Row],[Employee]])*(Rebiz!C:C=Table2[[#This Row],[Date]]),Rebiz!K:K,"")} -> Y
A93: Central | B93: MO/IA/NE | C93: 180th Street | D93: CRYSTAL MCCOY | E93: MOBILE EXPERT | F93: 46296 | G93: 0.39583333 | H93: 0.75 | I93: 0.3853588 | J93: 0.75361111 | K93: 8 | L93: 8.3380556 | M93: 1 | N93: 30 | O93: Early Clock In | P93: {=_xlfn.XLOOKUP(1,(Rebiz!A:A=Table2[[#This Row],[Employee]])*(Rebiz!C:C=Table2[[#This Row],[Date]]),Rebiz!E:E,"")} -> 46296.386 | Q93: {=_xlfn.XLOOKUP(1,(Rebiz!A:A=Table2[[#This Row],[Employee]])*(Rebiz!C:C=Table2[[#This Row],[Date]]),Rebiz!F:F,"")} -> 46296.756 | R93: {=_xlfn.XLOOKUP(1,(Rebiz!A:A=Table2[[#This Row],[Employee]])*(Rebiz!C:C=Table2[[#This Row],[Date]]),Rebiz!G:G,"")} -> 8:53 | S93: {=_xlfn.XLOOKUP(1,(Rebiz!A:A=Table2[[#This Row],[Employee]])*(Rebiz!C:C=Table2[[#This Row],[Date]]),Rebiz!H:H,"")} -> 8:41 | T93: {=_xlfn.XLOOKUP(1,(Rebiz!A:A=Table2[[#This Row],[Employee]])*(Rebiz!C:C=Table2[[#This Row],[Date]]),Rebiz!I:I,"")} -> 0:12 | U93: {=_xlfn.XLOOKUP(1,(Rebiz!A:A=Table2[[#This Row],[Employee]])*(Rebiz!C:C=Table2[[#This Row],[Date]]),Rebiz!J:J,"")} -> 0:0 | V93: {=_xlfn.XLOOKUP(1,(Rebiz!A:A=Table2[[#This Row],[Employee]])*(Rebiz!C:C=Table2[[#This Row],[Date]]),Rebiz!K:K,"")} -> Y
A94: Central | B94: KS/OK | C94: Wrangler | D94: SETH WALKER | E94: MOBILE EXPERT | F94: 46296 | G94: 0.375 | H94: 0.91666667 | I94: 0.375 | J94: 0.875 | K94: 11 | L94: 11 | M94: 1 | N94: 60 | O94: Early Clock Out | P94: {=_xlfn.XLOOKUP(1,(Rebiz!A:A=Table2[[#This Row],[Employee]])*(Rebiz!C:C=Table2[[#This Row],[Date]]),Rebiz!E:E,"")} -> 1 | Q94: {=_xlfn.XLOOKUP(1,(Rebiz!A:A=Table2[[#This Row],[Employee]])*(Rebiz!C:C=Table2[[#This Row],[Date]]),Rebiz!F:F,"")} -> 1 | R94: {=_xlfn.XLOOKUP(1,(Rebiz!A:A=Table2[[#This Row],[Employee]])*(Rebiz!C:C=Table2[[#This Row],[Date]]),Rebiz!G:G,"")} -> 0:0 | S94: {=_xlfn.XLOOKUP(1,(Rebiz!A:A=Table2[[#This Row],[Employee]])*(Rebiz!C:C=Table2[[#This Row],[Date]]),Rebiz!H:H,"")} -> 0:0 | T94: {=_xlfn.XLOOKUP(1,(Rebiz!A:A=Table2[[#This Row],[Employee]])*(Rebiz!C:C=Table2[[#This Row],[Date]]),Rebiz!I:I,"")} -> 0:0 | U94: {=_xlfn.XLOOKUP(1,(Rebiz!A:A=Table2[[#This Row],[Employee]])*(Rebiz!C:C=Table2[[#This Row],[Date]]),Rebiz!J:J,"")} -> 0:0 | V94: {=_xlfn.XLOOKUP(1,(Rebiz!A:A=Table2[[#This Row],[Employee]])*(Rebiz!C:C=Table2[[#This Row],[Date]]),Rebiz!K:K,"")} -> Y
A95: Central | B95: KS/OK | C95: Chickasha | D95: FINLEE WERNER | E95: MOBILE EXPERT | F95: 46296 | G95: 0.54166667 | H95: 0.85416667 | I95: 0.53861111 | J95: 0.84739583 | K95: 7 | L95: 6.91 | M95: 1 | N95: 30.05 | O95: On Time | P95: {=_xlfn.XLOOKUP(1,(Rebiz!A:A=Table2[[#This Row],[Employee]])*(Rebiz!C:C=Table2[[#This Row],[Date]]),Rebiz!E:E,"")} -> 46296.543 | Q95: {=_xlfn.XLOOKUP(1,(Rebiz!A:A=Table2[[#This Row],[Employee]])*(Rebiz!C:C=Table2[[#This Row],[Date]]),Rebiz!F:F,"")} -> 46296.849 | R95: {=_xlfn.XLOOKUP(1,(Rebiz!A:A=Table2[[#This Row],[Employee]])*(Rebiz!C:C=Table2[[#This Row],[Date]]),Rebiz!G:G,"")} -> 6:42 | S95: {=_xlfn.XLOOKUP(1,(Rebiz!A:A=Table2[[#This Row],[Employee]])*(Rebiz!C:C=Table2[[#This Row],[Date]]),Rebiz!H:H,"")} -> 6:30 | T95: {=_xlfn.XLOOKUP(1,(Rebiz!A:A=Table2[[#This Row],[Employee]])*(Rebiz!C:C=Table2[[#This Row],[Date]]),Rebiz!I:I,"")} -> 0:12 | U95: {=_xlfn.XLOOKUP(1,(Rebiz!A:A=Table2[[#This Row],[Employee]])*(Rebiz!C:C=Table2[[#This Row],[Date]]),Rebiz!J:J,"")} -> 0:39 | V95: {=_xlfn.XLOOKUP(1,(Rebiz!A:A=Table2[[#This Row],[Employee]])*(Rebiz!C:C=Table2[[#This Row],[Date]]),Rebiz!K:K,"")} -> Y
A96: Central | B96: SA/Hill Country | C96: Thousand Oaks | D96: NATTALY RAMIREZ | E96: MOBILE EXPERT | F96: 46296 | G96: 0.54166667 | H96: 0.83333333 | I96: 0.51574074 | J96: 0.8416088 | K96: 6 | L96: 6.8847222 | M96: 1 | N96: 56.166667 | O96: Early Clock In, Late Clock In, Late Store Open | P96: {=_xlfn.XLOOKUP(1,(Rebiz!A:A=Table2[[#This Row],[Employee]])*(Rebiz!C:C=Table2[[#This Row],[Date]]),Rebiz!E:E,"")} -> 46296.52 | Q96: {=_xlfn.XLOOKUP(1,(Rebiz!A:A=Table2[[#This Row],[Employee]])*(Rebiz!C:C=Table2[[#This Row],[Date]]),Rebiz!F:F,"")} -> 46296.844 | R96: {=_xlfn.XLOOKUP(1,(Rebiz!A:A=Table2[[#This Row],[Employee]])*(Rebiz!C:C=Table2[[#This Row],[Date]]),Rebiz!G:G,"")} -> 7:12 | S96: {=_xlfn.XLOOKUP(1,(Rebiz!A:A=Table2[[#This Row],[Employee]])*(Rebiz!C:C=Table2[[#This Row],[Date]]),Rebiz!H:H,"")} -> 6:18 | T96: {=_xlfn.XLOOKUP(1,(Rebiz!A:A=Table2[[#This Row],[Employee]])*(Rebiz!C:C=Table2[[#This Row],[Date]]),Rebiz!I:I,"")} -> 0:54 | U96: {=_xlfn.XLOOKUP(1,(Rebiz!A:A=Table2[[#This Row],[Employee]])*(Rebiz!C:C=Table2[[#This Row],[Date]]),Rebiz!J:J,"")} -> 0:35 | V96: {=_xlfn.XLOOKUP(1,(Rebiz!A:A=Table2[[#This Row],[Employee]])*(Rebiz!C:C=Table2[[#This Row],[Date]]),Rebiz!K:K,"")} -> Y
A97: Central | B97: SA/Hill Country | C97: Creekside | D97: KRISTOPHER BOLTON | E97: MOBILE EXPERT | F97: 46296 | G97: 0.41666667 | H97: 0.70833333 | I97: 0.41894676 | J97: 0.7105787 | K97: 6 | L97: 6.0033333 | M97: 1 | N97: 59.75 | O97: On Time | P97: {=_xlfn.XLOOKUP(1,(Rebiz!A:A=Table2[[#This Row],[Employee]])*(Rebiz!C:C=Table2[[#This Row],[Date]]),Rebiz!E:E,"")} -> 46296.419 | Q97: {=_xlfn.XLOOKUP(1,(Rebiz!A:A=Table2[[#This Row],[Employee]])*(Rebiz!C:C=Table2[[#This Row],[Date]]),Rebiz!F:F,"")} -> 46296.716 | R97: {=_xlfn.XLOOKUP(1,(Rebiz!A:A=Table2[[#This Row],[Employee]])*(Rebiz!C:C=Table2[[#This Row],[Date]]),Rebiz!G:G,"")} -> 7:8 | S97: {=_xlfn.XLOOKUP(1,(Rebiz!A:A=Table2[[#This Row],[Employee]])*(Rebiz!C:C=Table2[[#This Row],[Date]]),Rebiz!H:H,"")} -> 6:23 | T97: {=_xlfn.XLOOKUP(1,(Rebiz!A:A=Table2[[#This Row],[Employee]])*(Rebiz!C:C=Table2[[#This Row],[Date]]),Rebiz!I:I,"")} -> 0:45 | U97: {=_xlfn.XLOOKUP(1,(Rebiz!A:A=Table2[[#This Row],[Employee]])*(Rebiz!C:C=Table2[[#This Row],[Date]]),Rebiz!J:J,"")} -> 0:0 | V97: {=_xlfn.XLOOKUP(1,(Rebiz!A:A=Table2[[#This Row],[Employee]])*(Rebiz!C:C=Table2[[#This Row],[Date]]),Rebiz!K:K,"")} -> Y
A98: Central | B98: DFW North | C98: Stonebrook | D98: MIKAEL QUEVEDO | E98: MOBILE EXPERT | F98: 46296 | G98: 0.54166667 | H98: 0.85416667 | I98: 0.56016204 | J98: 0.85675926 | K98: 7 | L98: 6.1133333 | M98: 1 | N98: 60.3 | O98: Late Clock In | P98: {=_xlfn.XLOOKUP(1,(Rebiz!A:A=Table2[[#This Row],[Employee]])*(Rebiz!C:C=Table2[[#This Row],[Date]]),Rebiz!E:E,"")} -> 46296.561 | Q98: {=_xlfn.XLOOKUP(1,(Rebiz!A:A=Table2[[#This Row],[Employee]])*(Rebiz!C:C=Table2[[#This Row],[Date]]),Rebiz!F:F,"")} -> 46296.858 | R98: {=_xlfn.XLOOKUP(1,(Rebiz!A:A=Table2[[#This Row],[Employee]])*(Rebiz!C:C=Table2[[#This Row],[Date]]),Rebiz!G:G,"")} -> 5:43 | S98: {=_xlfn.XLOOKUP(1,(Rebiz!A:A=Table2[[#This Row],[Employee]])*(Rebiz!C:C=Table2[[#This Row],[Date]]),Rebiz!H:H,"")} -> 5:43 | T98: {=_xlfn.XLOOKUP(1,(Rebiz!A:A=Table2[[#This Row],[Employee]])*(Rebiz!C:C=Table2[[#This Row],[Date]]),Rebiz!I:I,"")} -> 0:0 | U98: {=_xlfn.XLOOKUP(1,(Rebiz!A:A=Table2[[#This Row],[Employee]])*(Rebiz!C:C=Table2[[#This Row],[Date]]),Rebiz!J:J,"")} -> 1:25 | V98: {=_xlfn.XLOOKUP(1,(Rebiz!A:A=Table2[[#This Row],[Employee]])*(Rebiz!C:C=Table2[[#This Row],[Date]]),Rebiz!K:K,"")} -> Y
A99: Central | B99: MO/IA/NE | C99: Jeff City | D99: JACOB WITHERSPOON | E99: MOBILE EXPERT | F99: 46296 | G99: 0.4375 | H99: 0.85416667 | I99: 0.3908912 | J99: 0.68746528 | K99: 9.5 | L99: 6.4411111 | M99: 1 | N99: 40.6 | O99: Early Clock In, Early Clock Out | P99: {=_xlfn.XLOOKUP(1,(Rebiz!A:A=Table2[[#This Row],[Employee]])*(Rebiz!C:C=Table2[[#This Row],[Date]]),Rebiz!E:E,"")} -> 46296.393 | Q99: {=_xlfn.XLOOKUP(1,(Rebiz!A:A=Table2[[#This Row],[Employee]])*(Rebiz!C:C=Table2[[#This Row],[Date]]),Rebiz!F:F,"")} -> 46296.69 | R99: {=_xlfn.XLOOKUP(1,(Rebiz!A:A=Table2[[#This Row],[Employee]])*(Rebiz!C:C=Table2[[#This Row],[Date]]),Rebiz!G:G,"")} -> 6:3 | S99: {=_xlfn.XLOOKUP(1,(Rebiz!A:A=Table2[[#This Row],[Employee]])*(Rebiz!C:C=Table2[[#This Row],[Date]]),Rebiz!H:H,"")} -> 5:33 | T99: {=_xlfn.XLOOKUP(1,(Rebiz!A:A=Table2[[#This Row],[Employee]])*(Rebiz!C:C=Table2[[#This Row],[Date]]),Rebiz!I:I,"")} -> 0:30 | U99: {=_xlfn.XLOOKUP(1,(Rebiz!A:A=Table2[[#This Row],[Employee]])*(Rebiz!C:C=Table2[[#This Row],[Date]]),Rebiz!J:J,"")} -> 1:5 | V99: {=_xlfn.XLOOKUP(1,(Rebiz!A:A=Table2[[#This Row],[Employee]])*(Rebiz!C:C=Table2[[#This Row],[Date]]),Rebiz!K:K,"")} -> Y
A100: Central | B100: DFW East | C100: Walnut | D100: LEONARDO LARA | E100: MOBILE EXPERT | F100: 46296 | G100: 0.375 | H100: 0.75 | K100: 8 | L100: 0 | M100: 0 | N100: 0 | O100: No Show | P100: {=_xlfn.XLOOKUP(1,(Rebiz!A:A=Table2[[#This Row],[Employee]])*(Rebiz!C:C=Table2[[#This Row],[Date]]),Rebiz!E:E,"")} | Q100: {=_xlfn.XLOOKUP(1,(Rebiz!A:A=Table2[[#This Row],[Employee]])*(Rebiz!C:C=Table2[[#This Row],[Date]]),Rebiz!F:F,"")} | R100: {=_xlfn.XLOOKUP(1,(Rebiz!A:A=Table2[[#This Row],[Employee]])*(Rebiz!C:C=Table2[[#This Row],[Date]]),Rebiz!G:G,"")} | S100: {=_xlfn.XLOOKUP(1,(Rebiz!A:A=Table2[[#This Row],[Employee]])*(Rebiz!C:C=Table2[[#This Row],[Date]]),Rebiz!H:H,"")} | T100: {=_xlfn.XLOOKUP(1,(Rebiz!A:A=Table2[[#This Row],[Employee]])*(Rebiz!C:C=Table2[[#This Row],[Date]]),Rebiz!I:I,"")} | U100: {=_xlfn.XLOOKUP(1,(Rebiz!A:A=Table2[[#This Row],[Employee]])*(Rebiz!C:C=Table2[[#This Row],[Date]]),Rebiz!J:J,"")} | V100: {=_xlfn.XLOOKUP(1,(Rebiz!A:A=Table2[[#This Row],[Employee]])*(Rebiz!C:C=Table2[[#This Row],[Date]]),Rebiz!K:K,"")}
A101: Central | B101: South TX/RGV | C101: Rockport | D101: APRIL HOSENFELD | E101: MOBILE EXPERT | F101: 46296 | G101: 0.39583333 | H101: 0.72916667 | I101: 0.39590278 | J101: 0.73827546 | K101: 7.5 | L101: 7.2025 | M101: 1 | N101: 60.866667 | O101: On Time | P101: {=_xlfn.XLOOKUP(1,(Rebiz!A:A=Table2[[#This Row],[Employee]])*(Rebiz!C:C=Table2[[#This Row],[Date]]),Rebiz!E:E,"")} -> 46296.387 | Q101: {=_xlfn.XLOOKUP(1,(Rebiz!A:A=Table2[[#This Row],[Employee]])*(Rebiz!C:C=Table2[[#This Row],[Date]]),Rebiz!F:F,"")} -> 46296.741 | R101: {=_xlfn.XLOOKUP(1,(Rebiz!A:A=Table2[[#This Row],[Employee]])*(Rebiz!C:C=Table2[[#This Row],[Date]]),Rebiz!G:G,"")} -> 8:8 | S101: {=_xlfn.XLOOKUP(1,(Rebiz!A:A=Table2[[#This Row],[Employee]])*(Rebiz!C:C=Table2[[#This Row],[Date]]),Rebiz!H:H,"")} -> 6:2 | T101: {=_xlfn.XLOOKUP(1,(Rebiz!A:A=Table2[[#This Row],[Employee]])*(Rebiz!C:C=Table2[[#This Row],[Date]]),Rebiz!I:I,"")} -> 2:6 | U101: {=_xlfn.XLOOKUP(1,(Rebiz!A:A=Table2[[#This Row],[Employee]])*(Rebiz!C:C=Table2[[#This Row],[Date]]),Rebiz!J:J,"")} -> 0:22 | V101: {=_xlfn.XLOOKUP(1,(Rebiz!A:A=Table2[[#This Row],[Employee]])*(Rebiz!C:C=Table2[[#This Row],[Date]]),Rebiz!K:K,"")} -> Y
A102: Central | B102: SA/Hill Country | C102: Cibolo | D102: MAURICIO GARZA | E102: MOBILE EXPERT | F102: 46296 | G102: 0.5 | H102: 0.83333333 | I102: 0.49736111 | J102: 0.84952546 | K102: 7.5 | L102: 7.5052778 | M102: 1 | N102: 56.8 | O102: Late Clock Out | P102: {=_xlfn.XLOOKUP(1,(Rebiz!A:A=Table2[[#This Row],[Employee]])*(Rebiz!C:C=Table2[[#This Row],[Date]]),Rebiz!E:E,"")} -> 46296.498 | Q102: {=_xlfn.XLOOKUP(1,(Rebiz!A:A=Table2[[#This Row],[Employee]])*(Rebiz!C:C=Table2[[#This Row],[Date]]),Rebiz!F:F,"")} -> 46296.851 | R102: {=_xlfn.XLOOKUP(1,(Rebiz!A:A=Table2[[#This Row],[Employee]])*(Rebiz!C:C=Table2[[#This Row],[Date]]),Rebiz!G:G,"")} -> 7:43 | S102: {=_xlfn.XLOOKUP(1,(Rebiz!A:A=Table2[[#This Row],[Employee]])*(Rebiz!C:C=Table2[[#This Row],[Date]]),Rebiz!H:H,"")} -> 5:28 | T102: {=_xlfn.XLOOKUP(1,(Rebiz!A:A=Table2[[#This Row],[Employee]])*(Rebiz!C:C=Table2[[#This Row],[Date]]),Rebiz!I:I,"")} -> 2:15 | U102: {=_xlfn.XLOOKUP(1,(Rebiz!A:A=Table2[[#This Row],[Employee]])*(Rebiz!C:C=Table2[[#This Row],[Date]]),Rebiz!J:J,"")} -> 0:45 | V102: {=_xlfn.XLOOKUP(1,(Rebiz!A:A=Table2[[#This Row],[Employee]])*(Rebiz!C:C=Table2[[#This Row],[Date]]),Rebiz!K:K,"")} -> Y
...

Sheet Rebiz
A1: Employee | B1: Location | C1: Date | D1: Employee2 | E1: Camera In | F1: Camera Out | G1: Total Time | H1: Showroom Time | I1: Backroom Time | J1: Break | K1: Monitored
A2: =TRIM(_xlfn.TEXTBEFORE(D2,"(")) -> DANA GLASS | B2: 2VSY: Springboro | C2: 46296 | D2: DANA GLASS (112301) | E2: 46296.6 | F2: 46296.759 | G2: 3:25 | H2: 3:25 | I2: 0:0 | J2: 0:24 | K2: Y
A3: =TRIM(_xlfn.TEXTBEFORE(D3,"(")) -> JORDAN REED | B3: 2VSY: Springboro | C3: 46296 | D3: JORDAN REED (125037) | E3: 46296.399 | F3: 46296.863 | G3: 10:31 | H3: 9:43 | I3: 0:48 | J3: 0:38 | K3: Y
A4: =TRIM(_xlfn.TEXTBEFORE(D4,"(")) -> WENDY ADAMS | B4: 2WSL: Springfield | C4: 46296 | D4: WENDY ADAMS (110752) | E4: 46296.376 | F4: 46296.754 | G4: 8:45 | H4: 6:54 | I4: 1:51 | J4: 0:19 | K4: Y
A5: =TRIM(_xlfn.TEXTBEFORE(D5,"(")) -> ADAM SEVERS | B5: 2WSL: Springfield | C5: 46296 | D5: ADAM SEVERS (124383) | E5: 46296.458 | F5: 46296.849 | G5: 8:51 | H5: 8:18 | I5: 0:33 | J5: 0:32 | K5: Y
A6: =TRIM(_xlfn.TEXTBEFORE(D6,"(")) -> LUIS CORONA | B6: 2WSL: Springfield | C6: 46296 | D6: LUIS CORONA (110427) | E6: 1 | F6: 1 | G6: 0:0 | H6: 0:0 | I6: 0:0 | J6: 0:0 | K6: Y
A7: =TRIM(_xlfn.TEXTBEFORE(D7,"(")) -> MICHAEL HASAN | B7: 2WSL: Springfield | C7: 46296 | D7: MICHAEL HASAN (130047) | E7: 46296.495 | F7: 46296.826 | G7: 7:20 | H7: 5:50 | I7: 1:30 | J7: 0:37 | K7: Y
A8: =TRIM(_xlfn.TEXTBEFORE(D8,"(")) -> JAYLON TAYLOR | B8: 2WSL: Springfield | C8: 46296 | D8: JAYLON TAYLOR (122451) | E8: 46296.381 | F8: 46296.744 | G8: 8:42 | H8: 7:36 | I8: 1:6 | J8: 0:0 | K8: Y
A9: =TRIM(_xlfn.TEXTBEFORE(D9,"(")) -> RICCO CURRIE | B9: 2WSL: Springfield | C9: 46296 | D9: RICCO CURRIE (126768) | E9: 1 | F9: 1 | G9: 0:0 | H9: 0:0 | I9: 0:0 | J9: 0:0 | K9: Y
A10: =TRIM(_xlfn.TEXTBEFORE(D10,"(")) -> EMILY DRAZER | B10: 2WSL: Springfield | C10: 46296 | D10: EMILY DRAZER (121778) | E10: 46296.501 | F10: 46296.849 | G10: 8:22 | H10: 6:31 | I10: 1:51 | J10: 0:0 | K10: Y
A11: =TRIM(_xlfn.TEXTBEFORE(D11,"(")) -> ALYSIA MEFFORD | B11: 2WSF: Xenia | C11: 46296 | D11: ALYSIA MEFFORD (127863) | E11: 46296.492 | F11: 46296.844 | G11: 8:28 | H11: 7:58 | I11: 0:30 | J11: 0:0 | K11: Y
A12: =TRIM(_xlfn.TEXTBEFORE(D12,"(")) -> KYRA BOBBITT | B12: 2WSF: Xenia | C12: 46296 | D12: KYRA BOBBITT (128542) | E12: 1 | F12: 1 | G12: 0:0 | H12: 0:0 | I12: 0:0 | J12: 0:0 | K12: Y
A13: =TRIM(_xlfn.TEXTBEFORE(D13,"(")) -> CHRISTOPHER MEFFORD | B13: 2WSF: Xenia | C13: 46296 | D13: CHRISTOPHER MEFFORD (112574) | E13: 46296.392 | F13: 46296.719 | G13: 7:42 | H13: 5:12 | I13: 2:30 | J13: 0:9 | K13: Y
... A11449: =TRIM(_xlfn.TEXTBEFORE(D11449,"(")) -> SHANITA MOBIN | B11449: 0118: Eastchase | C11449: 46301 | D11449: SHANITA MOBIN (126151) | E11449: 1 | F11449: 1 | G11449: 0:0 | H11449: 0:0 | I11449: 0:0 | J11449: 0:0 | K11449: Y
A11450: =TRIM(_xlfn.TEXTBEFORE(D11450,"(")) -> #N/A
A11451: =TRIM(_xlfn.TEXTBEFORE(D11451,"(")) -> #N/A
A11452: =TRIM(_xlfn.TEXTBEFORE(D11452,"(")) -> JAIDYN SCHILLING | B11452: 4CSN: Hot Springs | C11452: 46302 | D11452: JAIDYN SCHILLING (115696) | E11452: 46302.418 | F11452: 46302.857 | G11452: 10:32 | H11452: 7:0 | I11452: 3:32 | J11452: 0:0 | K11452: Y
A11453: =TRIM(_xlfn.TEXTBEFORE(D11453,"(")) -> JENNA WHITTAMORE | B11453: 4CSN: Hot Springs | C11453: 46302 | D11453: JENNA WHITTAMORE (129738) | E11453: 46302.375 | F11453: 46302.661 | G11453: 6:51 | H11453: 5:6 | I11453: 1:45 | J11453: 0:0 | K11453: Y
A11454: =TRIM(_xlfn.TEXTBEFORE(D11454,"(")) -> SHELBI HALL | B11454: 4CSN: Hot Springs | C11454: 46302 | D11454: SHELBI HALL (129683) | E11454: 46302.43 | F11454: 46302.602 | G11454: 3:54 | H11454: 3:54 | I11454: 0:0 | J11454: 0:14 | K11454: Y
A11455: =TRIM(_xlfn.TEXTBEFORE(D11455,"(")) -> CAINON WILLIAMS | B11455: 4CSN: Hot Springs | C11455: 46302 | D11455: CAINON WILLIAMS (130246) | E11455: 46302.474 | F11455: 46302.857 | G11455: 9:10 | H11455: 8:19 | I11455: 0:51 | J11455: 0:0 | K11455: Y
A11456: =TRIM(_xlfn.TEXTBEFORE(D11456,"(")) -> KISHA MACON | B11456: 4CST: Little Rock | C11456: 46302 | D11456: KISHA MACON (130420) | E11456: 46302.5 | F11456: 46302.843 | G11456: 8:13 | H11456: 6:39 | I11456: 1:34 | J11456: 0:0 | K11456: Y
A11457: =TRIM(_xlfn.TEXTBEFORE(D11457,"(")) -> MARCUS ROBINSON | B11457: 4CST: Little Rock | C11457: 46302 | D11457: MARCUS ROBINSON (130456) | E11457: 46302.375 | F11457: 46302.567 | G11457: 3:56 | H11457: 3:47 | I11457: 0:9 | J11457: 0:40 | K11457: Y
A11458: =TRIM(_xlfn.TEXTBEFORE(D11458,"(")) -> DENNIS GARDNER | B11458: 4CST: Little Rock | C11458: 46302 | D11458: DENNIS GARDNER (121326) | E11458: 46302.402 | F11458: 46302.857 | G11458: 9:52 | H11458: 8:26 | I11458: 1:26 | J11458: 1:3 | K11458: Y
A11459: =TRIM(_xlfn.TEXTBEFORE(D11459,"(")) -> JESS DITTRICH | B11459: 4CST: Little Rock | C11459: 46302 | D11459: JESS DITTRICH (111747) | E11459: 46302.434 | F11459: 46302.65 | G11459: 4:23 | H11459: 2:5 | I11459: 2:18 | J11459: 0:48 | K11459: Y
A11460: =TRIM(_xlfn.TEXTBEFORE(D11460,"(")) -> TRACIE KYLE | B11460: 4CST: Little Rock | C11460: 46302 | D11460: TRACIE KYLE (126385) | E11460: 46302.375 | F11460: 46302.65 | G11460: 6:23 | H11460: 3:59 | I11460: 2:24 | J11460: 0:13 | K11460: Y
A11461: =TRIM(_xlfn.TEXTBEFORE(D11461,"(")) -> WILLIAM HILL | B11461: 4CSM: Pine Bluff | C11461: 46302 | D11461: WILLIAM HILL (120933) | E11461: 46302.383 | F11461: 46302.675 | G11461: 6:24 | H11461: 5:19 | I11461: 1:5 | J11461: 0:37 | K11461: Y
A11462: =TRIM(_xlfn.TEXTBEFORE(D11462,"(")) -> JESHELLE NIEVES | B11462: 4CSM: Pine Bluff | C11462: 46302 | D11462: JESHELLE NIEVES (130212) | E11462: 46302.395 | F11462: 46302.707 | G11462: 6:36 | H11462: 6:12 | I11462: 0:24 | J11462: 0:54 | K11462: Y
A11463: =TRIM(_xlfn.TEXTBEFORE(D11463,"(")) -> MICHELLE STUART | B11463: 4CSM: Pine Bluff | C11463: 46302 | D11463: MICHELLE STUART (129556) | E11463: 46302.418 | F11463: 46302.848 | G11463: 9:33 | H11463: 8:39 | I11463: 0:54 | J11463: 0:46 | K11463: Y
... A12642: =TRIM(_xlfn.TEXTBEFORE(D12642,"(")) -> SABRINA BARRIENTOS | B12642: 5441: South Bibb | C12642: 46302 | D12642: SABRINA BARRIENTOS (126245) | E12642: 46302.386 | F12642: 46302.583 | G12642: 4:44 | H12642: 4:5 | I12642: 0:39 | J12642: 0:0 | K12642: Y
